Workbook

Sheet Exe Sum
M3: DASHBOARD AREA
O5: McDonalds | AH5: All
P23: 2024

Sheet ChartData
C2: Revenue | I2: Gross Profit | O2: Sales
C3: 2024 | D3: 2023 | E3: 2022 | F3: 2021 | I3: {=C3:F3} -> 2024 | J3: 2023 | K3: 2022 | L3: 2021 | O3: {=_xlfn.ANCHORARRAY(I3)} -> 2024 | P3: 2023 | Q3: 2022 | R3: 2021
B4: Chipotle | C4: {='C24-21'!B4:E4} -> 11313.85 | D4: 9871.65 | E4: 8634.65 | F4: 7547.06 | H4: {=B4:B7} -> Chipotle | I4: =_xlfn.XLOOKUP($I$2,'C24-21'!$A$4:$A$70,'C24-21'!B4:B70)*1000000 -> 3017690000 | J4: =_xlfn.XLOOKUP($I$2,'C24-21'!$A$4:$A$70,'C24-21'!C4:C70)*1000000 -> 2586090000 | K4: =_xlfn.XLOOKUP($I$2,'C24-21'!$A$4:$A$70,'C24-21'!D4:D70)*1000000 -> 2062120000 | L4: =_xlfn.XLOOKUP($I$2,'C24-21'!$A$4:$A$70,'C24-21'!E4:E70)*1000000 -> 1707010000 | N4: {=_xlfn.ANCHORARRAY(H4)} -> Chipotle | O4: =IF('Exe Sum'!$AH$5="All",_xlfn.XLOOKUP($N$4,$B$4:$B$7,C4:C7),IF($N$4='Exe Sum'!$AH$5,_xlfn.XLOOKUP(ChartData!$N$4,ChartData!$B$4:$B$7,ChartData!C4:C7),NA())) -> 11313.85 | P4: =IF('Exe Sum'!$AH$5="All",_xlfn.XLOOKUP($N$4,$B$4:$B$7,D4:D7),IF($N$4='Exe Sum'!$AH$5,_xlfn.XLOOKUP(ChartData!$N$4,ChartData!$B$4:$B$7,ChartData!D4:D7),NA())) -> 9871.65 | Q4: =IF('Exe Sum'!$AH$5="All",_xlfn.XLOOKUP($N$4,$B$4:$B$7,E4:E7),IF($N$4='Exe Sum'!$AH$5,_xlfn.XLOOKUP(ChartData!$N$4,ChartData!$B$4:$B$7,ChartData!E4:E7),NA())) -> 8634.65 | R4: =IF('Exe Sum'!$AH$5="All",_xlfn.XLOOKUP($N$4,$B$4:$B$7,F4:F7),IF($N$4='Exe Sum'!$AH$5,_xlfn.XLOOKUP(ChartData!$N$4,ChartData!$B$4:$B$7,ChartData!F4:F7),NA())) -> 7547.06
B5: Shake Shack | C5: {='S24-21'!B4:E4} -> 1252.61 | D5: 1087.53 | E5: 900.49 | F5: 739.89 | H5: Shake Shack | I5: =_xlfn.XLOOKUP($I$2,'S24-21'!$A$4:$A$71,'S24-21'!B4:B71)*1000000 -> 302470000 | J5: =_xlfn.XLOOKUP($I$2,'S24-21'!$A$4:$A$71,'S24-21'!C4:C71)*1000000 -> 248940000 | K5: =_xlfn.XLOOKUP($I$2,'S24-21'!$A$4:$A$71,'S24-21'!D4:D71)*1000000 -> 183390000 | L5: =_xlfn.XLOOKUP($I$2,'S24-21'!$A$4:$A$71,'S24-21'!E4:E71)*1000000 -> 145260000 | N5: Shake Shack | O5: =IF('Exe Sum'!$AH$5="All",_xlfn.XLOOKUP(ChartData!$N$5,ChartData!$B$4:$B$7,ChartData!C4:C7),IF($N$5='Exe Sum'!$AH$5,_xlfn.XLOOKUP(ChartData!$N$5,ChartData!$B$4:$B$7,ChartData!C4:C7),NA())) -> 1252.61 | P5: =IF('Exe Sum'!$AH$5="All",_xlfn.XLOOKUP(ChartData!$N$5,ChartData!$B$4:$B$7,ChartData!D4:D7),IF($N$5='Exe Sum'!$AH$5,_xlfn.XLOOKUP(ChartData!$N$5,ChartData!$B$4:$B$7,ChartData!D4:D7),NA())) -> 1087.53 | Q5: =IF('Exe Sum'!$AH$5="All",_xlfn.XLOOKUP(ChartData!$N$5,ChartData!$B$4:$B$7,ChartData!E4:E7),IF($N$5='Exe Sum'!$AH$5,_xlfn.XLOOKUP(ChartData!$N$5,ChartData!$B$4:$B$7,ChartData!E4:E7),NA())) -> 900.49 | R5: =IF('Exe Sum'!$AH$5="All",_xlfn.XLOOKUP(ChartData!$N$5,ChartData!$B$4:$B$7,ChartData!F4:F7),IF($N$5='Exe Sum'!$AH$5,_xlfn.XLOOKUP(ChartData!$N$5,ChartData!$B$4:$B$7,ChartData!F4:F7),NA())) -> 739.89
B6: McDonalds | C6: {='M24-21'!B4:E4} -> 25920 | D6: 25494 | E6: 23183 | F6: 23222.9 | H6: McDonalds | I6: =_xlfn.XLOOKUP($I$2,'M24-21'!$A$4:$A$71,'M24-21'!B4:B71)*1000000 -> 14710000000 | J6: =_xlfn.XLOOKUP($I$2,'M24-21'!$A$4:$A$71,'M24-21'!C4:C71)*1000000 -> 14563000000 | K6: =_xlfn.XLOOKUP($I$2,'M24-21'!$A$4:$A$71,'M24-21'!D4:D71)*1000000 -> 13208000000 | L6: =_xlfn.XLOOKUP($I$2,'M24-21'!$A$4:$A$71,'M24-21'!E4:E71)*1000000 -> 12580200000 | N6: McDonalds | O6: =IF('Exe Sum'!$AH$5="All",_xlfn.XLOOKUP(ChartData!$N$6,ChartData!$B$4:$B$7,ChartData!C4:C7),IF($N$6='Exe Sum'!$AH$5,_xlfn.XLOOKUP(ChartData!$N$6,ChartData!$B$4:$B$7,ChartData!C4:C7),NA())) -> 25920 | P6: =IF('Exe Sum'!$AH$5="All",_xlfn.XLOOKUP(ChartData!$N$6,ChartData!$B$4:$B$7,ChartData!D4:D7),IF($N$6='Exe Sum'!$AH$5,_xlfn.XLOOKUP(ChartData!$N$6,ChartData!$B$4:$B$7,ChartData!D4:D7),NA())) -> 25494 | Q6: =IF('Exe Sum'!$AH$5="All",_xlfn.XLOOKUP(ChartData!$N$6,ChartData!$B$4:$B$7,ChartData!E4:E7),IF($N$6='Exe Sum'!$AH$5,_xlfn.XLOOKUP(ChartData!$N$6,ChartData!$B$4:$B$7,ChartData!E4:E7),NA())) -> 23183 | R6: =IF('Exe Sum'!$AH$5="All",_xlfn.XLOOKUP(ChartData!$N$6,ChartData!$B$4:$B$7,ChartData!F4:F7),IF($N$6='Exe Sum'!$AH$5,_xlfn.XLOOKUP(ChartData!$N$6,ChartData!$B$4:$B$7,ChartData!F4:F7),NA())) -> 23222.9
B7: Yum | C7: {='Y24-21'!B4:E4} -> 7549 | D7: 7076 | E7: 6842 | F7: 6584 | H7: Yum | I7: =_xlfn.XLOOKUP($I$2,'Y24-21'!$A$4:$A$72,'Y24-21'!B4:B72)*1000000 -> 5429000000 | J7: =_xlfn.XLOOKUP($I$2,'Y24-21'!$A$4:$A$72,'Y24-21'!C4:C72)*1000000 -> 5302000000 | K7: =_xlfn.XLOOKUP($I$2,'Y24-21'!$A$4:$A$72,'Y24-21'!D4:D72)*1000000 -> 5097000000 | L7: =_xlfn.XLOOKUP($I$2,'Y24-21'!$A$4:$A$72,'Y24-21'!E4:E72)*1000000 -> 4859000000 | N7: Yum | O7: =IF('Exe Sum'!$AH$5="All",_xlfn.XLOOKUP(ChartData!$N$7,ChartData!$B$4:$B$7,ChartData!C4:C7),IF($N$7='Exe Sum'!$AH$5,_xlfn.XLOOKUP(ChartData!$N$7,ChartData!$B$4:$B$7,ChartData!C4:C7),NA())) -> 7549 | P7: =IF('Exe Sum'!$AH$5="All",_xlfn.XLOOKUP(ChartData!$N$7,ChartData!$B$4:$B$7,ChartData!D4:D7),IF($N$7='Exe Sum'!$AH$5,_xlfn.XLOOKUP(ChartData!$N$7,ChartData!$B$4:$B$7,ChartData!D4:D7),NA())) -> 7076 | Q7: =IF('Exe Sum'!$AH$5="All",_xlfn.XLOOKUP(ChartData!$N$7,ChartData!$B$4:$B$7,ChartData!E4:E7),IF($N$7='Exe Sum'!$AH$5,_xlfn.XLOOKUP(ChartData!$N$7,ChartData!$B$4:$B$7,ChartData!E4:E7),NA())) -> 6842 | R7: =IF('Exe Sum'!$AH$5="All",_xlfn.XLOOKUP(ChartData!$N$7,ChartData!$B$4:$B$7,ChartData!F4:F7),IF($N$7='Exe Sum'!$AH$5,_xlfn.XLOOKUP(ChartData!$N$7,ChartData!$B$4:$B$7,ChartData!F4:F7),NA())) -> 6584
B8: All
C9: Revenue | I9: EPS | O9: Gross Profit
C10: {=C3:F3} -> 2024 | D10: 2023 | E10: 2022 | F10: 2021 | I10: {=_xlfn.ANCHORARRAY(I3)} -> 2024 | J10: 2023 | K10: 2022 | L10: 2021 | O10: YOY % Change 2024 2023 | P10: YOY % Change 2023 2022 | Q10: YOY % Change 2022 2021
B11: ='Exe Sum'!O5 -> McDonalds | C11: =_xlfn.XLOOKUP($B$11,$B$4:$B$7,C4:C7) -> 25920 | D11: =_xlfn.XLOOKUP($B$11,$B$4:$B$7,D4:D7) -> 25494 | E11: =_xlfn.XLOOKUP($B$11,$B$4:$B$7,E4:E7) -> 23183 | F11: =_xlfn.XLOOKUP($B$11,$B$4:$B$7,F4:F7) -> 23222.9 | H11: {=_xlfn.ANCHORARRAY(H4)} -> Chipotle | I11: =_xlfn.XLOOKUP(ChartData!$I$9,'YOY CMG'!$A$22:$A$44,'YOY CMG'!C22:C44) -> 1.1211468 | J11: =_xlfn.XLOOKUP(ChartData!$I$9,'YOY CMG'!$A$22:$A$44,'YOY CMG'!D22:D44) -> 0.89183245 | K11: =_xlfn.XLOOKUP(ChartData!$I$9,'YOY CMG'!$A$22:$A$44,'YOY CMG'!F22:F44) -> 0.6456547 | L11: =_xlfn.XLOOKUP(ChartData!$I$9,'YOY CMG'!$A$22:$A$44,'YOY CMG'!H22:H44) -> 0.46422579 | N11: {=_xlfn.ANCHORARRAY(N4)} -> Chipotle | O11: =IF('Exe Sum'!$AH$5="All",_xlfn.XLOOKUP($O$9,'YOY CMG'!$A$3:$A$19,'YOY CMG'!$E$3:$E$19),IF('Exe Sum'!$AH$5=ChartData!$N$11,_xlfn.XLOOKUP($O$9,'YOY CMG'!$A$3:$A$19,'YOY CMG'!$E$3:$E$19),NA())) -> 0.16689288 | P11: =IF('Exe Sum'!$AH$5="All",_xlfn.XLOOKUP($O$9,'YOY CMG'!$A$3:$A$19,'YOY CMG'!$G$3:$G$19),IF('Exe Sum'!$AH$5=ChartData!$N$11,_xlfn.XLOOKUP($O$9,'YOY CMG'!$A$3:$A$19,'YOY CMG'!$G$3:$G$19),NA())) -> 0.25409288 | Q11: =IF('Exe Sum'!$AH$5="All",_xlfn.XLOOKUP($O$9,'YOY CMG'!$A$3:$A$19,'YOY CMG'!$I$3:$I$19),IF('Exe Sum'!$AH$5=ChartData!$N$11,_xlfn.XLOOKUP($O$9,'YOY CMG'!$A$3:$A$19,'YOY CMG'!$I$3:$I$19),NA())) -> 0.20803042
H12: Shake Shack | I12: =_xlfn.XLOOKUP($I$9,'YOY SHAK'!$A$22:$A$44,'YOY SHAK'!C22:C44) -> 0.25633944 | J12: =_xlfn.XLOOKUP($I$9,'YOY SHAK'!$A$22:$A$44,'YOY SHAK'!D22:D44) -> 0.51395231 | K12: =_xlfn.XLOOKUP($I$9,'YOY SHAK'!$A$22:$A$44,'YOY SHAK'!F22:F44) -> -0.54102956 | L12: =_xlfn.XLOOKUP($I$9,'YOY SHAK'!$A$22:$A$44,'YOY SHAK'!H22:H44) -> -0.11665388 | N12: Shake Shack | O12: =IF('Exe Sum'!$AH$5="All",_xlfn.XLOOKUP($O$9,'YOY SHAK'!$A$3:$A$19,'YOY SHAK'!$E$3:$E$19),IF('Exe Sum'!$AH$5=$N$12,_xlfn.XLOOKUP($O$9,'YOY SHAK'!$A$3:$A$19,'YOY SHAK'!$E$3:$E$19),NA())) -> 0.21503173 | P12: =IF('Exe Sum'!$AH$5="All",_xlfn.XLOOKUP($O$9,'YOY SHAK'!$A$3:$A$19,'YOY SHAK'!$G$3:$G$19),IF('Exe Sum'!$AH$5=$N$12,_xlfn.XLOOKUP($O$9,'YOY SHAK'!$A$3:$A$19,'YOY SHAK'!$G$3:$G$19),NA())) -> 0.35743497 | Q12: =IF('Exe Sum'!$AH$5="All",_xlfn.XLOOKUP($O$9,'YOY SHAK'!$A$3:$A$19,'YOY SHAK'!$I$3:$I$19),IF('Exe Sum'!$AH$5=$N$12,_xlfn.XLOOKUP($O$9,'YOY SHAK'!$A$3:$A$19,'YOY SHAK'!$I$3:$I$19),NA())) -> 0.26249484
C13: Net Income | H13: McDonalds | I13: =_xlfn.XLOOKUP($I$9,'YOY MCD'!$A$22:$A$44,'YOY MCD'!C22:C44) -> 11.447863 | J13: =_xlfn.XLOOKUP($I$9,'YOY MCD'!$A$22:$A$44,'YOY MCD'!D22:D44) -> 11.63484 | K13: =_xlfn.XLOOKUP($I$9,'YOY MCD'!$A$22:$A$44,'YOY MCD'!F22:F44) -> 8.3869654 | L13: =_xlfn.XLOOKUP($I$9,'YOY MCD'!$A$22:$A$44,'YOY MCD'!H22:H44) -> 10.110143 | N13: McDonalds | O13: =IF('Exe Sum'!$AH$5="All",_xlfn.XLOOKUP(ChartData!$O$9,'YOY MCD'!$A$3:$A$19,'YOY MCD'!$E$3:$E$19),IF('Exe Sum'!$AH$5=$N$13,_xlfn.XLOOKUP(ChartData!$O$9,'YOY MCD'!$A$3:$A$19,'YOY MCD'!$E$3:$E$19),NA())) -> 0.010094074 | P13: =IF('Exe Sum'!$AH$5="All",_xlfn.XLOOKUP(ChartData!$O$9,'YOY MCD'!$A$3:$A$19,'YOY MCD'!$G$3:$G$19),IF('Exe Sum'!$AH$5=$N$13,_xlfn.XLOOKUP(ChartData!$O$9,'YOY MCD'!$A$3:$A$19,'YOY MCD'!$G$3:$G$19),NA())) -> 0.10258934 | Q13: =IF('Exe Sum'!$AH$5="All",_xlfn.XLOOKUP(ChartData!$O$9,'YOY MCD'!$A$3:$A$19,'YOY MCD'!$I$3:$I$19),IF('Exe Sum'!$AH$5=$N$13,_xlfn.XLOOKUP(ChartData!$O$9,'YOY MCD'!$A$3:$A$19,'YOY MCD'!$I$3:$I$19),NA())) -> 0.049903817
C14: {=_xlfn.ANCHORARRAY(C10)} -> 2024 | D14: 2023 | E14: 2022 | F14: 2021 | H14: Yum | I14: =_xlfn.XLOOKUP($I$9,'YOY Yum'!$A$22:$A$44,'YOY Yum'!C22:C44) -> 5.2695035 | J14: =_xlfn.XLOOKUP($I$9,'YOY Yum'!$A$22:$A$44,'YOY Yum'!D22:D44) -> 5.683274 | K14: =_xlfn.XLOOKUP($I$9,'YOY Yum'!$A$22:$A$44,'YOY Yum'!F22:F44) -> 4.6328671 | L14: =_xlfn.XLOOKUP($I$9,'YOY Yum'!$A$22:$A$44,'YOY Yum'!H22:H44) -> 5.3030303 | N14: Yum | O14: =IF('Exe Sum'!$AH$5="All",_xlfn.XLOOKUP($O$9,'YOY Yum'!$A$3:$A$19,'YOY Yum'!$E$3:$E$19),IF('Exe Sum'!$AH$5=$N$14,_xlfn.XLOOKUP($O$9,'YOY CMG'!$A$3:$A$19,'YOY CMG'!$E$3:$E$19),NA())) -> 0.023953225 | P14: =IF('Exe Sum'!$AH$5="All",_xlfn.XLOOKUP($O$9,'YOY Yum'!$A$3:$A$19,'YOY Yum'!$G$3:$G$19),IF('Exe Sum'!AH5=N14,_xlfn.XLOOKUP($O$9,'YOY Yum'!$A$3:$A$19,'YOY Yum'!$G$3:$G$19),NA())) -> 0.040219737 | Q14: =IF('Exe Sum'!$AH$5="All",_xlfn.XLOOKUP($O$9,'YOY Yum'!$A$3:$A$19,'YOY Yum'!$I$3:$I$19),IF('Exe Sum'!AH5=N14,_xlfn.XLOOKUP($O$9,'YOY Yum'!$A$3:$A$19,'YOY Yum'!$I$3:$I$19),NA())) -> 0.048981272
B15: {=B4:B7} -> Chipotle | C15: {='C24-21'!B15:E15} -> 1534.11 | D15: 1228.74 | E15: 899.1 | F15: 652.98
B16: Shake Shack | C16: {='S24-21'!B18:E18} -> 10.21 | D16: 20.26 | E16: -21.23 | F16: -4.56 | I16: EPS
B17: McDonalds | C17: {='M24-21'!B17:E17} -> 8223 | D17: 8469 | E17: 6177 | F17: 7545.2 | I17: {=_xlfn.ANCHORARRAY(I10)} -> 2024 | J17: 2023 | K17: 2022 | L17: 2021
B18: Yum | C18: {='Y24-21'!B17:E17} -> 1486 | D18: 1597 | E18: 1325 | F18: 1575 | H18: {=_xlfn.ANCHORARRAY(H11)} -> Chipotle | I18: =IF('Exe Sum'!$AH$5="All",_xlfn.XLOOKUP($H$18,$H$11:$H$14,I11:I14),IF($H$18='Exe Sum'!$AH$5,_xlfn.XLOOKUP('Exe Sum'!$AH$5,ChartData!$H$11:$H$14,ChartData!I11:I14),NA())) -> 1.1211468 | J18: =IF('Exe Sum'!$AH$5="All",_xlfn.XLOOKUP($H$18,$H$11:$H$14,J11:J14),IF($H$18='Exe Sum'!$AH$5,_xlfn.XLOOKUP('Exe Sum'!$AH$5,ChartData!$H$11:$H$14,ChartData!J11:J14),NA())) -> 0.89183245 | K18: =IF('Exe Sum'!$AH$5="All",_xlfn.XLOOKUP($H$18,$H$11:$H$14,K11:K14),IF($H$18='Exe Sum'!$AH$5,_xlfn.XLOOKUP('Exe Sum'!$AH$5,ChartData!$H$11:$H$14,ChartData!K11:K14),NA())) -> 0.6456547 | L18: =IF('Exe Sum'!$AH$5="All",_xlfn.XLOOKUP($H$18,$H$11:$H$14,L11:L14),IF($H$18='Exe Sum'!$AH$5,_xlfn.XLOOKUP('Exe Sum'!$AH$5,ChartData!$H$11:$H$14,ChartData!L11:L14),NA())) -> 0.46422579
H19: Shake Shack | I19: {=IF('Exe Sum'!$AH$5="All",_xlfn.XLOOKUP(ChartData!$H$19,ChartData!$H$11:$H$14,ChartData!I11:I14),IF($H$19='Exe Sum'!$AH$5,_xlfn.XLOOKUP('Exe Sum'!$AH$5,_xlfn.ANCHORARRAY(ChartData!$H$11),ChartData!I11:I14),NA()))} -> 0.25633944 | J19: {=IF('Exe Sum'!$AH$5="All",_xlfn.XLOOKUP(ChartData!$H$19,ChartData!$H$11:$H$14,ChartData!J11:J14),IF($H$19='Exe Sum'!$AH$5,_xlfn.XLOOKUP('Exe Sum'!$AH$5,_xlfn.ANCHORARRAY(ChartData!$H$11),ChartData!J11:J14),NA()))} -> 0.51395231 | K19: {=IF('Exe Sum'!$AH$5="All",_xlfn.XLOOKUP(ChartData!$H$19,ChartData!$H$11:$H$14,ChartData!K11:K14),IF($H$19='Exe Sum'!$AH$5,_xlfn.XLOOKUP('Exe Sum'!$AH$5,_xlfn.ANCHORARRAY(ChartData!$H$11),ChartData!K11:K14),NA()))} -> -0.54102956 | L19: {=IF('Exe Sum'!$AH$5="All",_xlfn.XLOOKUP(ChartData!$H$19,ChartData!$H$11:$H$14,ChartData!L11:L14),IF($H$19='Exe Sum'!$AH$5,_xlfn.XLOOKUP('Exe Sum'!$AH$5,_xlfn.ANCHORARRAY(ChartData!$H$11),ChartData!L11:L14),NA()))} -> -0.11665388
C20: Net Income | H20: McDonalds | I20: {=IF('Exe Sum'!$AH$5="All",_xlfn.XLOOKUP(ChartData!$H$20,ChartData!$H$11:$H$14,ChartData!I11:I14),IF($H$20='Exe Sum'!$AH$5,_xlfn.XLOOKUP('Exe Sum'!$AH$5,_xlfn.ANCHORARRAY(ChartData!$H$11),ChartData!I11:I14),NA()))} -> 11.447863 | J20: {=IF('Exe Sum'!$AH$5="All",_xlfn.XLOOKUP(ChartData!$H$20,ChartData!$H$11:$H$14,ChartData!J11:J14),IF($H$20='Exe Sum'!$AH$5,_xlfn.XLOOKUP('Exe Sum'!$AH$5,_xlfn.ANCHORARRAY(ChartData!$H$11),ChartData!J11:J14),NA()))} -> 11.63484 | K20: {=IF('Exe Sum'!$AH$5="All",_xlfn.XLOOKUP(ChartData!$H$20,ChartData!$H$11:$H$14,ChartData!K11:K14),IF($H$20='Exe Sum'!$AH$5,_xlfn.XLOOKUP('Exe Sum'!$AH$5,_xlfn.ANCHORARRAY(ChartData!$H$11),ChartData!K11:K14),NA()))} -> 8.3869654 | L20: {=IF('Exe Sum'!$AH$5="All",_xlfn.XLOOKUP(ChartData!$H$20,ChartData!$H$11:$H$14,ChartData!L11:L14),IF($H$20='Exe Sum'!$AH$5,_xlfn.XLOOKUP('Exe Sum'!$AH$5,_xlfn.ANCHORARRAY(ChartData!$H$11),ChartData!L11:L14),NA()))} -> 10.110143
C21: {=_xlfn.ANCHORARRAY(C14)} -> 2024 | D21: 2023 | E21: 2022 | F21: 2021 | H21: Yum | I21: {=IF('Exe Sum'!$AH$5="All",_xlfn.XLOOKUP(ChartData!$H$21,ChartData!$H$11:$H$14,ChartData!I11:I14),IF($H$21='Exe Sum'!$AH$5,_xlfn.XLOOKUP('Exe Sum'!$AH$5,_xlfn.ANCHORARRAY(ChartData!$H$11),ChartData!I11:I14),NA()))} -> 5.2695035 | J21: {=IF('Exe Sum'!$AH$5="All",_xlfn.XLOOKUP(ChartData!$H$21,ChartData!$H$11:$H$14,ChartData!J11:J14),IF($H$21='Exe Sum'!$AH$5,_xlfn.XLOOKUP('Exe Sum'!$AH$5,_xlfn.ANCHORARRAY(ChartData!$H$11),ChartData!J11:J14),NA()))} -> 5.683274 | K21: {=IF('Exe Sum'!$AH$5="All",_xlfn.XLOOKUP(ChartData!$H$21,ChartData!$H$11:$H$14,ChartData!K11:K14),IF($H$21='Exe Sum'!$AH$5,_xlfn.XLOOKUP('Exe Sum'!$AH$5,_xlfn.ANCHORARRAY(ChartData!$H$11),ChartData!K11:K14),NA()))} -> 4.6328671 | L21: {=IF('Exe Sum'!$AH$5="All",_xlfn.XLOOKUP(ChartData!$H$21,ChartData!$H$11:$H$14,ChartData!L11:L14),IF($H$21='Exe Sum'!$AH$5,_xlfn.XLOOKUP('Exe Sum'!$AH$5,_xlfn.ANCHORARRAY(ChartData!$H$11),ChartData!L11:L14),NA()))} -> 5.3030303
B22: ='Exe Sum'!O5 -> McDonalds | C22: =_xlfn.XLOOKUP($B$22,$B$15:$B$18,C15:C18) -> 8223 | D22: =_xlfn.XLOOKUP($B$22,$B$15:$B$18,D15:D18) -> 8469 | E22: =_xlfn.XLOOKUP($B$22,$B$15:$B$18,E15:E18) -> 6177 | F22: =_xlfn.XLOOKUP($B$22,$B$15:$B$18,F15:F18) -> 7545.2
I23: P/E
C24: Net Profit Margin | I24: {=_xlfn.ANCHORARRAY(I17)} -> 2024 | J24: 2023 | K24: 2022 | L24: 2021
C25: {=_xlfn.ANCHORARRAY(C21)} -> 2024 | D25: 2023 | E25: 2022 | F25: 2021 | H25: {=_xlfn.ANCHORARRAY(H18)} -> Chipotle | I25: =_xlfn.XLOOKUP($I$23,'YOY CMG'!$A$22:$A$44,'YOY CMG'!C22:C44) -> 53.596907 | J25: =_xlfn.XLOOKUP($I$23,'YOY CMG'!$A$22:$A$44,'YOY CMG'!D22:D44) -> 51.28766 | K25: =_xlfn.XLOOKUP($I$23,'YOY CMG'!$A$22:$A$44,'YOY CMG'!F22:F44) -> 42.97963 | L25: =_xlfn.XLOOKUP($I$23,'YOY CMG'!$A$22:$A$44,'YOY CMG'!H22:H44) -> 75.265098
B26: {=_xlfn.ANCHORARRAY(B15)} -> Chipotle | C26: {='C24-21'!B23:E23} -> 0.1356 | D26: 0.1245 | E26: 0.1041 | F26: 0.0865 | H26: Shake Shack | I26: =_xlfn.XLOOKUP($I$23,'YOY SHAK'!$A$22:$A$44,'YOY SHAK'!C22:C44) -> 505.22853 | J26: =_xlfn.XLOOKUP($I$23,'YOY SHAK'!$A$22:$A$44,'YOY SHAK'!D22:D44) -> 144.21572 | K26: =_xlfn.XLOOKUP($I$23,'YOY SHAK'!$A$22:$A$44,'YOY SHAK'!F22:F44) -> -76.761055 | L26: =_xlfn.XLOOKUP($I$23,'YOY SHAK'!$A$22:$A$44,'YOY SHAK'!H22:H44) -> -626.38296
B27: Shake Shack | C27: {='S24-21'!B26:E26} -> 0.0081 | D27: 0.0186 | E27: -0.0236 | F27: -0.0062 | H27: McDonalds | I27: =_xlfn.XLOOKUP($I$23,'YOY MCD'!$A$22:$A$44,'YOY MCD'!C22:C44) -> 25.297298 | J27: =_xlfn.XLOOKUP($I$23,'YOY MCD'!$A$22:$A$44,'YOY MCD'!D22:D44) -> 25.484665 | K27: =_xlfn.XLOOKUP($I$23,'YOY MCD'!$A$22:$A$44,'YOY MCD'!F22:F44) -> 31.421377 | L27: =_xlfn.XLOOKUP($I$23,'YOY MCD'!$A$22:$A$44,'YOY MCD'!H22:H44) -> 26.429892
B28: McDonalds | C28: {='M24-21'!B25:E25} -> 0.3172 | D28: 0.3322 | E28: 0.2664 | F28: 0.3249 | H28: Yum | I28: =_xlfn.XLOOKUP($I$23,'YOY Yum'!$A$22:$A$44,'YOY Yum'!C22:C44) -> 25.33825 | J28: =_xlfn.XLOOKUP($I$23,'YOY Yum'!$A$22:$A$44,'YOY Yum'!D22:D44) -> 22.990269 | K28: =_xlfn.XLOOKUP($I$23,'YOY Yum'!$A$22:$A$44,'YOY Yum'!F22:F44) -> 27.645947 | L28: =_xlfn.XLOOKUP($I$23,'YOY Yum'!$A$22:$A$44,'YOY Yum'!H22:H44) -> 26.0964
B29: Yum | C29: {='Y24-21'!B25:E25} -> 0.1968 | D29: 0.2257 | E29: 0.1937 | F29: 0.2392
I30: P/E
C31: Net Profit Margin | I31: {=_xlfn.ANCHORARRAY(I24)} -> 2024 | J31: 2023 | K31: 2022 | L31: 2021
C32: {=_xlfn.ANCHORARRAY(C25)} -> 2024 | D32: 2023 | E32: 2022 | F32: 2021 | H32: {=_xlfn.ANCHORARRAY(H25)} -> Chipotle | I32: =IF('Exe Sum'!$P$23=ChartData!$I$31,_xlfn.XLOOKUP(ChartData!H32,ChartData!$H$25:$H$28,ChartData!$I$25:$I$28),NA()) -> 53.596907 | J32: {=IF($J$31='Exe Sum'!$P$23,_xlfn.XLOOKUP(ChartData!H32,_xlfn.ANCHORARRAY(ChartData!$H$25),ChartData!$J$25:$J$28),NA())} -> #N/A | K32: {=IF($K$31='Exe Sum'!$P$23,_xlfn.XLOOKUP(ChartData!H32,_xlfn.ANCHORARRAY(ChartData!$H$25),ChartData!$K$25:$K$28),NA())} -> #N/A | L32: {=IF($L$31='Exe Sum'!$P$23,_xlfn.XLOOKUP(ChartData!H32,_xlfn.ANCHORARRAY(ChartData!$H$25),ChartData!$L$25:$L$28),NA())} -> #N/A
B33: ='Exe Sum'!O5 -> McDonalds | C33: {=_xlfn.XLOOKUP($B$33,_xlfn.ANCHORARRAY($B$26),C26:C29)} -> 0.3172 | D33: {=_xlfn.XLOOKUP($B$33,_xlfn.ANCHORARRAY($B$26),D26:D29)} -> 0.3322 | E33: {=_xlfn.XLOOKUP($B$33,_xlfn.ANCHORARRAY($B$26),E26:E29)} -> 0.2664 | F33: {=_xlfn.XLOOKUP($B$33,_xlfn.ANCHORARRAY($B$26),F26:F29)} -> 0.3249 | H33: Shake Shack | I33: =IF('Exe Sum'!$P$23=ChartData!$I$31,_xlfn.XLOOKUP(ChartData!H33,ChartData!$H$25:$H$28,ChartData!$I$25:$I$28),NA()) -> 505.22853 | J33: {=IF($J$31='Exe Sum'!$P$23,_xlfn.XLOOKUP(ChartData!H33,_xlfn.ANCHORARRAY(ChartData!$H$25),ChartData!$J$25:$J$28),NA())} -> #N/A | K33: {=IF($K$31='Exe Sum'!$P$23,_xlfn.XLOOKUP(ChartData!H33,_xlfn.ANCHORARRAY(ChartData!$H$25),ChartData!$K$25:$K$28),NA())} -> #N/A | L33: {=IF($L$31='Exe Sum'!$P$23,_xlfn.XLOOKUP(ChartData!H33,_xlfn.ANCHORARRAY(ChartData!$H$25),ChartData!$L$25:$L$28),NA())} -> #N/A
H34: McDonalds | I34: =IF('Exe Sum'!$P$23=ChartData!$I$31,_xlfn.XLOOKUP(ChartData!H34,ChartData!$H$25:$H$28,ChartData!$I$25:$I$28),NA()) -> 25.297298 | J34: {=IF($J$31='Exe Sum'!$P$23,_xlfn.XLOOKUP(ChartData!H34,_xlfn.ANCHORARRAY(ChartData!$H$25),ChartData!$J$25:$J$28),NA())} -> #N/A | K34: {=IF($K$31='Exe Sum'!$P$23,_xlfn.XLOOKUP(ChartData!H34,_xlfn.ANCHORARRAY(ChartData!$H$25),ChartData!$K$25:$K$28),NA())} -> #N/A | L34: {=IF($L$31='Exe Sum'!$P$23,_xlfn.XLOOKUP(ChartData!H34,_xlfn.ANCHORARRAY(ChartData!$H$25),ChartData!$L$25:$L$28),NA())} -> #N/A
H35: Yum | I35: =IF('Exe Sum'!$P$23=ChartData!$I$31,_xlfn.XLOOKUP(ChartData!H35,ChartData!$H$25:$H$28,ChartData!$I$25:$I$28),NA()) -> 25.33825 | J35: {=IF($J$31='Exe Sum'!$P$23,_xlfn.XLOOKUP(ChartData!H35,_xlfn.ANCHORARRAY(ChartData!$H$25),ChartData!$J$25:$J$28),NA())} -> #N/A | K35: {=IF($K$31='Exe Sum'!$P$23,_xlfn.XLOOKUP(ChartData!H35,_xlfn.ANCHORARRAY(ChartData!$H$25),ChartData!$K$25:$K$28),NA())} -> #N/A | L35: {=IF($L$31='Exe Sum'!$P$23,_xlfn.XLOOKUP(ChartData!H35,_xlfn.ANCHORARRAY(ChartData!$H$25),ChartData!$L$25:$L$28),NA())} -> #N/A

Sheet MEMO

Sheet Industry
A1: Industry Analysis 2024
A2: Company Name | B2: CMG | C2: SHAK | D2: MCD | E2: YUM | F2: Industry
A3: *Numbers in Millions | B3: 2024 | C3: 2024 | D3: 2024 | E3: 2024 | F3: Average
A4: Stock Price | B4: =_xlfn.XLOOKUP(A4,'YOY CMG'!$A$3:$A$44,'YOY CMG'!$C$3:$C$44) -> 60.09 | C4: =_xlfn.XLOOKUP(A4,'YOY SHAK'!$A$3:$A$44,'YOY SHAK'!$C$3:$C$44) -> 129.51 | D4: =_xlfn.XLOOKUP(A4,'YOY MCD'!$A$3:$A$44,'YOY MCD'!$C$3:$C$44) -> 289.6 | E4: =_xlfn.XLOOKUP(A4,'YOY Yum'!$A$3:$A$44,'YOY Yum'!$C$3:$C$44) -> 133.52 | F4: =AVERAGE(B4:E4) -> 153.18
A5: Revenue | B5: =_xlfn.XLOOKUP(A5,'YOY CMG'!$A$3:$A$44,'YOY CMG'!$C$3:$C$44) -> 11313.85 | C5: =_xlfn.XLOOKUP(A5,'YOY SHAK'!$A$3:$A$44,'YOY SHAK'!$C$3:$C$44) -> 1252.61 | D5: =_xlfn.XLOOKUP(A5,'YOY MCD'!$A$3:$A$44,'YOY MCD'!$C$3:$C$44) -> 25920 | E5: =_xlfn.XLOOKUP(A5,'YOY Yum'!$A$3:$A$44,'YOY Yum'!$C$3:$C$44) -> 7549 | F5: =AVERAGE(B5:E5) -> 11508.865
A6: Cost of Revenue | B6: =_xlfn.XLOOKUP(A6,'YOY CMG'!$A$3:$A$44,'YOY CMG'!$C$3:$C$44) -> 8296.16 | C6: =_xlfn.XLOOKUP(A6,'YOY SHAK'!$A$3:$A$44,'YOY SHAK'!$C$3:$C$44) -> 950.14 | D6: =_xlfn.XLOOKUP(A6,'YOY MCD'!$A$3:$A$44,'YOY MCD'!$C$3:$C$44) -> 11210 | E6: =_xlfn.XLOOKUP(A6,'YOY Yum'!$A$3:$A$44,'YOY Yum'!$C$3:$C$44) -> 2120 | F6: =AVERAGE(B6:E6) -> 5644.075
A7: Gross Profit | B7: =_xlfn.XLOOKUP(A7,'YOY CMG'!$A$3:$A$44,'YOY CMG'!$C$3:$C$44) -> 3017.69 | C7: =_xlfn.XLOOKUP(A7,'YOY SHAK'!$A$3:$A$44,'YOY SHAK'!$C$3:$C$44) -> 302.47 | D7: =_xlfn.XLOOKUP(A7,'YOY MCD'!$A$3:$A$44,'YOY MCD'!$C$3:$C$44) -> 14710 | E7: =_xlfn.XLOOKUP(A7,'YOY Yum'!$A$3:$A$44,'YOY Yum'!$C$3:$C$44) -> 5429 | F7: =AVERAGE(B7:E7) -> 5864.79
A8: SG&A Expenses | B8: =_xlfn.XLOOKUP(A8,'YOY CMG'!$A$3:$A$44,'YOY CMG'!$C$3:$C$44) -> 697.48 | C8: =_xlfn.XLOOKUP(A8,'YOY SHAK'!$A$3:$A$44,'YOY SHAK'!$C$3:$C$44) -> 149.05 | D8: =_xlfn.XLOOKUP(A8,'YOY MCD'!$A$3:$A$44,'YOY MCD'!$C$3:$C$44) -> 2412 | E8: =_xlfn.XLOOKUP(A8,'YOY Yum'!$A$3:$A$44,'YOY Yum'!$C$3:$C$44) -> 2892 | F8: =AVERAGE(B8:E8) -> 1537.6325
A9: Operating Income | B9: =_xlfn.XLOOKUP(A9,'YOY CMG'!$A$3:$A$44,'YOY CMG'!$C$3:$C$44) -> 1916.33 | C9: =_xlfn.XLOOKUP(A9,'YOY SHAK'!$A$3:$A$44,'YOY SHAK'!$C$3:$C$44) -> 3.04 | D9: =_xlfn.XLOOKUP(A9,'YOY MCD'!$A$3:$A$44,'YOY MCD'!$C$3:$C$44) -> 11712 | E9: =_xlfn.XLOOKUP(A9,'YOY Yum'!$A$3:$A$44,'YOY Yum'!$C$3:$C$44) -> 2403 | F9: =AVERAGE(B9:E9) -> 4008.5925
A10: Net Income Common | B10: =_xlfn.XLOOKUP(A10,'YOY CMG'!$A$3:$A$44,'YOY CMG'!$C$3:$C$44) -> 1534.11 | C10: =_xlfn.XLOOKUP(A10,'YOY SHAK'!$A$3:$A$44,'YOY SHAK'!$C$3:$C$44) -> 10.21 | D10: =_xlfn.XLOOKUP(A10,'YOY MCD'!$A$3:$A$44,'YOY MCD'!$C$3:$C$44) -> 8223 | E10: =_xlfn.XLOOKUP(A10,'YOY Yum'!$A$3:$A$44,'YOY Yum'!$C$3:$C$44) -> 1486 | F10: =AVERAGE(B10:E10) -> 2813.33
A11: Cash and Short Term Investments | B11: =_xlfn.XLOOKUP(A11,'YOY CMG'!$A$3:$A$44,'YOY CMG'!$C$3:$C$44) -> 1422.91 | C11: =_xlfn.XLOOKUP(A11,'YOY SHAK'!$A$3:$A$44,'YOY SHAK'!$C$3:$C$44) -> 320.71 | D11: =_xlfn.XLOOKUP(A11,'YOY MCD'!$A$3:$A$44,'YOY MCD'!$C$3:$C$44) -> 1085 | E11: =_xlfn.XLOOKUP(A11,'YOY Yum'!$A$3:$A$44,'YOY Yum'!$C$3:$C$44) -> 616 | F11: =AVERAGE(B11:E11) -> 861.155
A12: Receivables | B12: =_xlfn.XLOOKUP(A12,'YOY CMG'!$A$3:$A$44,'YOY CMG'!$C$3:$C$44) -> 211.19 | C12: =_xlfn.XLOOKUP(A12,'YOY SHAK'!$A$3:$A$44,'YOY SHAK'!$C$3:$C$44) -> 19.69 | D12: =_xlfn.XLOOKUP(A12,'YOY MCD'!$A$3:$A$44,'YOY MCD'!$C$3:$C$44) -> 2383 | E12: =_xlfn.XLOOKUP(A12,'YOY Yum'!$A$3:$A$44,'YOY Yum'!$C$3:$C$44) -> 775 | F12: =AVERAGE(B12:E12) -> 847.22
A13: Inventory | B13: =_xlfn.XLOOKUP(A13,'YOY CMG'!$A$3:$A$44,'YOY CMG'!$C$3:$C$44) -> 48.94 | C13: =_xlfn.XLOOKUP(A13,'YOY SHAK'!$A$3:$A$44,'YOY SHAK'!$C$3:$C$44) -> 6.01 | D13: =_xlfn.XLOOKUP(A13,'YOY MCD'!$A$3:$A$44,'YOY MCD'!$C$3:$C$44) -> 56 | E13: =_xlfn.XLOOKUP(A13,'YOY Yum'!$A$3:$A$44,'YOY Yum'!$C$3:$C$44) -> 10 | F13: =AVERAGE(B13:E13) -> 30.2375
A14: Total current assets | B14: =_xlfn.XLOOKUP(A14,'YOY CMG'!$A$3:$A$44,'YOY CMG'!$C$3:$C$44) -> 1780.59 | C14: =_xlfn.XLOOKUP(A14,'YOY SHAK'!$A$3:$A$44,'YOY SHAK'!$C$3:$C$44) -> 368.22 | D14: =_xlfn.XLOOKUP(A14,'YOY MCD'!$A$3:$A$44,'YOY MCD'!$C$3:$C$44) -> 4599 | E14: =_xlfn.XLOOKUP(A14,'YOY Yum'!$A$3:$A$44,'YOY Yum'!$C$3:$C$44) -> 1871 | F14: =AVERAGE(B14:E14) -> 2154.7025
A15: Total Assets | B15: =_xlfn.XLOOKUP(A15,'YOY CMG'!$A$3:$A$44,'YOY CMG'!$C$3:$C$44) -> 9204.37 | C15: =_xlfn.XLOOKUP(A15,'YOY SHAK'!$A$3:$A$44,'YOY SHAK'!$C$3:$C$44) -> 1696.97 | D15: =_xlfn.XLOOKUP(A15,'YOY MCD'!$A$3:$A$44,'YOY MCD'!$C$3:$C$44) -> 55182 | E15: =_xlfn.XLOOKUP(A15,'YOY Yum'!$A$3:$A$44,'YOY Yum'!$C$3:$C$44) -> 6727 | F15: =AVERAGE(B15:E15) -> 18202.585
... A20: Shares (Basic, Weighted) | B20: =_xlfn.XLOOKUP(A20,'YOY CMG'!$A$3:$A$44,'YOY CMG'!$C$3:$C$44) -> 1368.34 | C20: =_xlfn.XLOOKUP(A20,'YOY SHAK'!$A$3:$A$44,'YOY SHAK'!$C$3:$C$44) -> 39.83 | D20: =_xlfn.XLOOKUP(A20,'YOY MCD'!$A$3:$A$44,'YOY MCD'!$C$3:$C$44) -> 718.3 | E20: =_xlfn.XLOOKUP(A20,'YOY Yum'!$A$3:$A$44,'YOY Yum'!$C$3:$C$44) -> 282 | F20: =AVERAGE(B20:E20) -> 602.1175
A21: Financial Ratio's
A22: Liquidity
A23: Current Ratio | B23: =_xlfn.XLOOKUP(A23,'YOY CMG'!$A$3:$A$44,'YOY CMG'!$C$3:$C$44) -> 1.5234734 | C23: =_xlfn.XLOOKUP(A23,'YOY SHAK'!$A$3:$A$44,'YOY SHAK'!$C$3:$C$44) -> 1.965832 | D23: =_xlfn.XLOOKUP(A23,'YOY MCD'!$A$3:$A$44,'YOY MCD'!$C$3:$C$44) -> 1.1911422 | E23: =_xlfn.XLOOKUP(A23,'YOY Yum'!$A$3:$A$44,'YOY Yum'!$C$3:$C$44) -> 1.4743893 | F23: =AVERAGE(B23:E23) -> 1.5387092
A24: Quick Ratio | B24: =_xlfn.XLOOKUP(A24,'YOY CMG'!$A$3:$A$44,'YOY CMG'!$C$3:$C$44) -> 1.4816003 | C24: =_xlfn.XLOOKUP(A24,'YOY SHAK'!$A$3:$A$44,'YOY SHAK'!$C$3:$C$44) -> 1.9337462 | D24: =_xlfn.XLOOKUP(A24,'YOY MCD'!$A$3:$A$44,'YOY MCD'!$C$3:$C$44) -> 1.1766382 | E24: =_xlfn.XLOOKUP(A24,'YOY Yum'!$A$3:$A$44,'YOY Yum'!$C$3:$C$44) -> 1.4665091 | F24: =AVERAGE(B24:E24) -> 1.5146234
A25: Net Working Capital | B25: =_xlfn.XLOOKUP(A25,'YOY CMG'!$A$3:$A$44,'YOY CMG'!$C$3:$C$44) -> 611.82 | C25: =_xlfn.XLOOKUP(A25,'YOY SHAK'!$A$3:$A$44,'YOY SHAK'!$C$3:$C$44) -> 180.91 | D25: =_xlfn.XLOOKUP(A25,'YOY MCD'!$A$3:$A$44,'YOY MCD'!$C$3:$C$44) -> 738 | E25: =_xlfn.XLOOKUP(A25,'YOY Yum'!$A$3:$A$44,'YOY Yum'!$C$3:$C$44) -> 602 | F25: =AVERAGE(B25:E25) -> 533.1825
A26: Asset Management
A27: Accounts Rec. Turnover | B27: =_xlfn.XLOOKUP(A27,'YOY CMG'!$A$3:$A$44,'YOY CMG'!$C$3:$C$44) -> 53.571902 | C27: =_xlfn.XLOOKUP(A27,'YOY SHAK'!$A$3:$A$44,'YOY SHAK'!$C$3:$C$44) -> 63.616557 | D27: =_xlfn.XLOOKUP(A27,'YOY MCD'!$A$3:$A$44,'YOY MCD'!$C$3:$C$44) -> 10.877046 | E27: =_xlfn.XLOOKUP(A27,'YOY Yum'!$A$3:$A$44,'YOY Yum'!$C$3:$C$44) -> 9.7406452 | F27: =AVERAGE(B27:E27) -> 34.451537
A28: Inventory Turnover | B28: =_xlfn.XLOOKUP(A28,'YOY CMG'!$A$3:$A$44,'YOY CMG'!$C$3:$C$44) -> 231.17797 | C28: =_xlfn.XLOOKUP(A28,'YOY SHAK'!$A$3:$A$44,'YOY SHAK'!$C$3:$C$44) -> 208.42097 | D28: =_xlfn.XLOOKUP(A28,'YOY MCD'!$A$3:$A$44,'YOY MCD'!$C$3:$C$44) -> 462.85714 | E28: =_xlfn.XLOOKUP(A28,'YOY Yum'!$A$3:$A$44,'YOY Yum'!$C$3:$C$44) -> 754.9 | F28: =AVERAGE(B28:E28) -> 414.33902
A29: Total Asset Turnover | B29: =_xlfn.XLOOKUP(A29,'YOY CMG'!$A$3:$A$44,'YOY CMG'!$C$3:$C$44) -> 1.2291824 | C29: =_xlfn.XLOOKUP(A29,'YOY SHAK'!$A$3:$A$44,'YOY SHAK'!$C$3:$C$44) -> 0.73814505 | D29: =_xlfn.XLOOKUP(A29,'YOY MCD'!$A$3:$A$44,'YOY MCD'!$C$3:$C$44) -> 0.46971839 | E29: =_xlfn.XLOOKUP(A29,'YOY Yum'!$A$3:$A$44,'YOY Yum'!$C$3:$C$44) -> 1.1221941 | F29: =AVERAGE(B29:E29) -> 0.88981
A30: Debt Management
A31: Debt to Equity Ratio | B31: =_xlfn.XLOOKUP(A31,'YOY CMG'!$A$3:$A$44,'YOY CMG'!$C$3:$C$44) -> 0.0027355665 | C31: =_xlfn.XLOOKUP(A31,'YOY SHAK'!$A$3:$A$44,'YOY SHAK'!$C$3:$C$44) -> 0.49972652 | D31: =_xlfn.XLOOKUP(A31,'YOY MCD'!$A$3:$A$44,'YOY MCD'!$C$3:$C$44) -> -10.122234 | E31: =_xlfn.XLOOKUP(A31,'YOY Yum'!$A$3:$A$44,'YOY Yum'!$C$3:$C$44) -> -1.478295 | F31: =AVERAGE(B31:E31) -> -2.7745167
A32: Equity multiplier | B32: =_xlfn.XLOOKUP(A32,'YOY CMG'!$A$3:$A$44,'YOY CMG'!$C$3:$C$44) -> 2.5179166 | C32: =_xlfn.XLOOKUP(A32,'YOY SHAK'!$A$3:$A$44,'YOY SHAK'!$C$3:$C$44) -> 3.4377368 | D32: =_xlfn.XLOOKUP(A32,'YOY MCD'!$A$3:$A$44,'YOY MCD'!$C$3:$C$44) -> -14.536881 | E32: =_xlfn.XLOOKUP(A32,'YOY Yum'!$A$3:$A$44,'YOY Yum'!$C$3:$C$44) -> -0.87957636 | F32: =AVERAGE(B32:E32) -> -2.365201
A33: Profitability
A34: Net Profit Margin | B34: =_xlfn.XLOOKUP(A34,'YOY CMG'!$A$3:$A$44,'YOY CMG'!$C$3:$C$44) -> 0.1356 | C34: =_xlfn.XLOOKUP(A34,'YOY SHAK'!$A$3:$A$44,'YOY SHAK'!$C$3:$C$44) -> 0.0081 | D34: =_xlfn.XLOOKUP(A34,'YOY MCD'!$A$3:$A$44,'YOY MCD'!$C$3:$C$44) -> 0.3172 | E34: =_xlfn.XLOOKUP(A34,'YOY Yum'!$A$3:$A$44,'YOY Yum'!$C$3:$C$44) -> 0.1968 | F34: =AVERAGE(B34:E34) -> 0.164425
A35: Gross Profit Margin | B35: =_xlfn.XLOOKUP(A35,'YOY CMG'!$A$3:$A$44,'YOY CMG'!$C$3:$C$44) -> 0.2667 | C35: =_xlfn.XLOOKUP(A35,'YOY SHAK'!$A$3:$A$44,'YOY SHAK'!$C$3:$C$44) -> 0.2415 | D35: =_xlfn.XLOOKUP(A35,'YOY MCD'!$A$3:$A$44,'YOY MCD'!$C$3:$C$44) -> 0.5675 | E35: =_xlfn.XLOOKUP(A35,'YOY Yum'!$A$3:$A$44,'YOY Yum'!$C$3:$C$44) -> 0.7192 | F35: =AVERAGE(B35:E35) -> 0.448725
A36: Return On Assets ROA | B36: =_xlfn.XLOOKUP(A36,'YOY CMG'!$A$3:$A$44,'YOY CMG'!$C$3:$C$44) -> 0.16667714 | C36: =_xlfn.XLOOKUP(A36,'YOY SHAK'!$A$3:$A$44,'YOY SHAK'!$C$3:$C$44) -> 0.0059789749 | D36: =_xlfn.XLOOKUP(A36,'YOY MCD'!$A$3:$A$44,'YOY MCD'!$C$3:$C$44) -> 0.14899467 | E36: =_xlfn.XLOOKUP(A36,'YOY Yum'!$A$3:$A$44,'YOY Yum'!$C$3:$C$44) -> 0.22084781 | F36: =AVERAGE(B36:E36) -> 0.13562465
A37: Return On Equity ROE | B37: =_xlfn.XLOOKUP(A37,'YOY CMG'!$A$3:$A$44,'YOY CMG'!$C$3:$C$44) -> 0.41967913 | C37: =_xlfn.XLOOKUP(A37,'YOY SHAK'!$A$3:$A$44,'YOY SHAK'!$C$3:$C$44) -> 0.020554142 | D37: =_xlfn.XLOOKUP(A37,'YOY MCD'!$A$3:$A$44,'YOY MCD'!$C$3:$C$44) -> -2.1659178 | E37: =_xlfn.XLOOKUP(A37,'YOY Yum'!$A$3:$A$44,'YOY Yum'!$C$3:$C$44) -> -0.19425251 | F37: =AVERAGE(B37:E37) -> -0.47998426
A38: Market Value
A39: EPS | B39: =_xlfn.XLOOKUP(A39,'YOY CMG'!$A$3:$A$44,'YOY CMG'!$C$3:$C$44) -> 1.1211468 | C39: =_xlfn.XLOOKUP(A39,'YOY SHAK'!$A$3:$A$44,'YOY SHAK'!$C$3:$C$44) -> 0.25633944 | D39: =_xlfn.XLOOKUP(A39,'YOY MCD'!$A$3:$A$44,'YOY MCD'!$C$3:$C$44) -> 11.447863 | E39: =_xlfn.XLOOKUP(A39,'YOY Yum'!$A$3:$A$44,'YOY Yum'!$C$3:$C$44) -> 5.2695035 | F39: =AVERAGE(B39:E39) -> 4.5237132
A40: P/E | B40: =_xlfn.XLOOKUP(A40,'YOY CMG'!$A$3:$A$44,'YOY CMG'!$C$3:$C$44) -> 53.596907 | C40: =_xlfn.XLOOKUP(A40,'YOY SHAK'!$A$3:$A$44,'YOY SHAK'!$C$3:$C$44) -> 505.22853 | D40: =_xlfn.XLOOKUP(A40,'YOY MCD'!$A$3:$A$44,'YOY MCD'!$C$3:$C$44) -> 25.297298 | E40: =_xlfn.XLOOKUP(A40,'YOY Yum'!$A$3:$A$44,'YOY Yum'!$C$3:$C$44) -> 25.33825 | F40: =AVERAGE(B40:E40) -> 152.36525
A41: Book Value Per Share | B41: =_xlfn.XLOOKUP(A41,'YOY CMG'!$A$3:$A$44,'YOY CMG'!$C$3:$C$44) -> 2.6715217 | C41: =_xlfn.XLOOKUP(A41,'YOY SHAK'!$A$3:$A$44,'YOY SHAK'!$C$3:$C$44) -> 12.393422 | D41: =_xlfn.XLOOKUP(A41,'YOY MCD'!$A$3:$A$44,'YOY MCD'!$C$3:$C$44) -> -5.2847 | E41: =_xlfn.XLOOKUP(A41,'YOY Yum'!$A$3:$A$44,'YOY Yum'!$C$3:$C$44) -> -27.120567 | F41: =AVERAGE(B41:E41) -> -4.3350809
A42: Market Capitalization (Stock Price * Shares) | B42: =_xlfn.XLOOKUP(A42,'YOY CMG'!$A$3:$A$44,'YOY CMG'!$C$3:$C$44) -> 82223.551 | C42: =_xlfn.XLOOKUP(A42,'YOY SHAK'!$A$3:$A$44,'YOY SHAK'!$C$3:$C$44) -> 5158.3833 | D42: =_xlfn.XLOOKUP(A42,'YOY MCD'!$A$3:$A$44,'YOY MCD'!$C$3:$C$44) -> 208019.68 | E42: =_xlfn.XLOOKUP(A42,'YOY Yum'!$A$3:$A$44,'YOY Yum'!$C$3:$C$44) -> 37652.64 | F42: =AVERAGE(B42:E42) -> 83263.563
A43: Cash Per Share | B43: =_xlfn.XLOOKUP(A43,'YOY CMG'!$A$3:$A$44,'YOY CMG'!$C$3:$C$44) -> 1.0398804 | C43: =_xlfn.XLOOKUP(A43,'YOY SHAK'!$A$3:$A$44,'YOY SHAK'!$C$3:$C$44) -> 8.0519709 | D43: =_xlfn.XLOOKUP(A43,'YOY MCD'!$A$3:$A$44,'YOY MCD'!$C$3:$C$44) -> 1.5105109 | E43: =_xlfn.XLOOKUP(A43,'YOY Yum'!$A$3:$A$44,'YOY Yum'!$C$3:$C$44) -> 2.1843972 | F43: =AVERAGE(B43:E43) -> 3.1966899
A44: Revenue Per Share | B44: =_xlfn.XLOOKUP(A44,'YOY CMG'!$A$3:$A$44,'YOY CMG'!$C$3:$C$44) -> 8.2683032 | C44: =_xlfn.XLOOKUP(A44,'YOY SHAK'!$A$3:$A$44,'YOY SHAK'!$C$3:$C$44) -> 31.448908 | D44: =_xlfn.XLOOKUP(A44,'YOY MCD'!$A$3:$A$44,'YOY MCD'!$C$3:$C$44) -> 36.085201 | E44: =_xlfn.XLOOKUP(A44,'YOY Yum'!$A$3:$A$44,'YOY Yum'!$C$3:$C$44) -> 26.769504 | F44: =AVERAGE(B44:E44) -> 25.642979
A45: Price to Book Value | B45: =_xlfn.XLOOKUP(A45,'YOY CMG'!$A$3:$A$44,'YOY CMG'!$C$3:$C$44) -> 22.492799 | C45: =_xlfn.XLOOKUP(A45,'YOY SHAK'!$A$3:$A$44,'YOY SHAK'!$C$3:$C$44) -> 10.449898 | D45: =_xlfn.XLOOKUP(A45,'YOY MCD'!$A$3:$A$44,'YOY MCD'!$C$3:$C$44) -> -54.799705 | E45: =_xlfn.XLOOKUP(A45,'YOY Yum'!$A$3:$A$44,'YOY Yum'!$C$3:$C$44) -> -4.9232008 | F45: =AVERAGE(B45:E45) -> -6.6950522

Sheet C24-21
A1: In the Millions | G1: In the Millions
B2: Dec '24 | C2: Dec '23 | D2: Dec '22 | E2: Dec '21 | H2: Dec '24 | I2: Dec '23 | J2: Dec '22 | K2: Dec '21
A3: Income Statement | G3: Balance Sheet
A4: Revenue | B4: 11313.85 | C4: 9871.65 | D4: 8634.65 | E4: 7547.06 | G4: Cash and Short Term Investments | H4: 1422.91 | I4: 1295.45 | J4: 899.14 | K4: 1076.32
A5: Revenue Growth | B5: 0.1461 | C5: 0.1433 | D5: 0.1441 | E5: 0.2611 | G5: Receivables | H5: 211.19 | I5: 168.5 | J5: 154.62 | K5: 193.66
A6: Cost of Revenue | B6: 8296.16 | C6: 7285.56 | D6: 6572.53 | E6: 5840.05 | G6: Inventory | H6: 48.94 | I6: 39.31 | J6: 35.67 | K6: 32.83
A7: Gross Profit | B7: 3017.69 | C7: 2586.09 | D7: 2062.12 | E7: 1707.01 | G7: Other current assets | H7: — | I7: — | J7: 86 | K7: 79
A8: SG&A Expenses | B8: 697.48 | C8: 633.58 | D8: 564.19 | E8: 606.85 | G8: Total current assets | H8: 1780.59 | I8: 1620.71 | J8: 1175.84 | K8: 1381.56
A9: Operating Income | B9: 1916.33 | C9: 1557.81 | D9: 1160.4 | E9: 804.94 | G9: Property, Plant, Equipment (Net) | H9: 2390.13 | I9: 2170.04 | J9: 1951.15 | K9: 1769.28
A10: Non-operating Income/Expense | B10: 93.9 | C10: 62.69 | D10: 21.13 | E10: 7.82 | G10: Long-Term Investments | H10: 868.02 | I10: 564.49 | J10: 388.06 | K10: 274.31
A11: Non-operating Interest Expenses | B11: — | C11: — | D11: — | E11: — | G11: Goodwill and Intangible Assets (Total) | H11: 21.94 | I11: 21.94 | J11: 21.94 | K11: 21.94
A12: EBT | B12: 2010.23 | C12: 1620.51 | D12: 1181.53 | E12: 812.76 | G12: Long-term assets (Other) | H12: 143.57 | I12: 88.64 | J12: 88.12 | K12: 87.57
A13: Income Tax Provision | B13: 476.12 | C13: 391.77 | D13: 282.43 | E13: 159.78 | G13: Total non-current assets | H13: 7423.79 | I13: 6423.65 | J13: 5751.67 | K13: 5271.39
A14: Income after Tax | B14: 1534.11 | C14: 1228.74 | D14: 899.1 | E14: 652.98 | G14: Total Assets | H14: 9204.37 | I14: 8044.36 | J14: 6927.5 | K14: 6652.96
A15: Net Income Common | B15: 1534.11 | C15: 1228.74 | D15: 899.1 | E15: 652.98 | G15: Accounts Payable | H15: 210.69 | I15: 197.65 | J15: 184.57 | K15: 163.16
A16: EPS (Basic) | B16: 1.12 | C16: 0.89 | D16: 0.65 | E16: 0.46 | G16: Accrued Expenses | H16: 179.75 | I16: 147.69 | J16: 147.54 | K16: 173.05
A17: EPS (Diluted) | B17: 1.11 | C17: 0.89 | D17: 0.64 | E17: 0.46 | G17: Current Part of Debt | H17: — | I17: — | J17: 236 | K17: 219
A18: Shares (Basic, Weighted) | B18: 1368.34 | C18: 1377.77 | D18: 1392.54 | E18: 1406.6 | G18: Current Part of Taxes to Pay | H18: — | I18: — | J18: — | K18: —
A19: Shares (Diluted, Weighted) | B19: 1376.56 | C19: 1385.5 | D19: 1403.08 | E19: 1425.55 | G19: Current Revenue (Deferred) | H19: 238.58 | I19: 209.68 | J19: 183.07 | K19: 156.35
A20: Gross Margin | B20: 0.2667 | C20: 0.262 | D20: 0.2388 | E20: 0.2262 | G20: Other current liabilities | H20: — | I20: — | J20: 465 | K20: 460
A21: EBIT Margin | B21: 0.1694 | C21: 0.1578 | D21: 0.1344 | E21: 0.1067 | G21: Total current liabilities | H21: 1168.77 | I21: 1030.63 | J21: 921.88 | K21: 873.68
A22: EBT margin | B22: 0.1777 | C22: 0.1642 | D22: 0.1368 | E22: 0.1077 | G22: Long Term Debt (Total) | H22: — | I22: — | J22: 3495 | K22: 3302
A23: Net Profit Margin | B23: 0.1356 | C23: 0.1245 | D23: 0.1041 | E23: 0.0865 | G23: Non-current Revenue (Deferred) | H23: — | I23: — | J23: — | K23: —
A24: Free Cash Flow Margin | B24: 0.1354 | C24: 0.1239 | D24: 0.0977 | E24: 0.1118 | G24: Long Term Tax Liability (Deferred) | H24: 46.21 | I24: 89.11 | J24: 98.62 | K24: 141.76
A25: EBITDA | B25: 2251.36 | C25: 1877.21 | D25: 1447.23 | E25: 1059.6 | G25: Non-current Liabilities (Other) | H25: 71.07 | I25: 58.87 | J25: 43.82 | K25: 38.54
A26: EBIT | B26: 1916.33 | C26: 1557.81 | D26: 1160.4 | E26: 804.94 | G26: Total non-current liabilities | H26: 4380.06 | I26: 3951.53 | J26: 3637.6 | K26: 3481.9
A27: Income from Continuous Operations | B27: 1534.11 | C27: 1228.74 | D27: 899.1 | E27: 652.98 | G27: Total liabilities | H27: 5548.83 | I27: 4982.15 | J27: 4559.48 | K27: 4355.58
A28: Consolidated Net Income/Loss | B28: 1534.11 | C28: 1228.74 | D28: 899.1 | E28: 652.98 | G28: Additional Paid In Capital | H28: 2078.01 | I28: 1937.79 | J28: 1829.3 | K28: 1729.31
A29: EPS (Basic, from Continuous Ops) | B29: 1.12 | C29: 0.89 | D29: 0.65 | E29: 0.46 | G29: Common Stock (Net) | H29: 13.59 | I29: 18.74 | J29: 0.37 | K29: 0.37
A30: EPS (Basic, Consolidated) | B30: 1.12 | C30: 0.89 | D30: 0.65 | E30: 0.46 | G30: Retained Earnings | H30: 1574.23 | I30: 6056.98 | J30: 4828.25 | K30: 3929.15
A31: EPS (Diluted, from Cont. Ops) | B31: 1.11 | C31: 0.89 | D31: 0.64 | E31: 0.46 | G31: Treasury Stock | H31: — | I31: 4944.66 | J31: 4282.01 | K31: 3356.1
A32: Shares (Diluted, Average) | B32: 1376.56 | C32: 1385.5 | D32: 1403.1 | E32: 1425.55 | G32: Common Equity (Total) | H32: 3655.55 | I32: 3062.21 | J32: 2368.02 | K32: 2297.37
A33: EPS (Diluted, Consolidated) | B33: 1.11 | C33: 0.89 | D33: 0.64 | E33: 0.46 | G33: Shareholders Equity (Total) | H33: 3655.55 | I33: 3062.21 | J33: 2368.02 | K33: 2297.37
A34: EBITDA Margin | B34: 0.199 | C34: 0.1902 | D34: 0.1676 | E34: 0.1404 | G34: Shareholders Equity and Liabilities (Total) | H34: 9204.37 | I34: 8044.36 | J34: 6927.5 | K34: 6652.96
A35: Operating Cash Flow Margin | B35: 0.1861 | C35: 0.1807 | D35: 0.1532 | E35: 0.1699 | G35: Shares (Common) | H35: 1358.75 | I35: 1371.3 | J35: 1381.35 | K35: 1404
A36: Cash and Short Term Investments | B36: 1422.91 | C36: 1295.45 | D36: 899.14 | E36: 1076.32 | G36: Shareholders Equity (Tangible) | H36: 3633.61 | I36: 3040.27 | J36: 2346.08 | K36: 2275.43
A37: Receivables | B37: 211.19 | C37: 168.5 | D37: 154.62 | E37: 193.66 | G37: Net Debt | H37: -1422.91 | I37: -1295.45 | J37: 2831.86 | K37: 2444.68
A38: Inventory | B38: 48.94 | C38: 39.31 | D38: 35.67 | E38: 32.83 | G38: Total Debt | H38: — | I38: — | J38: 3731 | K38: 3521
A39: Other current assets | B39: — | C39: — | D39: 86 | E39: 79
A40: Total current assets | B40: 1780.59 | C40: 1620.71 | D40: 1175.84 | E40: 1381.56
A41: Property, Plant, Equipment (Net) | B41: 2390.13 | C41: 2170.04 | D41: 1951.15 | E41: 1769.28
A42: Long-Term Investments | B42: 868.02 | C42: 564.49 | D42: 388.06 | E42: 274.31
A43: Goodwill and Intangible Assets (Total) | B43: 21.94 | C43: 21.94 | D43: 21.94 | E43: 21.94
A44: Long-term assets (Other) | B44: 143.57 | C44: 88.64 | D44: 88.12 | E44: 87.57
A45: Total non-current assets | B45: 7423.79 | C45: 6423.65 | D45: 5751.67 | E45: 5271.39
A46: Total Assets | B46: 9204.37 | C46: 8044.36 | D46: 6927.5 | E46: 6652.96
A47: Accounts Payable | B47: 210.69 | C47: 197.65 | D47: 184.57 | E47: 163.16
A48: Accrued Expenses | B48: 179.75 | C48: 147.69 | D48: 147.54 | E48: 173.05
A49: Current Part of Debt | B49: — | C49: — | D49: 236 | E49: 219
A50: Current Part of Taxes to Pay | B50: — | C50: — | D50: — | E50: —
A51: Current Revenue (Deferred) | B51: 238.58 | C51: 209.68 | D51: 183.07 | E51: 156.35
A52: Other current liabilities | B52: — | C52: — | D52: 465 | E52: 460
A53: Total current liabilities | B53: 1168.77 | C53: 1030.63 | D53: 921.88 | E53: 873.68
A54: Long Term Debt (Total) | B54: — | C54: — | D54: 3495 | E54: 3302
A55: Non-current Revenue (Deferred) | B55: — | C55: — | D55: — | E55: —
A56: Long Term Tax Liability (Deferred) | B56: 46.21 | C56: 89.11 | D56: 98.62 | E56: 141.76
A57: Non-current Liabilities (Other) | B57: 71.07 | C57: 58.87 | D57: 43.82 | E57: 38.54
A58: Total non-current liabilities | B58: 4380.06 | C58: 3951.53 | D58: 3637.6 | E58: 3481.9
A59: Total liabilities | B59: 5548.83 | C59: 4982.15 | D59: 4559.48 | E59: 4355.58
A60: Additional Paid In Capital | B60: 2078.01 | C60: 1937.79 | D60: 1829.3 | E60: 1729.31
A61: Common Stock (Net) | B61: 13.59 | C61: 18.74 | D61: 0.37 | E61: 0.37
A62: Retained Earnings | B62: 1574.23 | C62: 6056.98 | D62: 4828.25 | E62: 3929.15
A63: Treasury Stock | B63: — | C63: 4944.66 | D63: 4282.01 | E63: 3356.1
A64: Common Equity (Total) | B64: 3655.55 | C64: 3062.21 | D64: 2368.02 | E64: 2297.37
A65: Shareholders Equity (Total) | B65: 3655.55 | C65: 3062.21 | D65: 2368.02 | E65: 2297.37
A66: Shareholders Equity and Liabilities (Total) | B66: 9204.37 | C66: 8044.36 | D66: 6927.5 | E66: 6652.96
A67: Shares (Common) | B67: 1358.75 | C67: 1371.3 | D67: 1381.35 | E67: 1404
A68: Shareholders Equity (Tangible) | B68: 3633.61 | C68: 3040.27 | D68: 2346.08 | E68: 2275.43
A69: Net Debt | B69: -1422.91 | C69: -1295.45 | D69: 2831.86 | E69: 2444.68
A70: Total Debt | B70: — | C70: — | D70: 3731 | E70: 3521

Sheet YOY CMG
A1: Company Name | C1: CMG | D1: CMG | E1: YOY % Change 2024 2023 | F1: CMG | G1: YOY % Change 2023 2022 | H1: CMG | I1: YOY % Change 2022 2021
A2: Year ending: | C2: 2024 | D2: 2023 | F2: 2022 | H2: 2021
A3: Stock Price | C3: 60.09 | D3: 45.74 | E3: =+(C3-D3)/D3 -> 0.31372978 | F3: 27.75 | G3: =+(D3-F3)/F3 -> 0.64828829 | H3: 34.94 | I3: =(F3-H3)/H3 -> -0.20578134
A4: Revenue | C4: =_xlfn.XLOOKUP(A4,'C24-21'!$A$4:$A$70,'C24-21'!$B$4:$B$70,"LOOK",0) -> 11313.85 | D4: =_xlfn.XLOOKUP(A4,'C24-21'!$A$4:$A$70,'C24-21'!$C$4:$C$70,"LOOK",0) -> 9871.65 | E4: =+(C4-D4)/D4 -> 0.14609513 | F4: =_xlfn.XLOOKUP(A4,'C24-21'!$A$4:$A$70,'C24-21'!$D$4:$D$70,"LOOK",0) -> 8634.65 | G4: =+(D4-F4)/F4 -> 0.14326 | H4: =_xlfn.XLOOKUP(A4,'C24-21'!$A$4:$A$70,'C24-21'!$E$4:$E$70,"LOOK") -> 7547.06 | I4: =(F4-H4)/H4 -> 0.14410777
A5: Cost of Revenue | C5: =_xlfn.XLOOKUP(A5,'C24-21'!$A$4:$A$70,'C24-21'!$B$4:$B$70,"LOOK",0) -> 8296.16 | D5: =_xlfn.XLOOKUP(A5,'C24-21'!$A$4:$A$70,'C24-21'!$C$4:$C$70,"LOOK",0) -> 7285.56 | E5: =+(C5-D5)/D5 -> 0.13871274 | F5: =_xlfn.XLOOKUP(A5,'C24-21'!$A$4:$A$70,'C24-21'!$D$4:$D$70,"LOOK",0) -> 6572.53 | G5: =+(D5-F5)/F5 -> 0.10848638 | H5: =_xlfn.XLOOKUP(A5,'C24-21'!$A$4:$A$70,'C24-21'!$E$4:$E$70,"LOOK") -> 5840.05 | I5: =(F5-H5)/H5 -> 0.12542358
A6: Gross Profit | C6: =_xlfn.XLOOKUP(A6,'C24-21'!$A$4:$A$70,'C24-21'!$B$4:$B$70,"LOOK",0) -> 3017.69 | D6: =_xlfn.XLOOKUP(A6,'C24-21'!$A$4:$A$70,'C24-21'!$C$4:$C$70,"LOOK",0) -> 2586.09 | E6: =+(C6-D6)/D6 -> 0.16689288 | F6: =_xlfn.XLOOKUP(A6,'C24-21'!$A$4:$A$70,'C24-21'!$D$4:$D$70,"LOOK",0) -> 2062.12 | G6: =+(D6-F6)/F6 -> 0.25409288 | H6: =_xlfn.XLOOKUP(A6,'C24-21'!$A$4:$A$70,'C24-21'!$E$4:$E$70,"LOOK") -> 1707.01 | I6: =(F6-H6)/H6 -> 0.20803042
A7: SG&A Expenses | C7: =_xlfn.XLOOKUP(A7,'C24-21'!$A$4:$A$70,'C24-21'!$B$4:$B$70,"LOOK",0) -> 697.48 | D7: =_xlfn.XLOOKUP(A7,'C24-21'!$A$4:$A$70,'C24-21'!$C$4:$C$70,"LOOK",0) -> 633.58 | E7: =+(C7-D7)/D7 -> 0.10085546 | F7: =_xlfn.XLOOKUP(A7,'C24-21'!$A$4:$A$70,'C24-21'!$D$4:$D$70,"LOOK",0) -> 564.19 | G7: =+(D7-F7)/F7 -> 0.12299048 | H7: =_xlfn.XLOOKUP(A7,'C24-21'!$A$4:$A$70,'C24-21'!$E$4:$E$70,"LOOK") -> 606.85 | I7: =(F7-H7)/H7 -> -0.070297438
A8: Operating Income | C8: =_xlfn.XLOOKUP(A8,'C24-21'!$A$4:$A$70,'C24-21'!$B$4:$B$70,"LOOK",0) -> 1916.33 | D8: =_xlfn.XLOOKUP(A8,'C24-21'!$A$4:$A$70,'C24-21'!$C$4:$C$70,"LOOK",0) -> 1557.81 | E8: =+(C8-D8)/D8 -> 0.2301436 | F8: =_xlfn.XLOOKUP(A8,'C24-21'!$A$4:$A$70,'C24-21'!$D$4:$D$70,"LOOK",0) -> 1160.4 | G8: =+(D8-F8)/F8 -> 0.34247673 | H8: =_xlfn.XLOOKUP(A8,'C24-21'!$A$4:$A$70,'C24-21'!$E$4:$E$70,"LOOK") -> 804.94 | I8: =(F8-H8)/H8 -> 0.44159813
A9: Net Income Common | C9: =_xlfn.XLOOKUP(A9,'C24-21'!$A$4:$A$70,'C24-21'!$B$4:$B$70,"LOOK",0) -> 1534.11 | D9: =_xlfn.XLOOKUP(A9,'C24-21'!$A$4:$A$70,'C24-21'!$C$4:$C$70,"LOOK",0) -> 1228.74 | E9: =+(C9-D9)/D9 -> 0.24852288 | F9: =_xlfn.XLOOKUP(A9,'C24-21'!$A$4:$A$70,'C24-21'!$D$4:$D$70,"LOOK",0) -> 899.1 | G9: =+(D9-F9)/F9 -> 0.3666333 | H9: =_xlfn.XLOOKUP(A9,'C24-21'!$A$4:$A$70,'C24-21'!$E$4:$E$70,"LOOK") -> 652.98 | I9: =(F9-H9)/H9 -> 0.37691813
A10: Cash and Short Term Investments | C10: =_xlfn.XLOOKUP(A10,'C24-21'!$A$4:$A$70,'C24-21'!$B$4:$B$70,"LOOK",0) -> 1422.91 | D10: =_xlfn.XLOOKUP(A10,'C24-21'!$A$4:$A$70,'C24-21'!$C$4:$C$70,"LOOK",0) -> 1295.45 | E10: =+(C10-D10)/D10 -> 0.098390521 | F10: =_xlfn.XLOOKUP(A10,'C24-21'!$A$4:$A$70,'C24-21'!$D$4:$D$70,"LOOK",0) -> 899.14 | G10: =+(D10-F10)/F10 -> 0.44076562 | H10: =_xlfn.XLOOKUP(A10,'C24-21'!$A$4:$A$70,'C24-21'!$E$4:$E$70,"LOOK") -> 1076.32 | I10: =(F10-H10)/H10 -> -0.16461647
A11: Receivables | C11: =_xlfn.XLOOKUP(A11,'C24-21'!$A$4:$A$70,'C24-21'!$B$4:$B$70,"LOOK",0) -> 211.19 | D11: =_xlfn.XLOOKUP(A11,'C24-21'!$A$4:$A$70,'C24-21'!$C$4:$C$70,"LOOK",0) -> 168.5 | E11: =+(C11-D11)/D11 -> 0.25335312 | F11: =_xlfn.XLOOKUP(A11,'C24-21'!$A$4:$A$70,'C24-21'!$D$4:$D$70,"LOOK",0) -> 154.62 | G11: =+(D11-F11)/F11 -> 0.089768465 | H11: =_xlfn.XLOOKUP(A11,'C24-21'!$A$4:$A$70,'C24-21'!$E$4:$E$70,"LOOK") -> 193.66 | I11: =(F11-H11)/H11 -> -0.20159042
A12: Inventory | C12: =_xlfn.XLOOKUP(A12,'C24-21'!$A$4:$A$70,'C24-21'!$B$4:$B$70,"LOOK",0) -> 48.94 | D12: =_xlfn.XLOOKUP(A12,'C24-21'!$A$4:$A$70,'C24-21'!$C$4:$C$70,"LOOK",0) -> 39.31 | E12: =+(C12-D12)/D12 -> 0.24497583 | F12: =_xlfn.XLOOKUP(A12,'C24-21'!$A$4:$A$70,'C24-21'!$D$4:$D$70,"LOOK",0) -> 35.67 | G12: =+(D12-F12)/F12 -> 0.10204654 | H12: =_xlfn.XLOOKUP(A12,'C24-21'!$A$4:$A$70,'C24-21'!$E$4:$E$70,"LOOK") -> 32.83 | I12: =(F12-H12)/H12 -> 0.086506244
A13: Total current assets | C13: =_xlfn.XLOOKUP(A13,'C24-21'!$A$4:$A$70,'C24-21'!$B$4:$B$70,"LOOK",0) -> 1780.59 | D13: =_xlfn.XLOOKUP(A13,'C24-21'!$A$4:$A$70,'C24-21'!$C$4:$C$70,"LOOK",0) -> 1620.71 | E13: =+(C13-D13)/D13 -> 0.098648123 | F13: =_xlfn.XLOOKUP(A13,'C24-21'!$A$4:$A$70,'C24-21'!$D$4:$D$70,"LOOK",0) -> 1175.84 | G13: =+(D13-F13)/F13 -> 0.37834229 | H13: =_xlfn.XLOOKUP(A13,'C24-21'!$A$4:$A$70,'C24-21'!$E$4:$E$70,"LOOK") -> 1381.56 | I13: =(F13-H13)/H13 -> -0.14890414
A14: Total Assets | C14: =_xlfn.XLOOKUP(A14,'C24-21'!$A$4:$A$70,'C24-21'!$B$4:$B$70,"LOOK",0) -> 9204.37 | D14: =_xlfn.XLOOKUP(A14,'C24-21'!$A$4:$A$70,'C24-21'!$C$4:$C$70,"LOOK",0) -> 8044.36 | E14: =+(C14-D14)/D14 -> 0.14420165 | F14: =_xlfn.XLOOKUP(A14,'C24-21'!$A$4:$A$70,'C24-21'!$D$4:$D$70,"LOOK",0) -> 6927.5 | G14: =+(D14-F14)/F14 -> 0.16122122 | H14: =_xlfn.XLOOKUP(A14,'C24-21'!$A$4:$A$70,'C24-21'!$E$4:$E$70,"LOOK") -> 6652.96 | I14: =(F14-H14)/H14 -> 0.041265843
A15: Total current liabilities | C15: =_xlfn.XLOOKUP(A15,'C24-21'!$A$4:$A$70,'C24-21'!$B$4:$B$70,"LOOK",0) -> 1168.77 | D15: =_xlfn.XLOOKUP(A15,'C24-21'!$A$4:$A$70,'C24-21'!$C$4:$C$70,"LOOK",0) -> 1030.63 | E15: =+(C15-D15)/D15 -> 0.13403452 | F15: =_xlfn.XLOOKUP(A15,'C24-21'!$A$4:$A$70,'C24-21'!$D$4:$D$70,"LOOK",0) -> 921.88 | G15: =+(D15-F15)/F15 -> 0.11796546 | H15: =_xlfn.XLOOKUP(A15,'C24-21'!$A$4:$A$70,'C24-21'!$E$4:$E$70,"LOOK") -> 873.68 | I15: =(F15-H15)/H15 -> 0.055168941
A16: Long Term Debt (Total) | C16: 10 | D16: 10 | E16: =+(C16-D16)/D16 -> 0 | F16: =_xlfn.XLOOKUP(A16,'C24-21'!$A$4:$A$70,'C24-21'!$D$4:$D$70,"LOOK",0) -> 3495 | G16: =+(D16-F16)/F16 -> -0.99713877 | H16: =_xlfn.XLOOKUP(A16,'C24-21'!$A$4:$A$70,'C24-21'!$E$4:$E$70,"LOOK") -> 3302 | I16: =(F16-H16)/H16 -> 0.058449425
A17: Total liabilities | C17: =_xlfn.XLOOKUP(A17,'C24-21'!$A$4:$A$70,'C24-21'!$B$4:$B$70,"LOOK",0) -> 5548.83 | D17: =_xlfn.XLOOKUP(A17,'C24-21'!$A$4:$A$70,'C24-21'!$C$4:$C$70,"LOOK",0) -> 4982.15 | E17: =+(C17-D17)/D17 -> 0.11374206 | F17: =_xlfn.XLOOKUP(A17,'C24-21'!$A$4:$A$70,'C24-21'!$D$4:$D$70,"LOOK",0) -> 4559.48 | G17: =+(D17-F17)/F17 -> 0.092701361 | H17: =_xlfn.XLOOKUP(A17,'C24-21'!$A$4:$A$70,'C24-21'!$E$4:$E$70,"LOOK") -> 4355.58 | I17: =(F17-H17)/H17 -> 0.046813513
A18: Common Equity (Total) | C18: =_xlfn.XLOOKUP(A18,'C24-21'!$A$4:$A$70,'C24-21'!$B$4:$B$70,"LOOK",0) -> 3655.55 | D18: =_xlfn.XLOOKUP(A18,'C24-21'!$A$4:$A$70,'C24-21'!$C$4:$C$70,"LOOK",0) -> 3062.21 | E18: =+(C18-D18)/D18 -> 0.19376202 | F18: =_xlfn.XLOOKUP(A18,'C24-21'!$A$4:$A$70,'C24-21'!$D$4:$D$70,"LOOK",0) -> 2368.02 | G18: =+(D18-F18)/F18 -> 0.29315208 | H18: =_xlfn.XLOOKUP(A18,'C24-21'!$A$4:$A$70,'C24-21'!$E$4:$E$70,"LOOK") -> 2297.37 | I18: =(F18-H18)/H18 -> 0.030752556
A19: Shares (Basic, Weighted) | C19: =_xlfn.XLOOKUP(A19,'C24-21'!$A$4:$A$70,'C24-21'!$B$4:$B$70,"LOOK",0) -> 1368.34 | D19: =_xlfn.XLOOKUP(A19,'C24-21'!$A$4:$A$70,'C24-21'!$C$4:$C$70,"LOOK",0) -> 1377.77 | E19: =+(C19-D19)/D19 -> -0.0068443935 | F19: =_xlfn.XLOOKUP(A19,'C24-21'!$A$4:$A$70,'C24-21'!$D$4:$D$70,"LOOK",0) -> 1392.54 | G19: =+(D19-F19)/F19 -> -0.010606518 | H19: =_xlfn.XLOOKUP(A19,'C24-21'!$A$4:$A$70,'C24-21'!$E$4:$E$70,"LOOK") -> 1406.6 | I19: =(F19-H19)/H19 -> -0.0099957344
A20: Financial Ratio's | C20: CMG | D20: CMG | E20: YOY % Change 2024 2023 | F20: CMG | G20: YOY % Change 2023 2022 | H20: CMG | I20: YOY % Change 2022 2021
A21: Liquidity | C21: 2024 | D21: 2023 | F21: 2022 | H21: 2021
A22: Current Ratio | C22: =C13/C15 -> 1.5234734 | D22: =D13/D15 -> 1.572543 | E22: =(C22-D22)/D22 -> -0.031203988 | F22: =F13/F15 -> 1.2754805 | G22: =(D22-F22)/F22 -> 0.23290239 | H22: =H13/H15 -> 1.5813112 | I22: =(F22-H22)/H22 -> -0.19340323
A23: Quick Ratio | C23: =(C13-C12)/C15 -> 1.4816003 | D23: =(D13-D12)/D15 -> 1.5344013 | E23: =(C23-D23)/D23 -> -0.03441145 | F23: =(F13-F12)/F15 -> 1.2367879 | G23: =(D23-F23)/F23 -> 0.24063417 | H23: =(H13-H12)/H15 -> 1.5437345 | I23: =(F23-H23)/H23 -> -0.19883385
A24: Net Working Capital | C24: =C13-C15 -> 611.82 | D24: =D13-D15 -> 590.08 | E24: =(C24-D24)/D24 -> 0.036842462 | F24: =F13-F15 -> 253.96 | G24: =(D24-F24)/F24 -> 1.3235155 | H24: =H13-H15 -> 507.88 | I24: =(F24-H24)/H24 -> -0.49996062
A25: Asset Management
A26: Accounts Rec. Turnover | C26: =C4/C11 -> 53.571902 | D26: =D4/D11 -> 58.58546 | E26: =(C26-D26)/D26 -> -0.085576829 | F26: =F4/F11 -> 55.844328 | G26: =(D26-F26)/F26 -> 0.049085234 | H26: =H4/H11 -> 38.97067 | I26: =(F26-H26)/H26 -> 0.43298351
A27: Inventory Turnover | C27: =C4/C12 -> 231.17797 | D27: =D4/D12 -> 251.12312 | E27: =(C27-D27)/D27 -> -0.079423792 | F27: =F4/F12 -> 242.07037 | G27: =(D27-F27)/F27 -> 0.037397211 | H27: =H4/H12 -> 229.88303 | I27: =(F27-H27)/H27 -> 0.053015367
A28: Total Asset Turnover | C28: =C4/C14 -> 1.2291824 | D28: =D4/D14 -> 1.2271517 | E28: =(C28-D28)/D28 -> 0.0016548474 | F28: =F4/F14 -> 1.2464309 | G28: =(D28-F28)/F28 -> -0.015467522 | H28: =H4/H14 -> 1.1343913 | I28: =(F28-H28)/H28 -> 0.098766256
A29: Debt Management
A30: Debt to Equity Ratio | C30: =C16/C18 -> 0.0027355665 | D30: =D16/D18 -> 0.0032656154 | E30: =(C30-D30)/D30 -> -0.1623121 | F30: =F16/F18 -> 1.4759166 | G30: =(D30-F30)/F30 -> -0.9977874 | H30: =H16/H18 -> 1.4372957 | I30: =(F30-H30)/H30 -> 0.026870531
A31: Equity multiplier | C31: =C14/C18 -> 2.5179166 | D31: =D14/D18 -> 2.6269786 | E31: =(C31-D31)/D31 -> -0.041516122 | F31: =F14/F18 -> 2.9254398 | G31: =(D31-F31)/F31 -> -0.1020227 | H31: =H14/H18 -> 2.8959027 | I31: =(F31-H31)/H31 -> 0.010199622
A32: Profitability
A33: Net Profit Margin | C33: 0.1356 | D33: 0.1245 | E33: =(C33-D33)/D33 -> 0.089156627 | F33: 0.2388 | G33: =(D33-F33)/F33 -> -0.47864322 | H33: 0.2262 | I33: =(F33-H33)/H33 -> 0.055702918
A34: Gross Profit Margin | C34: 0.2667 | D34: 0.262 | E34: =(C34-D34)/D34 -> 0.017938931 | F34: 0.1041 | G34: =(D34-F34)/F34 -> 1.5168108 | H34: 0.0865 | I34: =(F34-H34)/H34 -> 0.20346821
A35: Return On Assets ROA | C35: =C33*C28 -> 0.16667714 | D35: =D33*D28 -> 0.15278039 | E35: =(C35-D35)/D35 -> 0.090959015 | F35: =F33*F28 -> 0.2976477 | G35: =(D35-F35)/F35 -> -0.48670731 | H35: =H33*H28 -> 0.25659931 | I35: =(F35-H35)/H35 -> 0.15997074
A36: Return On Equity ROE | C36: =C35*C31 -> 0.41967913 | D36: =D35*D31 -> 0.4013508 | E36: =(C36-D36)/D36 -> 0.045666627 | F36: =F35*F31 -> 0.87075042 | G36: =(D36-F36)/F36 -> -0.53907482 | H36: =H35*H31 -> 0.74308665 | I36: =(F36-H36)/H36 -> 0.17180201
A37: Market Value
A38: EPS | C38: =C9/C19 -> 1.1211468 | D38: =D9/D19 -> 0.89183245 | E38: =(C38-D38)/D38 -> 0.25712715 | F38: =F9/F19 -> 0.6456547 | G38: =(D38-F38)/F38 -> 0.38128391 | H38: =H9/H19 -> 0.46422579 | I38: =(F38-H38)/H38 -> 0.3908204
A39: P/E | C39: =C3/C38 -> 53.596907 | D39: =D3/D38 -> 51.28766 | E39: =(C39-D39)/D39 -> 0.04502538 | F39: =F3/F38 -> 42.97963 | G39: =(D39-F39)/F39 -> 0.19330159 | H39: =H3/H38 -> 75.265098 | I39: =(F39-H39)/H39 -> -0.42895671
A40: Book Value Per Share | C40: =C18/C19 -> 2.6715217 | D40: =D18/D19 -> 2.2225843 | E40: =(C40-D40)/D40 -> 0.20198891 | F40: =F18/F19 -> 1.7005041 | G40: =(D40-F40)/F40 -> 0.30701496 | H40: =H18/H19 -> 1.6332788 | I40: =(F40-H40)/H40 -> 0.041159712
A41: Market Capitalization (Stock Price * Shares) | C41: =C3*C19 -> 82223.551 | D41: =D3*D19 -> 63019.2 | E41: =(C41-D41)/D41 -> 0.30473809 | F41: =F3*F19 -> 38642.985 | G41: =(D41-F41)/F41 -> 0.63080569 | H41: =H3*H19 -> 49146.604 | I41: =(F41-H41)/H41 -> -0.21372014
A42: Cash Per Share | C42: =C10/C19 -> 1.0398804 | D42: =D10/D19 -> 0.94025128 | E42: =(C42-D42)/D42 -> 0.10596015 | F42: =F10/F19 -> 0.64568343 | G42: =(D42-F42)/F42 -> 0.45621095 | H42: =H10/H19 -> 0.76519266 | I42: =(F42-H42)/H42 -> -0.15618189
A43: Revenue Per Share | C43: =C4/C19 -> 8.2683032 | D43: =D4/D19 -> 7.1649477 | E43: =(C43-D43)/D43 -> 0.15399352 | F43: =F4/F19 -> 6.2006477 | G43: =(D43-F43)/F43 -> 0.15551601 | H43: =H4/H19 -> 5.3654628 | I43: =(F43-H43)/H43 -> 0.15565944
A44: Price to Book Value | C44: =C3/C40 -> 22.492799 | D44: =D3/D40 -> 20.579647 | E44: =(C44-D44)/D44 -> 0.092963313 | F44: =F3/F40 -> 16.31869 | G44: =(D44-F44)/F44 -> 0.26110897 | H44: =H3/H40 -> 21.392551 | I44: =(F44-H44)/H44 -> -0.23717884

Sheet S24-21
A1: In the Millions | G1: In the Millions
A3: Income Statement | B3: Dec '24 | C3: Dec '23 | D3: Dec '22 | E3: Dec '21 | G3: Balance Sheet | H3: Dec '24 | I3: Dec '23 | J3: Dec '22 | K3: Dec '21
A4: Revenue | B4: 1252.61 | C4: 1087.53 | D4: 900.49 | E4: 739.89 | G4: Cash and Short Term Investments | H4: 320.71 | I4: 293.21 | J4: 311.23 | K4: 382.41
A5: Revenue Growth | B5: 0.1518 | C5: 0.2077 | D5: 0.217 | E5: 0.4151 | G5: Receivables | H5: 19.69 | I5: 16.85 | J5: 13.88 | K5: 13.66
A6: Cost of Revenue | B6: 950.14 | C6: 838.59 | D6: 717.1 | E6: 594.64 | G6: Inventory | H6: 6.01 | I6: 5.4 | J6: 4.18 | K6: 3.85
A7: Gross Profit | B7: 302.47 | C7: 248.94 | D7: 183.39 | E7: 145.26 | G7: Other current assets | H7: — | I7: — | J7: 15 | K7: 10
A8: SG&A Expenses | B8: 149.05 | C8: 129.54 | D8: 120.01 | E8: 87.2 | G8: Total current assets | H8: 368.22 | I8: 334.43 | J8: 343.99 | K8: 409.68
A9: Operating Income | B9: 3.04 | C9: 5.92 | D9: -26.89 | E9: -15.85 | G9: Property, Plant, Equipment (Net) | H9: 551.6 | I9: 531 | J9: 467.03 | K9: 389.39
A10: Interest Expense (Operating) | B10: — | C10: — | D10: 1.52 | E10: 1.58 | G10: Long-Term Investments | H10: — | I10: — | J10: — | K10: —
A11: Non-operating Income/Expense | B11: 11.21 | C11: 11.06 | D11: 2.61 | E11: -1.48 | G11: Goodwill and Intangible Assets (Total) | H11: — | I11: — | J11: 2 | K11: 1
A12: Non-operating Interest Expenses | B12: 2.04 | C12: 1.72 | D12: 1.52 | E12: 1.58 | G12: Long Term Assets (Tax, Deferred) | H12: 341.59 | I12: 326.21 | J12: 317.63 | K12: 298.67
A13: EBT | B13: 14.24 | C13: 16.98 | D13: -24.29 | E13: -17.34 | G13: Long-term assets (Other) | H13: 10.96 | I13: 15.93 | J13: 15.82 | K13: 12.56
A14: Income Tax Provision | B14: 3.42 | C14: -4.01 | D14: -1.18 | E14: -11.32 | G14: Total non-current assets | H14: 1328.76 | I14: 1271.42 | J14: 1167.96 | K14: 1047.89
A15: Income after Tax | B15: 10.82 | C15: 20.99 | D15: -23.11 | E15: -6.02 | G15: Total Assets | H15: 1696.97 | I15: 1605.86 | J15: 1511.95 | K15: 1457.57
A16: Dividends (Preferred) | B16: — | C16: 0 | D16: — | E16: 0 | G16: Accounts Payable | H16: 23.61 | I16: 22.27 | J16: 20.41 | K16: 19.95
A17: Non-Controlling Interest | B17: 0.61 | C17: 0.73 | D17: -1.88 | E17: -1.46 | G17: Accrued Expenses | H17: 63.01 | I17: 54.74 | J17: 47.95 | K17: 36.89
A18: Net Income Common | B18: 10.21 | C18: 20.26 | D18: -21.23 | E18: -4.56 | G18: Current Part of Debt | H18: — | I18: — | J18: 45 | K18: 38
A19: EPS (Basic) | B19: 0.26 | C19: 0.5 | D19: -0.61 | E19: -0.22 | G19: Other current liabilities | H19: 19.54 | I19: 17.1 | J19: 19.55 | K19: 14.5
A20: EPS (Diluted) | B20: 0.24 | C20: 0.47 | D20: -0.61 | E20: -0.22 | G20: Total current liabilities | H20: 187.31 | I20: 164.07 | J20: 147.72 | K20: 121.5
A21: Shares (Basic, Weighted) | B21: 39.83 | C21: 39.42 | D21: 39.24 | E21: 39.09 | G21: Long Term Debt (Total) | H21: 246.68 | I21: 245.64 | J21: 244.59 | K21: 243.54
A22: Shares (Diluted, Weighted) | B22: 44.2 | C22: 43.9 | D22: 39.24 | E22: 39.09 | G22: Non-current Revenue (Deferred) | H22: — | I22: — | J22: 14 | K22: 13
A23: Gross Margin | B23: 0.2415 | C23: 0.2289 | D23: 0.2037 | E23: 0.1963 | G23: Long Term Tax Liability (Deferred) | H23: — | I23: — | J23: -301 | K23: -299
A24: EBIT Margin | B24: 0.0024 | C24: 0.0054 | D24: -0.0299 | E24: -0.0214 | G24: Non-current Liabilities (Other) | H24: 274.85 | I24: 262.25 | J24: 255.58 | K24: 256.82
A25: EBT margin | B25: 0.0114 | C25: 0.0156 | D25: -0.027 | E25: -0.0234 | G25: Total non-current liabilities | H25: 1016.03 | I25: 972.42 | J25: 927.4 | K25: 900.47
A26: Net Profit Margin | B26: 0.0081 | C26: 0.0186 | D26: -0.0236 | E26: -0.0062 | G26: Total liabilities | H26: 1203.35 | I26: 1136.49 | J26: 1075.11 | K26: 1021.97
A27: Free Cash Flow Margin | B27: 0.0285 | C27: -0.0129 | D27: -0.0731 | E27: -0.0582 | G27: Additional Paid In Capital | H27: 442.99 | I27: 426.6 | J27: 415.65 | K27: 405.94
A28: EBITDA | B28: 108.25 | C28: 98.39 | D28: 48.45 | E28: 45.25 | G28: Common Stock (Net) | H28: 0.04 | I28: 0.04 | J28: 0.04 | K28: 0.04
A29: EBIT | B29: 3.04 | C29: 5.92 | D29: -26.89 | E29: -15.85 | G29: Retained Earnings | H29: 26.98 | I29: 16.78 | J29: -3.49 | K29: 3.55
A30: Income from Continuous Operations | B30: 10.82 | C30: 20.99 | D30: -23.11 | E30: -6.02 | G30: Common Equity (Total) | H30: 493.63 | I30: 469.37 | J30: 436.84 | K30: 435.6
A31: Consolidated Net Income/Loss | B31: 10.82 | C31: 20.99 | D31: -23.11 | E31: -6.02 | G31: Shareholders Equity (Total) | H31: 493.63 | I31: 469.37 | J31: 436.84 | K31: 435.6
A32: EPS (Basic, from Continuous Ops) | B32: 0.27 | C32: 0.53 | D32: -0.59 | E32: -0.15 | G32: Shareholders Equity and Liabilities (Total) | H32: 1696.97 | I32: 1605.86 | J32: 1511.95 | K32: 1457.57
A33: EPS (Basic, Consolidated) | B33: 0.27 | C33: 0.53 | D33: -0.59 | E33: -0.15 | G33: Shares (Common) | H33: 42.52 | I33: 42.31 | J33: 42.16 | K33: 42.06
A34: EPS (Diluted, from Cont. Ops) | B34: 0.24 | C34: 0.48 | D34: -0.59 | E34: -0.15 | G34: Shareholders Equity (Tangible) | H34: 493.63 | I34: 469.37 | J34: 436.84 | K34: 435.6
A35: Shares (Diluted, Average) | B35: 44.2 | C35: 43.9 | D35: 39.24 | E35: 39.09 | G35: Net Debt | H35: -74.03 | I35: -47.58 | J35: -21.64 | K35: -100.86
A36: EPS (Diluted, Consolidated) | B36: 0.24 | C36: 0.48 | D36: -0.59 | E36: -0.15 | G36: Total Debt | H36: 246.68 | I36: 245.64 | J36: 289.59 | K36: 281.54
A37: EBITDA Margin | B37: 0.0864 | C37: 0.0905 | D37: 0.0538 | E37: 0.0612
A38: Operating Cash Flow Margin | B38: 0.1366 | C38: 0.1215 | D38: 0.0852 | E38: 0.0789
A39: Cash and Short Term Investments | B39: 320.71 | C39: 293.21 | D39: 311.23 | E39: 382.41
A40: Receivables | B40: 19.69 | C40: 16.85 | D40: 13.88 | E40: 13.66
A41: Inventory | B41: 6.01 | C41: 5.4 | D41: 4.18 | E41: 3.85
A42: Other current assets | B42: — | C42: — | D42: 15 | E42: 10
A43: Total current assets | B43: 368.22 | C43: 334.43 | D43: 343.99 | E43: 409.68
A44: Property, Plant, Equipment (Net) | B44: 551.6 | C44: 531 | D44: 467.03 | E44: 389.39
A45: Long-Term Investments | B45: — | C45: — | D45: — | E45: —
A46: Goodwill and Intangible Assets (Total) | B46: — | C46: — | D46: 2 | E46: 1
A47: Long Term Assets (Tax, Deferred) | B47: 341.59 | C47: 326.21 | D47: 317.63 | E47: 298.67
A48: Long-term assets (Other) | B48: 10.96 | C48: 15.93 | D48: 15.82 | E48: 12.56
A49: Total non-current assets | B49: 1328.76 | C49: 1271.42 | D49: 1167.96 | E49: 1047.89
A50: Total Assets | B50: 1696.97 | C50: 1605.86 | D50: 1511.95 | E50: 1457.57
A51: Accounts Payable | B51: 23.61 | C51: 22.27 | D51: 20.41 | E51: 19.95
A52: Accrued Expenses | B52: 63.01 | C52: 54.74 | D52: 47.95 | E52: 36.89
A53: Current Part of Debt | B53: — | C53: — | D53: 45 | E53: 38
A54: Other current liabilities | B54: 19.54 | C54: 17.1 | D54: 19.55 | E54: 14.5
A55: Total current liabilities | B55: 187.31 | C55: 164.07 | D55: 147.72 | E55: 121.5
A56: Long Term Debt (Total) | B56: 246.68 | C56: 245.64 | D56: 244.59 | E56: 243.54
A57: Non-current Revenue (Deferred) | B57: — | C57: — | D57: 14 | E57: 13
A58: Long Term Tax Liability (Deferred) | B58: — | C58: — | D58: -301 | E58: -299
A59: Non-current Liabilities (Other) | B59: 274.85 | C59: 262.25 | D59: 255.58 | E59: 256.82
A60: Total non-current liabilities | B60: 1016.03 | C60: 972.42 | D60: 927.4 | E60: 900.47
A61: Total liabilities | B61: 1203.35 | C61: 1136.49 | D61: 1075.11 | E61: 1021.97
A62: Additional Paid In Capital | B62: 442.99 | C62: 426.6 | D62: 415.65 | E62: 405.94
A63: Common Stock (Net) | B63: 0.04 | C63: 0.04 | D63: 0.04 | E63: 0.04
A64: Retained Earnings | B64: 26.98 | C64: 16.78 | D64: -3.49 | E64: 3.55
A65: Common Equity (Total) | B65: 493.63 | C65: 469.37 | D65: 436.84 | E65: 435.6
A66: Shareholders Equity (Total) | B66: 493.63 | C66: 469.37 | D66: 436.84 | E66: 435.6
A67: Shareholders Equity and Liabilities (Total) | B67: 1696.97 | C67: 1605.86 | D67: 1511.95 | E67: 1457.57
A68: Shares (Common) | B68: 42.52 | C68: 42.31 | D68: 42.16 | E68: 42.06
A69: Shareholders Equity (Tangible) | B69: 493.63 | C69: 469.37 | D69: 436.84 | E69: 435.6
A70: Net Debt | B70: -74.03 | C70: -47.58 | D70: -21.64 | E70: -100.86
A71: Total Debt | B71: 246.68 | C71: 245.64 | D71: 289.59 | E71: 281.54

Sheet YOY SHAK
A1: Company Name | C1: SHAK | D1: SHAK | E1: YOY % Change 2024 2023 | F1: SHAK | G1: YOY % Change 2023 2022 | H1: SHAK | I1: YOY % Change 2022 2021
A2: Year ending: | C2: 2024 | D2: 2023 | F2: 2022 | H2: 2021
A3: Stock Price | C3: 129.51 | D3: 74.12 | E3: =+(C3-D3)/D3 -> 0.74730167 | F3: 41.53 | G3: =+(D3-F3)/F3 -> 0.78473393 | H3: 73.07 | I3: =(F3-H3)/H3 -> -0.43164089
A4: Revenue | C4: =_xlfn.XLOOKUP(A4,'S24-21'!$A$4:$A$71,'S24-21'!$B$4:$B$71,"LOOK",0) -> 1252.61 | D4: =_xlfn.XLOOKUP(A4,'S24-21'!$A$4:$A$71,'S24-21'!$C$4:$C$71,"LOOK",0) -> 1087.53 | E4: =+(C4-D4)/D4 -> 0.15179351 | F4: =_xlfn.XLOOKUP(A4,'S24-21'!$A$4:$A$71,'S24-21'!$D$4:$D$71) -> 900.49 | G4: =+(D4-F4)/F4 -> 0.20770914 | H4: =_xlfn.XLOOKUP(A4,'S24-21'!$A$4:$A$71,'S24-21'!$E$4:$E$71) -> 739.89 | I4: =(F4-H4)/H4 -> 0.21705929
A5: Cost of Revenue | C5: =_xlfn.XLOOKUP(A5,'S24-21'!$A$4:$A$71,'S24-21'!$B$4:$B$71,"LOOK",0) -> 950.14 | D5: =_xlfn.XLOOKUP(A5,'S24-21'!$A$4:$A$71,'S24-21'!$C$4:$C$71,"LOOK",0) -> 838.59 | E5: =+(C5-D5)/D5 -> 0.1330209 | F5: =_xlfn.XLOOKUP(A5,'S24-21'!$A$4:$A$71,'S24-21'!$D$4:$D$71) -> 717.1 | G5: =+(D5-F5)/F5 -> 0.16941849 | H5: =_xlfn.XLOOKUP(A5,'S24-21'!$A$4:$A$71,'S24-21'!$E$4:$E$71) -> 594.64 | I5: =(F5-H5)/H5 -> 0.20593973
A6: Gross Profit | C6: =_xlfn.XLOOKUP(A6,'S24-21'!$A$4:$A$71,'S24-21'!$B$4:$B$71,"LOOK",0) -> 302.47 | D6: =_xlfn.XLOOKUP(A6,'S24-21'!$A$4:$A$71,'S24-21'!$C$4:$C$71,"LOOK",0) -> 248.94 | E6: =+(C6-D6)/D6 -> 0.21503173 | F6: =_xlfn.XLOOKUP(A6,'S24-21'!$A$4:$A$71,'S24-21'!$D$4:$D$71) -> 183.39 | G6: =+(D6-F6)/F6 -> 0.35743497 | H6: =_xlfn.XLOOKUP(A6,'S24-21'!$A$4:$A$71,'S24-21'!$E$4:$E$71) -> 145.26 | I6: =(F6-H6)/H6 -> 0.26249484
A7: SG&A Expenses | C7: =_xlfn.XLOOKUP(A7,'S24-21'!$A$4:$A$71,'S24-21'!$B$4:$B$71,"LOOK",0) -> 149.05 | D7: =_xlfn.XLOOKUP(A7,'S24-21'!$A$4:$A$71,'S24-21'!$C$4:$C$71,"LOOK",0) -> 129.54 | E7: =+(C7-D7)/D7 -> 0.15060985 | F7: =_xlfn.XLOOKUP(A7,'S24-21'!$A$4:$A$71,'S24-21'!$D$4:$D$71) -> 120.01 | G7: =+(D7-F7)/F7 -> 0.079410049 | H7: =_xlfn.XLOOKUP(A7,'S24-21'!$A$4:$A$71,'S24-21'!$E$4:$E$71) -> 87.2 | I7: =(F7-H7)/H7 -> 0.37626147
A8: Operating Income | C8: =_xlfn.XLOOKUP(A8,'S24-21'!$A$4:$A$71,'S24-21'!$B$4:$B$71,"LOOK",0) -> 3.04 | D8: =_xlfn.XLOOKUP(A8,'S24-21'!$A$4:$A$71,'S24-21'!$C$4:$C$71,"LOOK",0) -> 5.92 | E8: =+(C8-D8)/D8 -> -0.48648649 | F8: =_xlfn.XLOOKUP(A8,'S24-21'!$A$4:$A$71,'S24-21'!$D$4:$D$71) -> -26.89 | G8: =+(D8-F8)/F8 -> -1.2201562 | H8: =_xlfn.XLOOKUP(A8,'S24-21'!$A$4:$A$71,'S24-21'!$E$4:$E$71) -> -15.85 | I8: =(F8-H8)/H8 -> 0.69652997
A9: Net Income Common | C9: =_xlfn.XLOOKUP(A9,'S24-21'!$A$4:$A$71,'S24-21'!$B$4:$B$71,"LOOK",0) -> 10.21 | D9: =_xlfn.XLOOKUP(A9,'S24-21'!$A$4:$A$71,'S24-21'!$C$4:$C$71,"LOOK",0) -> 20.26 | E9: =+(C9-D9)/D9 -> -0.49605133 | F9: =_xlfn.XLOOKUP(A9,'S24-21'!$A$4:$A$71,'S24-21'!$D$4:$D$71) -> -21.23 | G9: =+(D9-F9)/F9 -> -1.9543099 | H9: =_xlfn.XLOOKUP(A9,'S24-21'!$A$4:$A$71,'S24-21'!$E$4:$E$71) -> -4.56 | I9: =(F9-H9)/H9 -> 3.6557018
A10: Cash and Short Term Investments | C10: =_xlfn.XLOOKUP(A10,'S24-21'!$A$4:$A$71,'S24-21'!$B$4:$B$71,"LOOK",0) -> 320.71 | D10: =_xlfn.XLOOKUP(A10,'S24-21'!$A$4:$A$71,'S24-21'!$C$4:$C$71,"LOOK",0) -> 293.21 | E10: =+(C10-D10)/D10 -> 0.093789434 | F10: =_xlfn.XLOOKUP(A10,'S24-21'!$A$4:$A$71,'S24-21'!$D$4:$D$71) -> 311.23 | G10: =+(D10-F10)/F10 -> -0.057899303 | H10: =_xlfn.XLOOKUP(A10,'S24-21'!$A$4:$A$71,'S24-21'!$E$4:$E$71) -> 382.41 | I10: =(F10-H10)/H10 -> -0.1861353
A11: Receivables | C11: =_xlfn.XLOOKUP(A11,'S24-21'!$A$4:$A$71,'S24-21'!$B$4:$B$71,"LOOK",0) -> 19.69 | D11: =_xlfn.XLOOKUP(A11,'S24-21'!$A$4:$A$71,'S24-21'!$C$4:$C$71,"LOOK",0) -> 16.85 | E11: =+(C11-D11)/D11 -> 0.16854599 | F11: =_xlfn.XLOOKUP(A11,'S24-21'!$A$4:$A$71,'S24-21'!$D$4:$D$71) -> 13.88 | G11: =+(D11-F11)/F11 -> 0.21397695 | H11: =_xlfn.XLOOKUP(A11,'S24-21'!$A$4:$A$71,'S24-21'!$E$4:$E$71) -> 13.66 | I11: =(F11-H11)/H11 -> 0.016105417
A12: Inventory | C12: =_xlfn.XLOOKUP(A12,'S24-21'!$A$4:$A$71,'S24-21'!$B$4:$B$71,"LOOK",0) -> 6.01 | D12: =_xlfn.XLOOKUP(A12,'S24-21'!$A$4:$A$71,'S24-21'!$C$4:$C$71,"LOOK",0) -> 5.4 | E12: =+(C12-D12)/D12 -> 0.11296296 | F12: =_xlfn.XLOOKUP(A12,'S24-21'!$A$4:$A$71,'S24-21'!$D$4:$D$71) -> 4.18 | G12: =+(D12-F12)/F12 -> 0.29186603 | H12: =_xlfn.XLOOKUP(A12,'S24-21'!$A$4:$A$71,'S24-21'!$E$4:$E$71) -> 3.85 | I12: =(F12-H12)/H12 -> 0.085714286
A13: Total current assets | C13: =_xlfn.XLOOKUP(A13,'S24-21'!$A$4:$A$71,'S24-21'!$B$4:$B$71,"LOOK",0) -> 368.22 | D13: =_xlfn.XLOOKUP(A13,'S24-21'!$A$4:$A$71,'S24-21'!$C$4:$C$71,"LOOK",0) -> 334.43 | E13: =+(C13-D13)/D13 -> 0.10103759 | F13: =_xlfn.XLOOKUP(A13,'S24-21'!$A$4:$A$71,'S24-21'!$D$4:$D$71) -> 343.99 | G13: =+(D13-F13)/F13 -> -0.027791506 | H13: =_xlfn.XLOOKUP(A13,'S24-21'!$A$4:$A$71,'S24-21'!$E$4:$E$71) -> 409.68 | I13: =(F13-H13)/H13 -> -0.16034466
A14: Total Assets | C14: =_xlfn.XLOOKUP(A14,'S24-21'!$A$4:$A$71,'S24-21'!$B$4:$B$71,"LOOK",0) -> 1696.97 | D14: =_xlfn.XLOOKUP(A14,'S24-21'!$A$4:$A$71,'S24-21'!$C$4:$C$71,"LOOK",0) -> 1605.86 | E14: =+(C14-D14)/D14 -> 0.056735955 | F14: =_xlfn.XLOOKUP(A14,'S24-21'!$A$4:$A$71,'S24-21'!$D$4:$D$71) -> 1511.95 | G14: =+(D14-F14)/F14 -> 0.062111842 | H14: =_xlfn.XLOOKUP(A14,'S24-21'!$A$4:$A$71,'S24-21'!$E$4:$E$71) -> 1457.57 | I14: =(F14-H14)/H14 -> 0.037308671
A15: Total current liabilities | C15: =_xlfn.XLOOKUP(A15,'S24-21'!$A$4:$A$71,'S24-21'!$B$4:$B$71,"LOOK",0) -> 187.31 | D15: =_xlfn.XLOOKUP(A15,'S24-21'!$A$4:$A$71,'S24-21'!$C$4:$C$71,"LOOK",0) -> 164.07 | E15: =+(C15-D15)/D15 -> 0.14164686 | F15: =_xlfn.XLOOKUP(A15,'S24-21'!$A$4:$A$71,'S24-21'!$D$4:$D$71) -> 147.72 | G15: =+(D15-F15)/F15 -> 0.11068237 | H15: =_xlfn.XLOOKUP(A15,'S24-21'!$A$4:$A$71,'S24-21'!$E$4:$E$71) -> 121.5 | I15: =(F15-H15)/H15 -> 0.21580247
... A19: Shares (Basic, Weighted) | C19: =_xlfn.XLOOKUP(A19,'S24-21'!$A$4:$A$71,'S24-21'!$B$4:$B$71,"LOOK",0) -> 39.83 | D19: =_xlfn.XLOOKUP(A19,'S24-21'!$A$4:$A$71,'S24-21'!$C$4:$C$71,"LOOK",0) -> 39.42 | E19: =+(C19-D19)/D19 -> 0.010400812 | F19: =_xlfn.XLOOKUP(A19,'S24-21'!$A$4:$A$71,'S24-21'!$D$4:$D$71) -> 39.24 | G19: =+(D19-F19)/F19 -> 0.004587156 | H19: =_xlfn.XLOOKUP(A19,'S24-21'!$A$4:$A$71,'S24-21'!$E$4:$E$71) -> 39.09 | I19: =(F19-H19)/H19 -> 0.0038372985
A20: Financial Ratio's | C20: SHAK | D20: SHAK | E20: YOY % Change 2024 2023 | F20: SHAK | G20: YOY % Change 2023 2022 | H20: SHAK | I20: YOY % Change 2022 2021
A21: Liquidity | C21: 2024 | D21: 2023 | F21: 2022 | H21: 2021
A22: Current Ratio | C22: =C13/C15 -> 1.965832 | D22: =D13/D15 -> 2.0383373 | E22: =(C22-D22)/D22 -> -0.035570782 | F22: =F13/F15 -> 2.3286623 | G22: =(D22-F22)/F22 -> -0.1246746 | H22: =H13/H15 -> 3.3718519 | I22: =(F22-H22)/H22 -> -0.30938178
A23: Quick Ratio | C23: =(C13-C12)/C15 -> 1.9337462 | D23: =(D13-D12)/D15 -> 2.0054245 | E23: =(C23-D23)/D23 -> -0.035742217 | F23: =(F13-F12)/F15 -> 2.3003656 | G23: =(D23-F23)/F23 -> -0.12821486 | H23: =(H13-H12)/H15 -> 3.3401646 | I23: =(F23-H23)/H23 -> -0.31130174
A24: Net Working Capital | C24: =C13-C15 -> 180.91 | D24: =D13-D15 -> 170.36 | E24: =(C24-D24)/D24 -> 0.061927683 | F24: =F13-F15 -> 196.27 | G24: =(D24-F24)/F24 -> -0.13201202 | H24: =H13-H15 -> 288.18 | I24: =(F24-H24)/H24 -> -0.31893261
A25: Asset Management
A26: Accounts Rec. Turnover | C26: =C4/C11 -> 63.616557 | D26: =D4/D11 -> 64.54184 | E26: =(C26-D26)/D26 -> -0.014336175 | F26: =F4/F11 -> 64.876801 | G26: =(D26-F26)/F26 -> -0.005163038 | H26: =H4/H11 -> 54.164714 | I26: =(F26-H26)/H26 -> 0.19776873
A27: Inventory Turnover | C27: =C4/C12 -> 208.42097 | D27: =D4/D12 -> 201.39444 | E27: =(C27-D27)/D27 -> 0.034889347 | F27: =F4/F12 -> 215.42823 | G27: =(D27-F27)/F27 -> -0.065143669 | H27: =H4/H12 -> 192.17922 | I27: =(F27-H27)/H27 -> 0.12097566
A28: Total Asset Turnover | C28: =C4/C14 -> 0.73814505 | D28: =D4/D14 -> 0.67722591 | E28: =(C28-D28)/D28 -> 0.089953937 | F28: =F4/F14 -> 0.59558186 | G28: =(D28-F28)/F28 -> 0.13708283 | H28: =H4/H14 -> 0.50761885 | I28: =(F28-H28)/H28 -> 0.17328557
A29: Debt Management
A30: Debt to Equity Ratio | C30: =C16/C18 -> 0.49972652 | D30: =D16/D18 -> 0.5233398 | E30: =(C30-D30)/D30 -> -0.04512036 | F30: =F16/F18 -> 0.55990752 | G30: =(D30-F30)/F30 -> -0.065310289 | H30: =H16/H18 -> 0.55909091 | I30: =(F30-H30)/H30 -> 0.0014606006
A31: Equity multiplier | C31: =C14/C18 -> 3.4377368 | D31: =D14/D18 -> 3.4213094 | E31: =(C31-D31)/D31 -> 0.0048014809 | F31: =F14/F18 -> 3.461107 | G31: =(D31-F31)/F31 -> -0.011498525 | H31: =H14/H18 -> 3.3461203 | I31: =(F31-H31)/H31 -> 0.0343642
A32: Profitability
A33: Net Profit Margin | C33: 0.0081 | D33: 0.0186 | E33: =(C33-D33)/D33 -> -0.56451613 | F33: -0.0236 | G33: =(D33-F33)/F33 -> -1.7881356 | H33: -0.0062 | I33: =(F33-H33)/H33 -> 2.8064516
A34: Gross Profit Margin | C34: 0.2415 | D34: 0.2289 | E34: =(C34-D34)/D34 -> 0.055045872 | F34: 0.2037 | G34: =(D34-F34)/F34 -> 0.12371134 | H34: 0.1963 | I34: =(F34-H34)/H34 -> 0.037697402
A35: Return On Assets ROA | C35: =C33*C28 -> 0.0059789749 | D35: =D33*D28 -> 0.012596402 | E35: =(C35-D35)/D35 -> -0.52534264 | F35: =F33*F28 -> -0.014055732 | G35: =(D35-F35)/F35 -> -1.8961754 | H35: =H33*H28 -> -0.0031472368 | I35: =(F35-H35)/H35 -> 3.4660547
A36: Return On Equity ROE | C36: =C35*C31 -> 0.020554142 | D36: =D35*D31 -> 0.043096189 | E36: =(C36-D36)/D36 -> -0.52306358 | F36: =F35*F31 -> -0.048648393 | G36: =(D36-F36)/F36 -> -1.8858708 | H36: =H35*H31 -> -0.010531033 | I36: =(F36-H36)/H36 -> 3.6195271
A37: Market Value
A38: EPS | C38: =C9/C19 -> 0.25633944 | D38: =D9/D19 -> 0.51395231 | E38: =(C38-D38)/D38 -> -0.50123885 | F38: =F9/F19 -> -0.54102956 | G38: =(D38-F38)/F38 -> -1.9499524 | H38: =H9/H19 -> -0.11665388 | I38: =(F38-H38)/H38 -> 3.6379047
A39: P/E | C39: =C3/C38 -> 505.22853 | D39: =D3/D38 -> 144.21572 | E39: =(C39-D39)/D39 -> 2.5032835 | F39: =F3/F38 -> -76.761055 | G39: =(D39-F39)/F39 -> -2.8787615 | H39: =H3/H38 -> -626.38296 | I39: =(F39-H39)/H39 -> -0.87745348
A40: Book Value Per Share | C40: =C18/C19 -> 12.393422 | D40: =D18/D19 -> 11.9069 | E40: =(C40-D40)/D40 -> 0.040860509 | F40: =F18/F19 -> 11.132518 | G40: =(D40-F40)/F40 -> 0.069560384 | H40: =H18/H19 -> 11.143515 | I40: =(F40-H40)/H40 -> -0.00098686335
A41: Market Capitalization (Stock Price * Shares) | C41: =C3*C19 -> 5158.3833 | D41: =D3*D19 -> 2921.8104 | E41: =(C41-D41)/D41 -> 0.76547503 | F41: =F3*F19 -> 1629.6372 | G41: =(D41-F41)/F41 -> 0.79292078 | H41: =H3*H19 -> 2856.3063 | I41: =(F41-H41)/H41 -> -0.42945993
A42: Cash Per Share | C42: =C10/C19 -> 8.0519709 | D42: =D10/D19 -> 7.4381025 | E42: =(C42-D42)/D42 -> 0.082530241 | F42: =F10/F19 -> 7.9314475 | G42: =(D42-F42)/F42 -> -0.062201132 | H42: =H10/H19 -> 9.7828089 | I42: =(F42-H42)/H42 -> -0.1892464
A43: Revenue Per Share | C43: =C4/C19 -> 31.448908 | D43: =D4/D19 -> 27.58828 | E43: =(C43-D43)/D43 -> 0.13993724 | F43: =F4/F19 -> 22.948267 | G43: =(D43-F43)/F43 -> 0.20219448 | H43: =H4/H19 -> 18.927859 | I43: =(F43-H43)/H43 -> 0.21240693
A44: Price to Book Value | C44: =C3/C40 -> 10.449898 | D44: =D3/D40 -> 6.224962 | E44: =(C44-D44)/D44 -> 0.67870878 | F44: =F3/F40 -> 3.7305128 | G44: =(D44-F44)/F44 -> 0.66866121 | H44: =H3/H40 -> 6.557177 | I44: =(F44-H44)/H44 -> -0.43107945

Sheet M24-21
A1: In the Millions | G1: In the Millions
A3: Income Statement | B3: Dec '24 | C3: Dec '23 | D3: Dec '22 | E3: Dec '21 | G3: Balance Sheet | H3: Dec '24 | I3: Dec '23 | J3: Dec '22 | K3: Dec '21
A4: Revenue | B4: 25920 | C4: 25494 | D4: 23183 | E4: 23222.9 | G4: Cash and Short Term Investments | H4: 1085 | I4: 4579 | J4: 2583.8 | K4: 4709.2
A5: Revenue Growth | B5: 0.0167 | C5: 0.0997 | D5: -0.0017 | E5: 0.209 | G5: Receivables | H5: 2383 | I5: 2488 | J5: 2115 | K5: 1872.4
A6: Cost of Revenue | B6: 11210 | C6: 10931 | D6: 9975 | E6: 10642.7 | G6: Inventory | H6: 56 | I6: 53 | J6: 52 | K6: 55.6
A7: Gross Profit | B7: 14710 | C7: 14563 | D7: 13208 | E7: 12580.2 | G7: Other current assets | H7: 1130 | I7: 919.1 | J7: 673 | K7: 511
A8: SG&A Expenses | B8: 2412 | C8: 2435 | D8: 2492 | E8: 2707.5 | G8: Total current assets | H8: 4599 | I8: 7986 | J8: 5424.2 | K8: 7148.5
A9: Operating Income | B9: 11712 | C9: 11647 | D9: 9372 | E9: 10356 | G9: Property, Plant, Equipment (Net) | H9: 25295 | I9: 24908 | J9: 23773.6 | K9: 24720.6
A10: Interest Expense (Operating) | B10: — | C10: — | D10: 1299 | E10: 1194 | G10: Long-Term Investments | H10: 2710 | I10: 1080 | J10: 1064.5 | K10: 1201.2
A11: Non-operating Income/Expense | B11: -1367 | C11: -1125 | D11: -1546 | E11: -1228.1 | G11: Goodwill and Intangible Assets (Total) | H11: 3145 | I11: 3040 | J11: 2900.4 | K11: 2782.5
A12: Non-operating Interest Expenses | B12: 1506 | C12: 1361 | D12: 1207 | E12: 1185.8 | G12: Long-term assets (Other) | H12: 6095 | I12: 5618 | J12: 4707.2 | K12: 4449.5
A13: EBT | B13: 10345 | C13: 10522 | D13: 7825 | E13: 9127.9 | G13: Total non-current assets | H13: 50584 | I13: 48160 | J13: 45011.4 | K13: 46705.8
A14: Income Tax Provision | B14: 2121 | C14: 2053 | D14: 1648 | E14: 1582.7 | G14: Total Assets | H14: 55182 | I14: 56147 | J14: 50435.6 | K14: 53854.3
A15: Income after Tax | B15: 8224 | C15: 8469 | D15: 6177 | E15: 7545.2 | G15: Accounts Payable | H15: 1029 | I15: 1103 | J15: 980.2 | K15: 1006.8
A16: Dividends (Preferred) | B16: 1 | C16: 0 | D16: — | E16: — | G16: Accrued Expenses | H16: 1611 | I16: 1903 | J16: 1630.8 | K16: 1710.3
A17: Net Income Common | B17: 8223 | C17: 8469 | D17: 6177 | E17: 7545.2 | G17: Current Part of Debt | H17: — | I17: 2192 | J17: 661 | K17: 706
A18: EPS (Basic) | B18: 11.39 | C18: 11.56 | D18: 8.33 | E18: 10.04 | G18: Current Part of Taxes to Pay | H18: 361 | I18: 705 | J18: 274.9 | K18: 360.7
A19: EPS (Diluted) | B19: 11.39 | C19: 11.56 | D19: 8.33 | E19: 10.04 | G19: Other current liabilities | H19: — | I19: — | J19: 1886 | K19: 1947
A20: Shares (Basic, Weighted) | B20: 718.3 | C20: 727.9 | D20: 736.5 | E20: 746.3 | G20: Total current liabilities | H20: 3861 | I20: 6859 | J20: 3802.1 | K20: 4020
A21: Shares (Diluted, Weighted) | B21: 721.9 | C21: 732.3 | D21: 741.3 | E21: 751.8 | G21: Long Term Debt (Total) | H21: 38424 | I21: 37153 | J21: 35903.5 | K21: 35622.7
A22: Gross Profit Margin | B22: 0.5675 | C22: 0.5712 | D22: 0.5697 | E22: 0.5417 | G22: Non-current Revenue (Deferred) | H22: 778 | I22: 790 | J22: 757.8 | K22: 738.3
A23: EBIT Margin | B23: 0.4519 | C23: 0.4569 | D23: 0.4043 | E23: 0.4459 | G23: Long Term Tax Liability (Deferred) | H23: 1914 | I23: 1681 | J23: 1997.5 | K23: 2075.6
A24: EBT margin | B24: 0.3991 | C24: 0.4127 | D24: 0.3375 | E24: 0.3931 | G24: Non-current Liabilities (Other) | H24: 1115 | I24: 1313 | J24: 1843.7 | K24: 2977.8
A25: Net Profit Margin | B25: 0.3172 | C25: 0.3322 | D25: 0.2664 | E25: 0.3249 | G25: Total non-current liabilities | H25: 55119 | I25: 53995 | J25: 52636.9 | K25: 54435.3
A26: Free Cash Flow Margin | B26: 0.2621 | C26: 0.2883 | D26: 0.2384 | E26: 0.3104 | G26: Total liabilities | H26: 58979 | I26: 60854 | J26: 56439 | K26: 58455.3
A27: EBITDA | B27: 13809 | C27: 13625 | D27: 11243 | E27: 12224.1 | G27: Additional Paid In Capital | H27: 9281 | I27: 8893 | J27: 8547.1 | K27: 8231.6
A28: EBIT | B28: 11712 | C28: 11647 | D28: 9372 | E28: 10356 | G28: Common Stock (Net) | H28: 17 | I28: 17 | J28: 16.6 | K28: 16.6
A29: Income from Continuous Operations | B29: 8224 | C29: 8469 | D29: 6177 | E29: 7545.2 | G29: Retained Earnings | H29: 66834 | I29: 63480 | J29: 59543.9 | K29: 57534.7
A30: Consolidated Net Income/Loss | B30: 8224 | C30: 8469 | D30: 6177 | E30: 7545.2 | G30: Treasury Stock | H30: 77375 | I30: 74640 | J30: 71624.4 | K30: 67810.2
A31: EPS (Basic, from Continuous Ops) | B31: 11.45 | C31: 11.63 | D31: 8.39 | E31: 10.11 | G31: Common Equity (Total) | H31: -3796 | I31: -4706 | J31: -6003.4 | K31: -4601.01
... A37: Operating Cash Flow Margin | B37: 0.3645 | C37: 0.377 | D37: 0.3186 | E37: 0.3936 | G37: Total Debt | H37: 38424 | I37: 39345 | J37: 36564.5 | K37: 36328.7
A38: Cash and Short Term Investments | B38: 1085 | C38: 4579 | D38: 2583.8 | E38: 4709.2
A39: Receivables | B39: 2383 | C39: 2488 | D39: 2115 | E39: 1872.4 | G39: © 2016–2025 stockrow.comTerms and Conditions
A40: Inventory | B40: 56 | C40: 53 | D40: 52 | E40: 55.6
A41: Other current assets | B41: 1130 | C41: 919.1 | D41: 673 | E41: 511
A42: Total current assets | B42: 4599 | C42: 7986 | D42: 5424.2 | E42: 7148.5
A43: Property, Plant, Equpment (Net) | B43: 25295 | C43: 24908 | D43: 23773.6 | E43: 24720.6
A44: Long-Term Investments | B44: 2710 | C44: 1080 | D44: 1064.5 | E44: 1201.2
A45: Goodwill and Intangible Assets (Total) | B45: 3145 | C45: 3040 | D45: 2900.4 | E45: 2782.5
A46: Long-term assets (Other) | B46: 6095 | C46: 5618 | D46: 4707.2 | E46: 4449.5
A47: Total non-current assets | B47: 50584 | C47: 48160 | D47: 45011.4 | E47: 46705.8
A48: Total Assets | B48: 55182 | C48: 56147 | D48: 50435.6 | E48: 53854.3
A49: Accounts Payable | B49: 1029 | C49: 1103 | D49: 980.2 | E49: 1006.8
A50: Accrued Expenses | B50: 1611 | C50: 1903 | D50: 1630.8 | E50: 1710.3
A51: Current Part of Debt | B51: — | C51: 2192 | D51: 661 | E51: 706
A52: Current Part of Taxes to Pay | B52: 361 | C52: 705 | D52: 274.9 | E52: 360.7
A53: Other current liabilities | B53: — | C53: — | D53: 1886 | E53: 1947
A54: Total current liabilities | B54: 3861 | C54: 6859 | D54: 3802.1 | E54: 4020
A55: Long Term Debt (Total) | B55: 38424 | C55: 37153 | D55: 35903.5 | E55: 35622.7
A56: Non-current Revenue (Deferred) | B56: 778 | C56: 790 | D56: 757.8 | E56: 738.3
A57: Long Term Tax Liability (Deferred) | B57: 1914 | C57: 1681 | D57: 1997.5 | E57: 2075.6
A58: Non-current Liabilities (Other) | B58: 1115 | C58: 1313 | D58: 1843.7 | E58: 2977.8
A59: Total non-current liabilities | B59: 55119 | C59: 53995 | D59: 52636.9 | E59: 54435.3
A60: Total liabilities | B60: 58979 | C60: 60854 | D60: 56439 | E60: 58455.3
A61: Additional Paid In Capital | B61: 9281 | C61: 8893 | D61: 8547.1 | E61: 8231.6
A62: Common Stock (Net) | B62: 17 | C62: 17 | D62: 16.6 | E62: 16.6
A63: Retained Earnings | B63: 66834 | C63: 63480 | D63: 59543.9 | E63: 57534.7
A64: Treasury Stock | B64: 77375 | C64: 74640 | D64: 71624.4 | E64: 67810.2
A65: Common Equity (Total) | B65: -3796 | C65: -4706 | D65: -6003.4 | E65: -4601.01
... A71: Total Debt | B71: 38424 | C71: 39345 | D71: 36564.5 | E71: 36328.7

Sheet YOY MCD
A1: Company Name | C1: MCD | D1: MCD | E1: YOY % Change 2024 2023 | F1: MCD | G1: YOY % Change 2023 2022 | H1: MCD | I1: YOY % Change 2022 2021
A2: Year ending: | C2: 2024 | D2: 2023 | F2: 2022 | H2: 2021
A3: Stock Price | C3: 289.6 | D3: 296.51 | E3: =+(C3-D3)/D3 -> -0.023304442 | F3: 263.53 | G3: =+(D3-F3)/F3 -> 0.12514704 | H3: 267.21 | I3: =(F3-H3)/H3 -> -0.01377194
A4: Revenue | C4: =_xlfn.XLOOKUP(A4,'M24-21'!$A$4:$A$71,'M24-21'!$B$4:$B$71) -> 25920 | D4: =_xlfn.XLOOKUP(A4,'M24-21'!$A$4:$A$71,'M24-21'!$C$4:$C$71) -> 25494 | E4: =+(C4-D4)/D4 -> 0.016709814 | F4: =_xlfn.XLOOKUP(A4,'M24-21'!$A$4:$A$71,'M24-21'!$D$4:$D$71) -> 23183 | G4: =+(D4-F4)/F4 -> 0.099685114 | H4: =_xlfn.XLOOKUP(A4,'M24-21'!$A$4:$A$71,'M24-21'!$E$4:$E$71) -> 23222.9 | I4: =(F4-H4)/H4 -> -0.0017181317
A5: Cost of Revenue | C5: =_xlfn.XLOOKUP(A5,'M24-21'!$A$4:$A$71,'M24-21'!$B$4:$B$71) -> 11210 | D5: =_xlfn.XLOOKUP(A5,'M24-21'!$A$4:$A$71,'M24-21'!$C$4:$C$71) -> 10931 | E5: =+(C5-D5)/D5 -> 0.02552374 | F5: =_xlfn.XLOOKUP(A5,'M24-21'!$A$4:$A$71,'M24-21'!$D$4:$D$71) -> 9975 | G5: =+(D5-F5)/F5 -> 0.095839599 | H5: =_xlfn.XLOOKUP(A5,'M24-21'!$A$4:$A$71,'M24-21'!$E$4:$E$71) -> 10642.7 | I5: =(F5-H5)/H5 -> -0.062737839
A6: Gross Profit | C6: =_xlfn.XLOOKUP(A6,'M24-21'!$A$4:$A$71,'M24-21'!$B$4:$B$71) -> 14710 | D6: =_xlfn.XLOOKUP(A6,'M24-21'!$A$4:$A$71,'M24-21'!$C$4:$C$71) -> 14563 | E6: =+(C6-D6)/D6 -> 0.010094074 | F6: =_xlfn.XLOOKUP(A6,'M24-21'!$A$4:$A$71,'M24-21'!$D$4:$D$71) -> 13208 | G6: =+(D6-F6)/F6 -> 0.10258934 | H6: =_xlfn.XLOOKUP(A6,'M24-21'!$A$4:$A$71,'M24-21'!$E$4:$E$71) -> 12580.2 | I6: =(F6-H6)/H6 -> 0.049903817
A7: SG&A Expenses | C7: =_xlfn.XLOOKUP(A7,'M24-21'!$A$4:$A$71,'M24-21'!$B$4:$B$71) -> 2412 | D7: =_xlfn.XLOOKUP(A7,'M24-21'!$A$4:$A$71,'M24-21'!$C$4:$C$71) -> 2435 | E7: =+(C7-D7)/D7 -> -0.0094455852 | F7: =_xlfn.XLOOKUP(A7,'M24-21'!$A$4:$A$71,'M24-21'!$D$4:$D$71) -> 2492 | G7: =+(D7-F7)/F7 -> -0.022873194 | H7: =_xlfn.XLOOKUP(A7,'M24-21'!$A$4:$A$71,'M24-21'!$E$4:$E$71) -> 2707.5 | I7: =(F7-H7)/H7 -> -0.079593721
A8: Operating Income | C8: =_xlfn.XLOOKUP(A8,'M24-21'!$A$4:$A$71,'M24-21'!$B$4:$B$71) -> 11712 | D8: =_xlfn.XLOOKUP(A8,'M24-21'!$A$4:$A$71,'M24-21'!$C$4:$C$71) -> 11647 | E8: =+(C8-D8)/D8 -> 0.0055808363 | F8: =_xlfn.XLOOKUP(A8,'M24-21'!$A$4:$A$71,'M24-21'!$D$4:$D$71) -> 9372 | G8: =+(D8-F8)/F8 -> 0.24274434 | H8: =_xlfn.XLOOKUP(A8,'M24-21'!$A$4:$A$71,'M24-21'!$E$4:$E$71) -> 10356 | I8: =(F8-H8)/H8 -> -0.095017381
A9: Net Income Common | C9: =_xlfn.XLOOKUP(A9,'M24-21'!$A$4:$A$71,'M24-21'!$B$4:$B$71) -> 8223 | D9: =_xlfn.XLOOKUP(A9,'M24-21'!$A$4:$A$71,'M24-21'!$C$4:$C$71) -> 8469 | E9: =+(C9-D9)/D9 -> -0.029047113 | F9: =_xlfn.XLOOKUP(A9,'M24-21'!$A$4:$A$71,'M24-21'!$D$4:$D$71) -> 6177 | G9: =+(D9-F9)/F9 -> 0.37105391 | H9: =_xlfn.XLOOKUP(A9,'M24-21'!$A$4:$A$71,'M24-21'!$E$4:$E$71) -> 7545.2 | I9: =(F9-H9)/H9 -> -0.18133383
A10: Cash and Short Term Investments | C10: =_xlfn.XLOOKUP(A10,'M24-21'!$A$4:$A$71,'M24-21'!$B$4:$B$71) -> 1085 | D10: =_xlfn.XLOOKUP(A10,'M24-21'!$A$4:$A$71,'M24-21'!$C$4:$C$71) -> 4579 | E10: =+(C10-D10)/D10 -> -0.7630487 | F10: =_xlfn.XLOOKUP(A10,'M24-21'!$A$4:$A$71,'M24-21'!$D$4:$D$71) -> 2583.8 | G10: =+(D10-F10)/F10 -> 0.77219599 | H10: =_xlfn.XLOOKUP(A10,'M24-21'!$A$4:$A$71,'M24-21'!$E$4:$E$71) -> 4709.2 | I10: =(F10-H10)/H10 -> -0.45132931
A11: Receivables | C11: =_xlfn.XLOOKUP(A11,'M24-21'!$A$4:$A$71,'M24-21'!$B$4:$B$71) -> 2383 | D11: =_xlfn.XLOOKUP(A11,'M24-21'!$A$4:$A$71,'M24-21'!$C$4:$C$71) -> 2488 | E11: =+(C11-D11)/D11 -> -0.042202572 | F11: =_xlfn.XLOOKUP(A11,'M24-21'!$A$4:$A$71,'M24-21'!$D$4:$D$71) -> 2115 | G11: =+(D11-F11)/F11 -> 0.17635934 | H11: =_xlfn.XLOOKUP(A11,'M24-21'!$A$4:$A$71,'M24-21'!$E$4:$E$71) -> 1872.4 | I11: =(F11-H11)/H11 -> 0.12956633
A12: Inventory | C12: =_xlfn.XLOOKUP(A12,'M24-21'!$A$4:$A$71,'M24-21'!$B$4:$B$71) -> 56 | D12: =_xlfn.XLOOKUP(A12,'M24-21'!$A$4:$A$71,'M24-21'!$C$4:$C$71) -> 53 | E12: =+(C12-D12)/D12 -> 0.056603774 | F12: =_xlfn.XLOOKUP(A12,'M24-21'!$A$4:$A$71,'M24-21'!$D$4:$D$71) -> 52 | G12: =+(D12-F12)/F12 -> 0.019230769 | H12: =_xlfn.XLOOKUP(A12,'M24-21'!$A$4:$A$71,'M24-21'!$E$4:$E$71) -> 55.6 | I12: =(F12-H12)/H12 -> -0.064748201
A13: Total current assets | C13: =_xlfn.XLOOKUP(A13,'M24-21'!$A$4:$A$71,'M24-21'!$B$4:$B$71) -> 4599 | D13: =_xlfn.XLOOKUP(A13,'M24-21'!$A$4:$A$71,'M24-21'!$C$4:$C$71) -> 7986 | E13: =+(C13-D13)/D13 -> -0.42411721 | F13: =_xlfn.XLOOKUP(A13,'M24-21'!$A$4:$A$71,'M24-21'!$D$4:$D$71) -> 5424.2 | G13: =+(D13-F13)/F13 -> 0.47229084 | H13: =_xlfn.XLOOKUP(A13,'M24-21'!$A$4:$A$71,'M24-21'!$E$4:$E$71) -> 7148.5 | I13: =(F13-H13)/H13 -> -0.24121144
A14: Total Assets | C14: =_xlfn.XLOOKUP(A14,'M24-21'!$A$4:$A$71,'M24-21'!$B$4:$B$71) -> 55182 | D14: =_xlfn.XLOOKUP(A14,'M24-21'!$A$4:$A$71,'M24-21'!$C$4:$C$71) -> 56147 | E14: =+(C14-D14)/D14 -> -0.017187027 | F14: =_xlfn.XLOOKUP(A14,'M24-21'!$A$4:$A$71,'M24-21'!$D$4:$D$71) -> 50435.6 | G14: =+(D14-F14)/F14 -> 0.11324144 | H14: =_xlfn.XLOOKUP(A14,'M24-21'!$A$4:$A$71,'M24-21'!$E$4:$E$71) -> 53854.3 | I14: =(F14-H14)/H14 -> -0.063480539
A15: Total current liabilities | C15: =_xlfn.XLOOKUP(A15,'M24-21'!$A$4:$A$71,'M24-21'!$B$4:$B$71) -> 3861 | D15: =_xlfn.XLOOKUP(A15,'M24-21'!$A$4:$A$71,'M24-21'!$C$4:$C$71) -> 6859 | E15: =+(C15-D15)/D15 -> -0.43708995 | F15: =_xlfn.XLOOKUP(A15,'M24-21'!$A$4:$A$71,'M24-21'!$D$4:$D$71) -> 3802.1 | G15: =+(D15-F15)/F15 -> 0.80400305 | H15: =_xlfn.XLOOKUP(A15,'M24-21'!$A$4:$A$71,'M24-21'!$E$4:$E$71) -> 4020 | I15: =(F15-H15)/H15 -> -0.05420398
... A19: Shares (Basic, Weighted) | C19: =_xlfn.XLOOKUP(A19,'M24-21'!$A$4:$A$71,'M24-21'!$B$4:$B$71) -> 718.3 | D19: =_xlfn.XLOOKUP(A19,'M24-21'!$A$4:$A$71,'M24-21'!$C$4:$C$71) -> 727.9 | E19: =+(C19-D19)/D19 -> -0.013188625 | F19: =_xlfn.XLOOKUP(A19,'M24-21'!$A$4:$A$71,'M24-21'!$D$4:$D$71) -> 736.5 | G19: =+(D19-F19)/F19 -> -0.01167685 | H19: =_xlfn.XLOOKUP(A19,'M24-21'!$A$4:$A$71,'M24-21'!$E$4:$E$71) -> 746.3 | I19: =(F19-H19)/H19 -> -0.013131448
A20: Financial Ratio's | C20: MCD | D20: MCD | E20: YOY % Change 2024 2023 | F20: MCD | G20: YOY % Change 2023 2022 | H20: MCD | I20: YOY % Change 2022 2021
A21: Liquidity | C21: 2024 | D21: 2023 | F21: 2022 | H21: 2021
A22: Current Ratio | C22: =C13/C15 -> 1.1911422 | D22: =D13/D15 -> 1.1643097 | E22: =(C22-D22)/D22 -> 0.023045866 | F22: =F13/F15 -> 1.4266327 | G22: =(D22-F22)/F22 -> -0.18387563 | H22: =H13/H15 -> 1.7782338 | I22: =(F22-H22)/H22 -> -0.19772494
A23: Quick Ratio | C23: =(C13-C12)/C15 -> 1.1766382 | D23: =(D13-D12)/D15 -> 1.1565826 | E23: =(C23-D23)/D23 -> 0.017340382 | F23: =(F13-F12)/F15 -> 1.412956 | G23: =(D23-F23)/F23 -> -0.18144472 | H23: =(H13-H12)/H15 -> 1.764403 | I23: =(F23-H23)/H23 -> -0.19918748
A24: Net Working Capital | C24: =C13-C15 -> 738 | D24: =D13-D15 -> 1127 | E24: =(C24-D24)/D24 -> -0.34516415 | F24: =F13-F15 -> 1622.1 | G24: =(D24-F24)/F24 -> -0.30522163 | H24: =H13-H15 -> 3128.5 | I24: =(F24-H24)/H24 -> -0.48150871
A25: Asset Management
A26: Accounts Rec. Turnover | C26: =C4/C11 -> 10.877046 | D26: =D4/D11 -> 10.246785 | E26: =(C26-D26)/D26 -> 0.06150819 | F26: =F4/F11 -> 10.961229 | G26: =(D26-F26)/F26 -> -0.065179254 | H26: =H4/H11 -> 12.402745 | I26: =(F26-H26)/H26 -> -0.11622555
A27: Inventory Turnover | C27: =C4/C12 -> 462.85714 | D27: =D4/D12 -> 481.01887 | E27: =(C27-D27)/D27 -> -0.037756783 | F27: =F4/F12 -> 445.82692 | G27: =(D27-F27)/F27 -> 0.078936338 | H27: =H4/H12 -> 417.67806 | I27: =(F27-H27)/H27 -> 0.06739369
A28: Total Asset Turnover | C28: =C4/C14 -> 0.46971839 | D28: =D4/D14 -> 0.4540581 | E28: =(C28-D28)/D28 -> 0.034489615 | F28: =F4/F14 -> 0.45965548 | G28: =(D28-F28)/F28 -> -0.012177346 | H28: =H4/H14 -> 0.43121719 | I28: =(F28-H28)/H28 -> 0.065948878
A29: Debt Management
A30: Debt to Equity Ratio | C30: =C16/C18 -> -10.122234 | D30: =D16/D18 -> -7.8948151 | E30: =(C30-D30)/D30 -> 0.28213692 | F30: =F16/F18 -> -5.9805277 | G30: =(D30-F30)/F30 -> 0.32008671 | H30: =H16/H18 -> -7.7423653 | I30: =(F30-H30)/H30 -> -0.22755805
A31: Equity multiplier | C31: =C14/C18 -> -14.536881 | D31: =D14/D18 -> -11.930939 | E31: =(C31-D31)/D31 -> 0.21841882 | F31: =F14/F18 -> -8.4011727 | G31: =(D31-F31)/F31 -> 0.42015165 | H31: =H14/H18 -> -11.704887 | I31: =(F31-H31)/H31 -> -0.28225082
A32: Profitability
A33: Net Profit Margin | C33: =_xlfn.XLOOKUP(A33,'M24-21'!$A$4:$A$71,'M24-21'!B4:B71) -> 0.3172 | D33: =_xlfn.XLOOKUP(A33,'M24-21'!$A$4:$A$71,'M24-21'!C4:C71) -> 0.3322 | E33: =(C33-D33)/D33 -> -0.045153522 | F33: =_xlfn.XLOOKUP(A33,'M24-21'!$A$4:$A$71,'M24-21'!D4:D71) -> 0.2664 | G33: =(D33-F33)/F33 -> 0.246997 | H33: =_xlfn.XLOOKUP(A33,'M24-21'!$A$4:$A$71,'M24-21'!E4:E71) -> 0.3249 | I33: =(F33-H33)/H33 -> -0.1800554
A34: Gross Profit Margin | C34: =_xlfn.XLOOKUP($A$34,'M24-21'!$A$4:$A$71,'M24-21'!B4:B71) -> 0.5675 | D34: =_xlfn.XLOOKUP($A$34,'M24-21'!$A$4:$A$71,'M24-21'!C4:C71) -> 0.5712 | E34: =(C34-D34)/D34 -> -0.006477591 | F34: =_xlfn.XLOOKUP($A$34,'M24-21'!$A$4:$A$71,'M24-21'!D4:D71) -> 0.5697 | G34: =(D34-F34)/F34 -> 0.0026329647 | H34: =_xlfn.XLOOKUP($A$34,'M24-21'!$A$4:$A$71,'M24-21'!E4:E71) -> 0.5417 | I34: =(F34-H34)/H34 -> 0.051689127
A35: Return On Assets ROA | C35: =C33*C28 -> 0.14899467 | D35: =D33*D28 -> 0.1508381 | E35: =(C35-D35)/D35 -> -0.012221235 | F35: =F33*F28 -> 0.12245222 | G35: =(D35-F35)/F35 -> 0.23181188 | H35: =H33*H28 -> 0.14010247 | I35: =(F35-H35)/H35 -> -0.12598098
A36: Return On Equity ROE | C36: =C35*C31 -> -2.1659178 | D36: =D35*D31 -> -1.7996402 | E36: =(C36-D36)/D36 -> 0.20352824 | F36: =F35*F31 -> -1.0287422 | G36: =(D36-F36)/F36 -> 0.74935968 | H36: =H35*H31 -> -1.6398835 | I36: =(F36-H36)/H36 -> -0.37267357
A37: Market Value
A38: EPS | C38: =C9/C19 -> 11.447863 | D38: =D9/D19 -> 11.63484 | E38: =(C38-D38)/D38 -> -0.016070435 | F38: =F9/F19 -> 8.3869654 | G38: =(D38-F38)/F38 -> 0.38725265 | H38: =H9/H19 -> 10.110143 | I38: =(F38-H38)/H38 -> -0.17044051
A39: P/E | C39: =C3/C38 -> 25.297298 | D39: =D3/D38 -> 25.484665 | E39: =(C39-D39)/D39 -> -0.0073521589 | F39: =F3/F38 -> 31.421377 | G39: =(D39-F39)/F39 -> -0.18893863 | H39: =H3/H38 -> 26.429892 | I39: =(F39-H39)/H39 -> 0.18885755
A40: Book Value Per Share | C40: =C18/C19 -> -5.2847 | D40: =D18/D19 -> -6.4651738 | E40: =(C40-D40)/D40 -> -0.18258965 | F40: =F18/F19 -> -8.1512559 | G40: =(D40-F40)/F40 -> -0.20684937 | H40: =H18/H19 -> -6.1650945 | I40: =(F40-H40)/H40 -> 0.32216237
A41: Market Capitalization (Stock Price * Shares) | C41: =C3*C19 -> 208019.68 | D41: =D3*D19 -> 215829.63 | E41: =(C41-D41)/D41 -> -0.036185713 | F41: =F3*F19 -> 194089.84 | G41: =(D41-F41)/F41 -> 0.11200887 | H41: =H3*H19 -> 199418.82 | I41: =(F41-H41)/H41 -> -0.026722543
A42: Cash Per Share | C42: =C10/C19 -> 1.5105109 | D42: =D10/D19 -> 6.2906993 | E42: =(C42-D42)/D42 -> -0.75988187 | F42: =F10/F19 -> 3.5082145 | G42: =(D42-F42)/F42 -> 0.79313415 | H42: =H10/H19 -> 6.310063 | I42: =(F42-H42)/H42 -> -0.4440286
A43: Revenue Per Share | C43: =C4/C19 -> 36.085201 | D43: =D4/D19 -> 35.024042 | E43: =(C43-D43)/D43 -> 0.030298028 | F43: =F4/F19 -> 31.477257 | G43: =(D43-F43)/F43 -> 0.11267768 | H43: =H4/H19 -> 31.117379 | I43: =(F43-H43)/H43 -> 0.011565184
A44: Price to Book Value | C44: =C3/C40 -> -54.799705 | D44: =D3/D40 -> -45.86265 | E44: =(C44-D44)/D44 -> 0.19486566 | F44: =F3/F40 -> -32.329987 | G44: =(D44-F44)/F44 -> 0.41857927 | H44: =H3/H40 -> -43.342402 | I44: =(F44-H44)/H44 -> -0.25407947

Sheet Y24-21
A1: In the Millions | G1: In the Millions
A3: Income Statement | B3: Dec '24 | C3: Dec '23 | D3: Dec '22 | E3: Dec '21 | G3: Balance Sheet | H3: Dec '24 | I3: Dec '23 | J3: Dec '22 | K3: Dec '21
A4: Revenue | B4: 7549 | C4: 7076 | D4: 6842 | E4: 6584 | G4: Cash and Short Term Investments | H4: 616 | I4: 512 | J4: 367 | K4: 486
A5: Revenue Growth | B5: 0.0668 | C5: 0.0342 | D5: 0.0392 | E5: 0.1649 | G5: Receivables | H5: 775 | I5: 737 | J5: 648 | K5: 596
A6: Cost of Revenue | B6: 2120 | C6: 1774 | D6: 1745 | E6: 1725 | G6: Inventory | H6: — | I6: — | J6: — | K6: —
A7: Gross Profit | B7: 5429 | C7: 5302 | D7: 5097 | E7: 4859 | G7: Other current assets | H7: — | I7: — | J7: 342 | K7: 150
A8: R&D Expenses | B8: — | C8: — | D8: — | E8: — | G8: Total current assets | H8: 1871 | I8: 1609 | J8: 1609 | K8: 1532
A9: SG&A Expenses | B9: 2892 | C9: 2876 | D9: 2807 | E9: 2636 | G9: Property, Plant, Equipment (Net) | H9: 1304 | I9: 1197 | J9: 1171 | K9: 1207
A10: Operating Income | B10: 2403 | C10: 2318 | D10: 2187 | E10: 2139 | G10: Long-Term Investments | H10: — | I10: — | J10: 274 | K10: 277
A11: Interest Expense (Operating) | B11: — | C11: — | D11: 537 | E11: 522 | G11: Goodwill and Intangible Assets (Total) | H11: 1152 | I11: 1019 | J11: 992 | K11: 1016
A12: Non-operating Income/Expense | B12: -503 | C12: -500 | D12: -525 | E12: -465 | G12: Long Term Assets (Tax, Deferred) | H12: 1071 | I12: 1045 | J12: 750 | K12: 724
A13: Non-operating Interest Expenses | B13: 489 | C13: 513 | D13: 527 | E13: 544 | G13: Long-term assets (Other) | H13: 1329 | I13: 1361 | J13: 1324 | K13: 1487
A14: EBT | B14: 1900 | C14: 1818 | D14: 1662 | E14: 1674 | G14: Total non-current assets | H14: 4856 | I14: 4622 | J14: 4237 | K14: 4434
A15: Income Tax Provision | B15: 414 | C15: 221 | D15: 337 | E15: 99 | G15: Total Assets | H15: 6727 | I15: 6231 | J15: 5846 | K15: 5966
A16: Income after Tax | B16: 1486 | C16: 1597 | D16: 1325 | E16: 1575 | G16: Accounts Payable | H16: 1211 | I16: 1169 | J16: 1251 | K16: 1334
A17: Net Income Common | B17: 1486 | C17: 1597 | D17: 1325 | E17: 1575 | G17: Current Part of Debt | H17: 27 | I17: 53 | J17: 398 | K17: 68
A18: EPS (Basic) | B18: 5.28 | C18: 5.68 | D18: 4.63 | E18: 5.3 | G18: Current Part of Taxes to Pay | H18: 31 | I18: 55 | J18: 16 | K18: 13
A19: EPS (Diluted) | B19: 5.22 | C19: 5.59 | D19: 4.57 | E19: 5.21 | G19: Other current liabilities | H19: — | I19: — | J19: 929 | K19: 1019
A20: Shares (Basic, Weighted) | B20: 282 | C20: 281 | D20: 286 | E20: 297 | G20: Total current liabilities | H20: 1269 | I20: 1277 | J20: 1665 | K20: 1415
A21: Shares (Diluted, Weighted) | B21: 285 | C21: 285 | D21: 290 | E21: 302 | G21: Long Term Debt (Total) | H21: 11306 | I21: 11142 | J21: 11453 | K21: 11178
A22: Gross Profit Margin | B22: 0.7192 | C22: 0.7493 | D22: 0.745 | E22: 0.738 | G22: Long Term Tax Liability (Deferred) | H22: — | I22: — | J22: -750 | K22: -724
A23: EBIT Margin | B23: 0.3183 | C23: 0.3276 | D23: 0.3196 | E23: 0.3249 | G23: Minority Interests | H23: — | I23: — | J23: — | K23: —
A24: EBT margin | B24: 0.2517 | C24: 0.2569 | D24: 0.2429 | E24: 0.2543 | G24: Non-current Liabilities (Other) | H24: 1800 | I24: 1670 | J24: 1604 | K24: 1746
A25: Net Profit Margin | B25: 0.1968 | C25: 0.2257 | D25: 0.1937 | E25: 0.2392 | G25: Total non-current liabilities | H25: 13106 | I25: 12812 | J25: 13057 | K25: 12924
A26: Free Cash Flow Margin | B26: 0.1897 | C26: 0.1863 | D26: 0.1678 | E26: 0.2242 | G26: Total liabilities | H26: 14375 | I26: 14089 | J26: 14722 | K26: 14339
A27: EBITDA | B27: 2578 | C27: 2471 | D27: 2333 | E27: 2303 | G27: Common Stock (Net) | H27: 0 | I27: 60 | J27: 0 | K27: —
A28: EBIT | B28: 2403 | C28: 2318 | D28: 2187 | E28: 2139 | G28: Retained Earnings | H28: -7256 | I28: -7616 | J28: -8507 | K28: -8048
A29: Income from Continuous Operations | B29: 1486 | C29: 1597 | D29: 1325 | E29: 1575 | G29: Common Equity (Total) | H29: -7648 | I29: -7858 | J29: -8876 | K29: -8373
A30: Income from Discontinued Operations | B30: — | C30: — | D30: — | E30: — | G30: Shareholders Equity (Total) | H30: -7648 | I30: -7858 | J30: -8876 | K30: -8373
A31: Consolidated Net Income/Loss | B31: 1486 | C31: 1597 | D31: 1325 | E31: 1575 | G31: Shareholders Equity and Liabilities (Total) | H31: 6727 | I31: 6231 | J31: 5846 | K31: 5966
A32: EPS (Basic, from Continuous Ops) | B32: 5.27 | C32: 5.68 | D32: 4.63 | E32: 5.3 | G32: Shares (Common) | H32: 279 | I32: 281 | J32: 280 | K32: 289
A33: EPS (Basic, from Discontinued Ops) | B33: — | C33: — | D33: — | E33: — | G33: Shareholders Equity (Tangible) | H33: -8800 | I33: -8877 | J33: -9868 | K33: -9389
A34: EPS (Basic, Consolidated) | B34: 5.27 | C34: 5.68 | D34: 4.63 | E34: 5.3 | G34: Net Debt | H34: 10717 | I34: 10683 | J34: 11484 | K34: 10760
A35: EPS (Diluted, from Cont. Ops) | B35: 5.21 | C35: 5.6 | D35: 4.57 | E35: 5.22 | G35: Total Debt | H35: 11333 | I35: 11195 | J35: 11851 | K35: 11246
A36: EPS (Diluted, from Disc. Ops) | B36: — | C36: — | D36: — | E36: —
A37: Shares (Diluted, Average) | B37: 285 | C37: 285 | D37: 290 | E37: 302
A38: EPS (Diluted, Consolidated) | B38: 5.21 | C38: 5.6 | D38: 4.57 | E38: 5.22
A39: EBITDA Margin | B39: 0.3415 | C39: 0.3492 | D39: 0.341 | E39: 0.3498
A40: Operating Cash Flow Margin | B40: 0.2237 | C40: 0.2265 | D40: 0.2086 | E40: 0.2591
A41: Cash and Short Term Investments | B41: 616 | C41: 512 | D41: 367 | E41: 486
A42: Receivables | B42: 775 | C42: 737 | D42: 648 | E42: 596
A43: Inventory | B43: — | C43: — | D43: — | E43: —
A44: Other current assets | B44: — | C44: — | D44: 342 | E44: 150
A45: Total current assets | B45: 1871 | C45: 1609 | D45: 1609 | E45: 1532
A46: Property, Plant, Equipment (Net) | B46: 1304 | C46: 1197 | D46: 1171 | E46: 1207
A47: Long-Term Investments | B47: — | C47: — | D47: 274 | E47: 277
A48: Goodwill and Intangible Assets (Total) | B48: 1152 | C48: 1019 | D48: 992 | E48: 1016
A49: Long Term Assets (Tax, Deferred) | B49: 1071 | C49: 1045 | D49: 750 | E49: 724
A50: Long-term assets (Other) | B50: 1329 | C50: 1361 | D50: 1324 | E50: 1487
A51: Total non-current assets | B51: 4856 | C51: 4622 | D51: 4237 | E51: 4434
A52: Total Assets | B52: 6727 | C52: 6231 | D52: 5846 | E52: 5966
A53: Accounts Payable | B53: 1211 | C53: 1169 | D53: 1251 | E53: 1334
A54: Current Part of Debt | B54: 27 | C54: 53 | D54: 398 | E54: 68
A55: Current Part of Taxes to Pay | B55: 31 | C55: 55 | D55: 16 | E55: 13
A56: Other current liabilities | B56: — | C56: — | D56: 929 | E56: 1019
A57: Total current liabilities | B57: 1269 | C57: 1277 | D57: 1665 | E57: 1415
A58: Long Term Debt (Total) | B58: 11306 | C58: 11142 | D58: 11453 | E58: 11178
A59: Long Term Tax Liability (Deferred) | B59: — | C59: — | D59: -750 | E59: -724
A60: Minority Interests | B60: — | C60: — | D60: — | E60: —
A61: Non-current Liabilities (Other) | B61: 1800 | C61: 1670 | D61: 1604 | E61: 1746
A62: Total non-current liabilities | B62: 13106 | C62: 12812 | D62: 13057 | E62: 12924
A63: Total liabilities | B63: 14375 | C63: 14089 | D63: 14722 | E63: 14339
A64: Common Stock (Net) | B64: 0 | C64: 60 | D64: 0 | E64: —
A65: Retained Earnings | B65: -7256 | C65: -7616 | D65: -8507 | E65: -8048
A66: Common Equity (Total) | B66: -7648 | C66: -7858 | D66: -8876 | E66: -8373
A67: Shareholders Equity (Total) | B67: -7648 | C67: -7858 | D67: -8876 | E67: -8373
A68: Shareholders Equity and Liabilities (Total) | B68: 6727 | C68: 6231 | D68: 5846 | E68: 5966
A69: Shares (Common) | B69: 279 | C69: 281 | D69: 280 | E69: 289
A70: Shareholders Equity (Tangible) | B70: -8800 | C70: -8877 | D70: -9868 | E70: -9389
A71: Net Debt | B71: 10717 | C71: 10683 | D71: 11484 | E71: 10760
A72: Total Debt | B72: 11333 | C72: 11195 | D72: 11851 | E72: 11246

Sheet YOY Yum
A1: Company Name | C1: YUM | D1: YUM | E1: YOY % Change 2024 2023 | F1: YUM | G1: YOY % Change 2023 2022 | H1: YUM | I1: YOY % Change 2022 2021
A2: Year ending: | C2: 2024 | D2: 2023 | F2: 2022 | H2: 2021
A3: Stock Price | C3: 133.52 | D3: 130.66 | E3: =+(C3-D3)/D3 -> 0.021888872 | F3: 128.08 | G3: =+(D3-F3)/F3 -> 0.02014366 | H3: 138.39 | I3: =(F3-H3)/H3 -> -0.074499603
A4: Revenue | C4: =_xlfn.XLOOKUP(A4,'Y24-21'!$A$4:$A$72,'Y24-21'!$B$4:$B$72) -> 7549 | D4: =_xlfn.XLOOKUP(A4,'Y24-21'!$A$4:$A$72,'Y24-21'!$C$4:$C$72) -> 7076 | E4: =+(C4-D4)/D4 -> 0.066845676 | F4: =_xlfn.XLOOKUP(A4,'Y24-21'!$A$4:$A$72,'Y24-21'!$D$4:$D$72) -> 6842 | G4: =+(D4-F4)/F4 -> 0.034200526 | H4: =_xlfn.XLOOKUP(A4,'Y24-21'!$A$4:$A$72,'Y24-21'!$E$4:$E$72) -> 6584 | I4: =(F4-H4)/H4 -> 0.039185905
A5: Cost of Revenue | C5: =_xlfn.XLOOKUP(A5,'Y24-21'!$A$4:$A$72,'Y24-21'!$B$4:$B$72) -> 2120 | D5: =_xlfn.XLOOKUP(A5,'Y24-21'!$A$4:$A$72,'Y24-21'!$C$4:$C$72) -> 1774 | E5: =+(C5-D5)/D5 -> 0.19503946 | F5: =_xlfn.XLOOKUP(A5,'Y24-21'!$A$4:$A$72,'Y24-21'!$D$4:$D$72) -> 1745 | G5: =+(D5-F5)/F5 -> 0.016618911 | H5: =_xlfn.XLOOKUP(A5,'Y24-21'!$A$4:$A$72,'Y24-21'!$E$4:$E$72) -> 1725 | I5: =(F5-H5)/H5 -> 0.011594203
A6: Gross Profit | C6: =_xlfn.XLOOKUP(A6,'Y24-21'!$A$4:$A$72,'Y24-21'!$B$4:$B$72) -> 5429 | D6: =_xlfn.XLOOKUP(A6,'Y24-21'!$A$4:$A$72,'Y24-21'!$C$4:$C$72) -> 5302 | E6: =+(C6-D6)/D6 -> 0.023953225 | F6: =_xlfn.XLOOKUP(A6,'Y24-21'!$A$4:$A$72,'Y24-21'!$D$4:$D$72) -> 5097 | G6: =+(D6-F6)/F6 -> 0.040219737 | H6: =_xlfn.XLOOKUP(A6,'Y24-21'!$A$4:$A$72,'Y24-21'!$E$4:$E$72) -> 4859 | I6: =(F6-H6)/H6 -> 0.048981272
A7: SG&A Expenses | C7: =_xlfn.XLOOKUP(A7,'Y24-21'!$A$4:$A$72,'Y24-21'!$B$4:$B$72) -> 2892 | D7: =_xlfn.XLOOKUP(A7,'Y24-21'!$A$4:$A$72,'Y24-21'!$C$4:$C$72) -> 2876 | E7: =+(C7-D7)/D7 -> 0.0055632823 | F7: =_xlfn.XLOOKUP(A7,'Y24-21'!$A$4:$A$72,'Y24-21'!$D$4:$D$72) -> 2807 | G7: =+(D7-F7)/F7 -> 0.024581404 | H7: =_xlfn.XLOOKUP(A7,'Y24-21'!$A$4:$A$72,'Y24-21'!$E$4:$E$72) -> 2636 | I7: =(F7-H7)/H7 -> 0.064871017
A8: Operating Income | C8: =_xlfn.XLOOKUP(A8,'Y24-21'!$A$4:$A$72,'Y24-21'!$B$4:$B$72) -> 2403 | D8: =_xlfn.XLOOKUP(A8,'Y24-21'!$A$4:$A$72,'Y24-21'!$C$4:$C$72) -> 2318 | E8: =+(C8-D8)/D8 -> 0.036669543 | F8: =_xlfn.XLOOKUP(A8,'Y24-21'!$A$4:$A$72,'Y24-21'!$D$4:$D$72) -> 2187 | G8: =+(D8-F8)/F8 -> 0.059899406 | H8: =_xlfn.XLOOKUP(A8,'Y24-21'!$A$4:$A$72,'Y24-21'!$E$4:$E$72) -> 2139 | I8: =(F8-H8)/H8 -> 0.022440393
A9: Net Income Common | C9: =_xlfn.XLOOKUP(A9,'Y24-21'!$A$4:$A$72,'Y24-21'!$B$4:$B$72) -> 1486 | D9: =_xlfn.XLOOKUP(A9,'Y24-21'!$A$4:$A$72,'Y24-21'!$C$4:$C$72) -> 1597 | E9: =+(C9-D9)/D9 -> -0.069505322 | F9: =_xlfn.XLOOKUP(A9,'Y24-21'!$A$4:$A$72,'Y24-21'!$D$4:$D$72) -> 1325 | G9: =+(D9-F9)/F9 -> 0.20528302 | H9: =_xlfn.XLOOKUP(A9,'Y24-21'!$A$4:$A$72,'Y24-21'!$E$4:$E$72) -> 1575 | I9: =(F9-H9)/H9 -> -0.15873016
A10: Cash and Short Term Investments | C10: =_xlfn.XLOOKUP(A10,'Y24-21'!$A$4:$A$72,'Y24-21'!$B$4:$B$72) -> 616 | D10: =_xlfn.XLOOKUP(A10,'Y24-21'!$A$4:$A$72,'Y24-21'!$C$4:$C$72) -> 512 | E10: =+(C10-D10)/D10 -> 0.203125 | F10: =_xlfn.XLOOKUP(A10,'Y24-21'!$A$4:$A$72,'Y24-21'!$D$4:$D$72) -> 367 | G10: =+(D10-F10)/F10 -> 0.39509537 | H10: =_xlfn.XLOOKUP(A10,'Y24-21'!$A$4:$A$72,'Y24-21'!$E$4:$E$72) -> 486 | I10: =(F10-H10)/H10 -> -0.24485597
A11: Receivables | C11: =_xlfn.XLOOKUP(A11,'Y24-21'!$A$4:$A$72,'Y24-21'!$B$4:$B$72) -> 775 | D11: =_xlfn.XLOOKUP(A11,'Y24-21'!$A$4:$A$72,'Y24-21'!$C$4:$C$72) -> 737 | E11: =+(C11-D11)/D11 -> 0.05156038 | F11: =_xlfn.XLOOKUP(A11,'Y24-21'!$A$4:$A$72,'Y24-21'!$D$4:$D$72) -> 648 | G11: =+(D11-F11)/F11 -> 0.13734568 | H11: =_xlfn.XLOOKUP(A11,'Y24-21'!$A$4:$A$72,'Y24-21'!$E$4:$E$72) -> 596 | I11: =(F11-H11)/H11 -> 0.087248322
A12: Inventory | C12: 10 | D12: 10 | E12: =+(C12-D12)/D12 -> 0 | F12: 10 | G12: =+(D12-F12)/F12 -> 0 | H12: 10 | I12: =(F12-H12)/H12 -> 0
A13: Total current assets | C13: =_xlfn.XLOOKUP(A13,'Y24-21'!$A$4:$A$72,'Y24-21'!$B$4:$B$72) -> 1871 | D13: =_xlfn.XLOOKUP(A13,'Y24-21'!$A$4:$A$72,'Y24-21'!$C$4:$C$72) -> 1609 | E13: =+(C13-D13)/D13 -> 0.16283406 | F13: =_xlfn.XLOOKUP(A13,'Y24-21'!$A$4:$A$72,'Y24-21'!$D$4:$D$72) -> 1609 | G13: =+(D13-F13)/F13 -> 0 | H13: =_xlfn.XLOOKUP(A13,'Y24-21'!$A$4:$A$72,'Y24-21'!$E$4:$E$72) -> 1532 | I13: =(F13-H13)/H13 -> 0.050261097
A14: Total Assets | C14: =_xlfn.XLOOKUP(A14,'Y24-21'!$A$4:$A$72,'Y24-21'!$B$4:$B$72) -> 6727 | D14: =_xlfn.XLOOKUP(A14,'Y24-21'!$A$4:$A$72,'Y24-21'!$C$4:$C$72) -> 6231 | E14: =+(C14-D14)/D14 -> 0.07960199 | F14: =_xlfn.XLOOKUP(A14,'Y24-21'!$A$4:$A$72,'Y24-21'!$D$4:$D$72) -> 5846 | G14: =+(D14-F14)/F14 -> 0.065856996 | H14: =_xlfn.XLOOKUP(A14,'Y24-21'!$A$4:$A$72,'Y24-21'!$E$4:$E$72) -> 5966 | I14: =(F14-H14)/H14 -> -0.020113979
A15: Total current liabilities | C15: =_xlfn.XLOOKUP(A15,'Y24-21'!$A$4:$A$72,'Y24-21'!$B$4:$B$72) -> 1269 | D15: =_xlfn.XLOOKUP(A15,'Y24-21'!$A$4:$A$72,'Y24-21'!$C$4:$C$72) -> 1277 | E15: =+(C15-D15)/D15 -> -0.0062646829 | F15: =_xlfn.XLOOKUP(A15,'Y24-21'!$A$4:$A$72,'Y24-21'!$D$4:$D$72) -> 1665 | G15: =+(D15-F15)/F15 -> -0.23303303 | H15: =_xlfn.XLOOKUP(A15,'Y24-21'!$A$4:$A$72,'Y24-21'!$E$4:$E$72) -> 1415 | I15: =(F15-H15)/H15 -> 0.17667845
A16: Long Term Debt (Total) | C16: =_xlfn.XLOOKUP(A16,'Y24-21'!$A$4:$A$72,'Y24-21'!$B$4:$B$72) -> 11306 | D16: =_xlfn.XLOOKUP(A16,'Y24-21'!$A$4:$A$72,'Y24-21'!$C$4:$C$72) -> 11142 | E16: =+(C16-D16)/D16 -> 0.014719081 | F16: =_xlfn.XLOOKUP(A16,'Y24-21'!$A$4:$A$72,'Y24-21'!$D$4:$D$72) -> 11453 | G16: =+(D16-F16)/F16 -> -0.027154457 | H16: =_xlfn.XLOOKUP(A16,'Y24-21'!$A$4:$A$72,'Y24-21'!$E$4:$E$72) -> 11178 | I16: =(F16-H16)/H16 -> 0.024601897
A17: Total liabilities | C17: =_xlfn.XLOOKUP(A17,'Y24-21'!$A$4:$A$72,'Y24-21'!$B$4:$B$72) -> 14375 | D17: =_xlfn.XLOOKUP(A17,'Y24-21'!$A$4:$A$72,'Y24-21'!$C$4:$C$72) -> 14089 | E17: =+(C17-D17)/D17 -> 0.020299524 | F17: =_xlfn.XLOOKUP(A17,'Y24-21'!$A$4:$A$72,'Y24-21'!$D$4:$D$72) -> 14722 | G17: =+(D17-F17)/F17 -> -0.042996875 | H17: =_xlfn.XLOOKUP(A17,'Y24-21'!$A$4:$A$72,'Y24-21'!$E$4:$E$72) -> 14339 | I17: =(F17-H17)/H17 -> 0.02671037
A18: Common Equity (Total) | C18: =_xlfn.XLOOKUP(A18,'Y24-21'!$A$4:$A$72,'Y24-21'!$B$4:$B$72) -> -7648 | D18: =_xlfn.XLOOKUP(A18,'Y24-21'!$A$4:$A$72,'Y24-21'!$C$4:$C$72) -> -7858 | E18: =+(C18-D18)/D18 -> -0.026724357 | F18: =_xlfn.XLOOKUP(A18,'Y24-21'!$A$4:$A$72,'Y24-21'!$D$4:$D$72) -> -8876 | G18: =+(D18-F18)/F18 -> -0.1146913 | H18: =_xlfn.XLOOKUP(A18,'Y24-21'!$A$4:$A$72,'Y24-21'!$E$4:$E$72) -> -8373 | I18: =(F18-H18)/H18 -> 0.060074048
A19: Shares (Basic, Weighted) | C19: =_xlfn.XLOOKUP(A19,'Y24-21'!$A$4:$A$72,'Y24-21'!$B$4:$B$72) -> 282 | D19: =_xlfn.XLOOKUP(A19,'Y24-21'!$A$4:$A$72,'Y24-21'!$C$4:$C$72) -> 281 | E19: =+(C19-D19)/D19 -> 0.0035587189 | F19: =_xlfn.XLOOKUP(A19,'Y24-21'!$A$4:$A$72,'Y24-21'!$D$4:$D$72) -> 286 | G19: =+(D19-F19)/F19 -> -0.017482517 | H19: =_xlfn.XLOOKUP(A19,'Y24-21'!$A$4:$A$72,'Y24-21'!$E$4:$E$72) -> 297 | I19: =(F19-H19)/H19 -> -0.037037037
A20: Financial Ratio's | C20: YUM | D20: YUM | E20: YOY % Change 2024 2023 | F20: YUM | G20: YOY % Change 2023 2022 | H20: YUM | I20: YOY % Change 2022 2021
A21: Liquidity | C21: 2024 | D21: 2023 | F21: 2022 | H21: 2021
A22: Current Ratio | C22: =C13/C15 -> 1.4743893 | D22: =D13/D15 -> 1.2599843 | E22: =(C22-D22)/D22 -> 0.17016477 | F22: =F13/F15 -> 0.96636637 | G22: =(D22-F22)/F22 -> 0.30383712 | H22: =H13/H15 -> 1.0826855 | I22: =(F22-H22)/H22 -> -0.10743576
A23: Quick Ratio | C23: =(C13-C12)/C15 -> 1.4665091 | D23: =(D13-D12)/D15 -> 1.2521535 | E23: =(C23-D23)/D23 -> 0.17118954 | F23: =(F13-F12)/F15 -> 0.96036036 | G23: =(D23-F23)/F23 -> 0.30383712 | H23: =(H13-H12)/H15 -> 1.0756184 | I23: =(F23-H23)/H23 -> -0.10715512
A24: Net Working Capital | C24: =C13-C15 -> 602 | D24: =D13-D15 -> 332 | E24: =(C24-D24)/D24 -> 0.81325301 | F24: =F13-F15 -> -56 | G24: =(D24-F24)/F24 -> -6.9285714 | H24: =H13-H15 -> 117 | I24: =(F24-H24)/H24 -> -1.4786325
A25: Asset Management
A26: Accounts Rec. Turnover | C26: =C4/C11 -> 9.7406452 | D26: =D4/D11 -> 9.6010855 | E26: =(C26-D26)/D26 -> 0.014535823 | F26: =F4/F11 -> 10.558642 | G26: =(D26-F26)/F26 -> -0.090689361 | H26: =H4/H11 -> 11.04698 | I26: =(F26-H26)/H26 -> -0.044205556
A27: Inventory Turnover | C27: =C4/C12 -> 754.9 | D27: =D4/D12 -> 707.6 | E27: =(C27-D27)/D27 -> 0.066845676 | F27: =F4/F12 -> 684.2 | G27: =(D27-F27)/F27 -> 0.034200526 | H27: =H4/H12 -> 658.4 | I27: =(F27-H27)/H27 -> 0.039185905
A28: Total Asset Turnover | C28: =C4/C14 -> 1.1221941 | D28: =D4/D14 -> 1.1356123 | E28: =(C28-D28)/D28 -> -0.011815757 | F28: =F4/F14 -> 1.1703729 | G28: =(D28-F28)/F28 -> -0.029700485 | H28: =H4/H14 -> 1.103587 | I28: =(F28-H28)/H28 -> 0.060517125
A29: Debt Management
A30: Debt to Equity Ratio | C30: =C16/C18 -> -1.478295 | D30: =D16/D18 -> -1.417918 | E30: =(C30-D30)/D30 -> 0.042581399 | F30: =F16/F18 -> -1.2903335 | G30: =(D30-F30)/F30 -> 0.0988772 | H30: =H16/H18 -> -1.3350054 | I30: =(F30-H30)/H30 -> -0.033461956
A31: Equity multiplier | C31: =C14/C18 -> -0.87957636 | D31: =D14/D18 -> -0.79294986 | E31: =(C31-D31)/D31 -> 0.10924587 | F31: =F14/F18 -> -0.65863001 | G31: =(D31-F31)/F31 -> 0.20393824 | H31: =H14/H18 -> -0.71252836 | I31: =(F31-H31)/H31 -> -0.075643798
A32: Profitability
A33: Net Profit Margin | C33: =_xlfn.XLOOKUP(A33,'Y24-21'!$A$4:$A$72,'Y24-21'!B4:B72) -> 0.1968 | D33: =_xlfn.XLOOKUP(A33,'Y24-21'!$A$4:$A$72,'Y24-21'!C4:C72) -> 0.2257 | E33: =(C33-D33)/D33 -> -0.12804608 | F33: =_xlfn.XLOOKUP(A33,'Y24-21'!$A$4:$A$72,'Y24-21'!D4:D72) -> 0.1937 | G33: =(D33-F33)/F33 -> 0.16520392 | H33: =_xlfn.XLOOKUP(A33,'Y24-21'!$A$4:$A$72,'Y24-21'!E4:E72) -> 0.2392 | I33: =(F33-H33)/H33 -> -0.19021739
A34: Gross Profit Margin | C34: =_xlfn.XLOOKUP($A$34,'Y24-21'!$A$4:$A$72,'Y24-21'!B4:B72) -> 0.7192 | D34: =_xlfn.XLOOKUP($A$34,'Y24-21'!$A$4:$A$72,'Y24-21'!C4:C72) -> 0.7493 | E34: =(C34-D34)/D34 -> -0.040170826 | F34: =_xlfn.XLOOKUP($A$34,'Y24-21'!$A$4:$A$72,'Y24-21'!D4:D72) -> 0.745 | G34: =(D34-F34)/F34 -> 0.0057718121 | H34: =_xlfn.XLOOKUP($A$34,'Y24-21'!$A$4:$A$72,'Y24-21'!E4:E72) -> 0.738 | I34: =(F34-H34)/H34 -> 0.0094850949
A35: Return On Assets ROA | C35: =C33*C28 -> 0.22084781 | D35: =D33*D28 -> 0.25630769 | E35: =(C35-D35)/D35 -> -0.13834887 | F35: =F33*F28 -> 0.22670123 | G35: =(D35-F35)/F35 -> 0.1305968 | H35: =H33*H28 -> 0.26397801 | I35: =(F35-H35)/H35 -> -0.14121168
A36: Return On Equity ROE | C36: =C35*C31 -> -0.19425251 | D36: =D35*D31 -> -0.20323914 | E36: =(C36-D36)/D36 -> -0.044217045 | F36: =F35*F31 -> -0.14931224 | G36: =(D36-F36)/F36 -> 0.36116872 | H36: =H35*H31 -> -0.18809182 | I36: =(F36-H36)/H36 -> -0.20617369
A37: Market Value
A38: EPS | C38: =C9/C19 -> 5.2695035 | D38: =D9/D19 -> 5.683274 | E38: =(C38-D38)/D38 -> -0.072804949 | F38: =F9/F19 -> 4.6328671 | G38: =(D38-F38)/F38 -> 0.22672934 | H38: =H9/H19 -> 5.3030303 | I38: =(F38-H38)/H38 -> -0.12637363
A39: P/E | C39: =C3/C38 -> 25.33825 | D39: =D3/D38 -> 22.990269 | E39: =(C39-D39)/D39 -> 0.10212934 | F39: =F3/F38 -> 27.645947 | G39: =(D39-F39)/F39 -> -0.16840363 | H39: =H3/H38 -> 26.0964 | I39: =(F39-H39)/H39 -> 0.059377813
A40: Book Value Per Share | C40: =C18/C19 -> -27.120567 | D40: =D18/D19 -> -27.964413 | E40: =(C40-D40)/D40 -> -0.030175689 | F40: =F18/F19 -> -31.034965 | G40: =(D40-F40)/F40 -> -0.098938479 | H40: =H18/H19 -> -28.191919 | I40: =(F40-H40)/H40 -> 0.10084613
A41: Market Capitalization (Stock Price * Shares) | C41: =C3*C19 -> 37652.64 | D41: =D3*D19 -> 36715.46 | E41: =(C41-D41)/D41 -> 0.025525487 | F41: =F3*F19 -> 36630.88 | G41: =(D41-F41)/F41 -> 0.0023089808 | H41: =H3*H19 -> 41101.83 | I41: =(F41-H41)/H41 -> -0.1087774
A42: Cash Per Share | C42: =C10/C19 -> 2.1843972 | D42: =D10/D19 -> 1.8220641 | E42: =(C42-D42)/D42 -> 0.1988586 | F42: =F10/F19 -> 1.2832168 | G42: =(D42-F42)/F42 -> 0.41991913 | H42: =H10/H19 -> 1.6363636 | I42: =(F42-H42)/H42 -> -0.21581197
A43: Revenue Per Share | C43: =C4/C19 -> 26.769504 | D43: =D4/D19 -> 25.181495 | E43: =(C43-D43)/D43 -> 0.063062535 | F43: =F4/F19 -> 23.923077 | G43: =(D43-F43)/F43 -> 0.052602671 | H43: =H4/H19 -> 22.16835 | I43: =(F43-H43)/H43 -> 0.079154594
A44: Price to Book Value | C44: =C3/C40 -> -4.9232008 | D44: =D3/D40 -> -4.672367 | E44: =(C44-D44)/D44 -> 0.053684529 | F44: =F3/F40 -> -4.1269581 | G44: =(D44-F44)/F44 -> 0.13215761 | H44: =H3/H40 -> -4.9088535 | I44: =(F44-H44)/H44 -> -0.15928269

Sheet Ratio Formulas

Sheet Sheet1
A1: Revenue distribution
I2: 2024
A3: Company | B3: 2021 | C3: 2022 | D3: 2023 | E3: 2024 | H3: Company | I3: Sales | J3: 2024 Cost of revenue | K3: 2024 gross Profit in million | L3: EPS | M3: P/E Ratio
A4: CMG | B4: 7,547.06M | C4: 8,634.65M | D4: 9871.65M | E4: 11,313.85M | H4: SHAK | I4: 1252.61 | J4: 950.14 | K4: 302.47 | L4: 1.2 | M4: 90
A5: SHAK | B5: 739.89M | C5: 900.49M | D5: 1,087.53M | E5: 1,252.61M | H5: YUM | I5: 7549 | J5: 2120 | K5: 5429 | L5: 3.8 | M5: 28
A6: MCD | B6: 23,222.9M | C6: 23,183M | D6: 25,494M | E6: 25,920M | H6: CMG | I6: 11313.85 | J6: 8296.6 | K6: 3017.69 | L6: 15 | M6: 55
A7: YUM | B7: 6,584 M | C7: 6,842M | D7: 7,076M | E7: 7,509M | H7: MCD | I7: 25920 | J7: 11210 | K7: 14710 | L7: 9.5 | M7: 25
A9: Gross Profit
A10: Gross Profit = Revenue-Cost of Revenue
H11: Company | I11: Sales | J11: 2024 Cost of revenue | K11: 2024 gross Profit in million | L11: EPS | M11: P/E Ratio
A12: Company | B12: 2024 Revenue | C12: 2024 Cost of revenue | D12: 2024 gross Profit in million | H12: SHAK | I12: 1252.61 | J12: 950.14 | K12: 302.47 | L12: 15 | M12: 55
A13: CMG | B13: 11313.85 | C13: 8296.6 | D13: 3017.69 | H13: YUM | I13: 7549 | J13: 2120 | K13: 5429 | L13: 1.2 | M13: 90
A14: SHAK | B14: 1252.61 | C14: 950.14 | D14: 302.47 | H14: CMG | I14: 11313.85 | J14: 8296.6 | K14: 3017.69 | L14: 9.5 | M14: 25
A15: MCD | B15: 25920 | C15: 11210 | D15: 14710 | H15: MCD | I15: 25920 | J15: 11210 | K15: 14710 | L15: 3.8 | M15: 28
A16: YUM | B16: 7549 | C16: 2120 | D16: 5429
A18: EPS (Earnings Per share) | H18: Company | I18: P/E Ratio | J18: EPS
A19: Company | B19: 2021 | C19: 2022 | D19: 2023 | E19: 2024 | H19: SHAK | I19: 55 | J19: 15
A20: CMG | B20: 10.5 | C20: 12 | D20: 13 | E20: 15 | H20: CMG | I20: 25 | J20: 9.5
A21: SHAK | B21: 0.5 | C21: 0.7 | D21: 0.9 | E21: 1.2 | H21: MCD | I21: 28 | J21: 3.8
A22: MCD | B22: 8 | C22: 8.3 | D22: 8.9 | E22: 9.5 | H22: YUM | I22: 90 | J22: 1.2
A23: YUM | B23: 3 | C23: 3.2 | D23: 3.5 | E23: 3.8
L24: P/E Ration (Price to Earnings)
A25: P/E Ration (Price to Earnings) | H25: Company | I25: 2024 Cost of revenue | L25: Company | M25: 2021 | N25: 2022 | O25: 2023 | P25: 2024 | Q25: EPS 2021 | R25: EPS 2022 | S25: EPS 2023 | T25: EPS 2024
A26: Company | B26: 2021 | C26: 2022 | D26: 2023 | E26: 2024 | H26: SHAK | I26: 950.14 | L26: CMG PE | M26: 70 | N26: 65 | O26: 60 | P26: 55
A27: CMG | B27: 70 | C27: 65 | D27: 60 | E27: 55 | H27: YUM | I27: 2120 | L27: SHAK PE | M27: 150 | N27: 120 | O27: 110 | P27: 90
A28: SHAK | B28: 150 | C28: 120 | D28: 110 | E28: 90 | H28: CMG | I28: 8296.6 | L28: MCD P/E | M28: 28 | N28: 27 | O28: 26 | P28: 25
A29: MCD | B29: 28 | C29: 27 | D29: 26 | E29: 25 | H29: MCD | I29: 11210 | L29: YUM P/E | M29: 32 | N29: 31 | O29: 30 | P29: 28
A30: YUM | B30: 32 | C30: 31 | D30: 30 | E30: 28 | L30: CMG Sales | M30: 7547.06 | N30: 8634.65 | O30: 9871.65 | P30: 11313.85
L31: SHAK Sales | M31: 739.89 | N31: 900.49 | O31: 1087.53 | P31: 1252.61
A32: Total sales in million USD | L32: MCD Sales | M32: 23222.9 | N32: 23183 | O32: 25494 | P32: 25920
A33: Company | B33: 2021 | C33: 2022 | D33: 2023 | E33: 2024 | L33: YUM Sales | M33: 6584 | N33: 6842 | O33: 7076 | P33: 7549
A34: CMG | B34: 7547.06 | C34: 8634.65 | D34: 9871.65 | E34: 11313.85
A35: SHAK | B35: 739.89 | C35: 900.49 | D35: 1087.53 | E35: 1252.61
A36: MCD | B36: 23222.9 | C36: 23183 | D36: 25494 | E36: 25920
A37: YUM | B37: 6584 | C37: 6842 | D37: 7076 | E37: 7549
A39: Tree map (Total sales for 2024)
A40: Company | B40: 2024 total sales
A41: CMG | B41: $11.3B
A42: SHAK | B42: $1.25B
A43: MCD | B43: $25.9B
A44: YUM | B44: $7.5B
A46: Sales and Gross Profit combo
A47: Company | B47: Sales (2024) in Millions USD | C47: Gross Profit (2024) in Millions USD
A48: CMG | B48: 11313.85 | C48: 3017.69
A49: SHAK | B49: 1252.61 | C49: 302.47
A50: MCD | B50: 25920 | C50: 14710
A51: YUM | B51: 7549 | C51: 5429
A54: STOCK PRICE AS OF DECEMBER 31ST 2024
A55: Company | B55: stock price (USD)
A56: CMG | B56: 60.3
A57: SHAK | B57: 85.5
A58: MCD | B58: 275
A59: YUM | B59: 120
A62: YOY Trend Calculations
A63: From Revenues, EPS, and profit figures, year over year (YOY) trends were derived using
A64: YOY Growth= Current year value -Previos year value /previous year value x100%
A69: P/E YOY Trend
A70: Year | B70: CMG | C70: SHAK | D70: MCD | E70: YUM
A71: 2021 | B71: 70 | C71: 150 | D71: 28 | E71: 32
A72: 2022 | B72: 65 | C72: 120 | D72: 27 | E72: 31
A73: 2023 | B73: 60 | C73: 110 | D73: 26 | E73: 30
A74: 2024 | B74: 55 | C74: 90 | D74: 25 | E74: 28
A78: EPS YOY Trend
A79: Year | B79: CMG | C79: SHAK | D79: MCD | E79: YUM
A80: 2021 | B80: 10.5 | C80: 0.5 | D80: 8 | E80: 3
A81: 2022 | B81: 12 | C81: 0.7 | D81: 8.3 | E81: 3.2
A82: 2023 | B82: 13 | C82: 0.9 | D82: 8.9 | E82: 3.5
A83: 2024 | B83: 15 | C83: 1.2 | D83: 9.5 | E83: 3.8
A86: Profits YOY Trend
A87: Year | B87: CMG | C87: SHAK | D87: MCD | E87: YUM
A88: 2021 | B88: 2791.47 | C88: 178.28 | D88: 11145 | E88: 4845
A89: 2022 | B89: 3209.17 | C89: 216.12 | D89: 11612 | E89: 4942
A90: 2023 | B90: 3676.87 | C90: 261.01 | D90: 12352 | E90: 5061
A91: 2024 | B91: 3017.69 | C91: 302.47 | D91: 14710 | E91: 5429
A94: Sales YOY Trend
A95: Year | B95: CMG | C95: SHAK | D95: MCD | E95: YUM
A96: 2021 | B96: 7547.06 | C96: 739.89 | D96: 23222.9 | E96: 6584
A97: 2022 | B97: 8634.65 | C97: 900.49 | D97: 23183 | E97: 6842
A98: 2023 | B98: 9871.65 | C98: 1087.53 | D98: 25494 | E98: 7076
A99: 2024 | B99: 11313.85 | C99: 1252.61 | D99: 25920 | E99: 7549
A103: Sales &Gross Profit Comparison
A104: Year | B104: CMG Revenue | C104: SHAK Revenue | D104: MCD Revenue | E104: YUM Revenue | F104: CMG Profit | G104: SHAK Profit | H104: MCD Profit | I104: YUM Profit
A105: 2021 | B105: 7547.06 | C105: 739.89 | D105: 23222.9 | E105: 6584 | F105: 2791.47 | G105: 178.28 | H105: 11145 | I105: 4845
A106: 2022 | B106: 8634.65 | C106: 900.49 | D106: 23183 | E106: 6842 | F106: 3209.17 | G106: 216.12 | H106: 11612 | I106: 4942
A107: 2023 | B107: 9871.65 | C107: 1087.53 | D107: 25494 | E107: 7076 | F107: 3676.87 | G107: 261.01 | H107: 12352 | I107: 5061
A108: 2024 | B108: 11313.85 | C108: 1252.61 | D108: 25920 | E108: 7549 | F108: 3017.69 | G108: 302.47 | H108: 14710 | I108: 5429
