Workbook

Sheet Exe Sum & Dashboard
Q3: DASHBOARD AREA

Sheet Memo

Sheet Project 1
A1: PROJECT 1 ASSUMPTIONS
H2: `
A3: Site Assumptions | D3: Unit Mix
A4: Project Name | B4: Apartments | D4: Unit Type | E4: # Units | F4: % Total | G4: SF/Unit | H4: SF | I4: Rent/Month | J4: Rent/SF | K4: Annual Rent
A5: County | B5: Suffolk | D5: 1 Bed / 1 Bath (A1) | E5: 121 | F5: =+E5/$E$10 -> 0.36227545 | G5: 724 | H5: =+G5*E5 -> 87604 | I5: 1657.96 | J5: =+(I5*12)/G5 -> 27.48 | K5: =+I5*12*E5 -> 2407357.9
A6: State | B6: New York | D6: 1 Bed / 1 Bath (A2) | E6: 63 | F6: =+E6/$E$10 -> 0.18862275 | G6: 879 | H6: =+G6*E6 -> 55377 | I6: 1705.26 | J6: =+(I6*12)/G6 -> 23.28 | K6: =+I6*12*E6 -> 1289176.6
A7: Building Assumptions | D7: 2 Bed / 2 Bath (B1) | E7: 114 | F7: =+E7/$E$10 -> 0.34131737 | G7: 1121 | H7: =+G7*E7 -> 127794 | I7: 2040.22 | J7: =+(I7*12)/G7 -> 21.84 | K7: =+I7*12*E7 -> 2791021
A8: Gross Buildable SF (GSF) | B8: 0 | D8: 2 Bed / 2 Bath (B2) Den | E8: 24 | F8: =+E8/$E$10 -> 0.071856287 | G8: 1230 | H8: =+G8*E8 -> 29520 | I8: 2115.6 | J8: =+(I8*12)/G8 -> 20.64 | K8: =+I8*12*E8 -> 609292.8
A9: Residential Net Rentable SF | B9: =H10 -> 316963 | D9: 3 Bed / 2 Bath (B2) | E9: 12 | F9: =+E9/$E$10 -> 0.035928144 | G9: 1389 | H9: =+G9*E9 -> 16668 | I9: 2444.64 | J9: =+(I9*12)/G9 -> 21.12 | K9: =+I9*12*E9 -> 352028.16
A10: Commercial Net Rentable SF | B10: 0 | D10: Total/Average | E10: =SUM(E5:E9) -> 334 | F10: =SUM(F5:F9) -> 1 | G10: =SUMPRODUCT(G5:G9,E5:E9)/E10 -> 948.99102 | H10: =SUM(H5:H9) -> 316963 | I10: =SUMPRODUCT(I5:I9,E5:E9)/E10 -> 1858.5021 | J10: =+(I10*12)/G10 -> 23.500776 | K10: =+E10*I10*12 -> 7448876.4
A11: Total Net Rentable SF (NSF) | B11: =B9+B10 -> 316963 | D11: 1 Bed | E11: =SUM(E5:E6) -> 184 | F11: =+E11/$E$10 -> 0.5508982 | G11: =+SUMPRODUCT(G5:G6,E5:E6)/E11 -> 777.07065 | H11: =+G11*E11 -> 142981 | I11: =+SUMPRODUCT(I5:I6,E5:E6)/E11 -> 1674.1551 | J11: =+(I11*12)/G11 -> 25.853327 | K11: =+E11*I11*12 -> 3696534.5
A12: Efficiency Factor | B12: 0 | D12: 2 Bed | E12: =SUM(E7:E8) -> 138 | F12: =+E12/$E$10 -> 0.41317365 | G12: =SUMPRODUCT(G7:G8,E7:E8)/E12 -> 1139.9565 | H12: =+G12*E12 -> 157314 | I12: =+SUMPRODUCT(I7:I8,E7:E8)/E12 -> 2053.3296 | J12: =+(I12*12)/G12 -> 21.61482 | K12: =+E12*I12*12 -> 3400313.8
A13: Residential Units | B13: =E10 -> 334 | D13: 3 Bed | E13: =+E9 -> 12 | F13: =+E13/$E$10 -> 0.035928144 | G13: =+G9 -> 1389 | H13: =+G13*E13 -> 16668 | I13: =I9 -> 2444.64 | J13: =+(I13*12)/G13 -> 21.12 | K13: =+E13*I13*12 -> 352028.16
A14: Avg. Unit Size | B14: =G10 -> 948.99102
A15: Parking Spaces | B15: 546 | D15: Market Rent Growth | F15: 0.03
A16: Storage Units | B16: 100
A18: Exit Assumptions | D18: Sources And Uses | E18: % Total | F18: $ Amount | G18: $/Unit | H18: $/NSF
A19: Hold Period (Years) | B19: 11 | D19: Sources
A20: Sale Date | B20: 44927 | D20: Equity | E20: 0.34535046 | F20: 30333255 | G20: =+F20/$E$10 -> 90818.128 | H20: =+G20/$G$10 -> 95.699671
A21: Forward NOI | B21: ='Project 1 Financial Analysis'!O54 -> 7709771.2 | D21: LP Equity | E21: 0.31081541 | F21: 27299929 | G21: =+F21/$E$10 -> 81736.316 | H21: =+G21/$G$10 -> 86.129704
A22: Exit Cap | B22: 0.0525 | D22: GP Equity | E22: 0.034535046 | F22: 3033325.5 | G22: =+F22/$E$10 -> 9081.8128 | H22: =+G22/$G$10 -> 9.5699671
A23: Gross Proceeds | B23: =+B21/B22 -> 1.4685278e+08 | D23: Debt | E23: 0.65464954 | F23: =52654771+F29 -> 57637500 | G23: =+F23/$E$10 -> 172567.37 | H23: =+G23/$G$10 -> 181.84299
A24: Per Unit | B24: =+B23/E10 -> 439678.99 | D24: Total Sources | E24: 1 | F24: =SUM(F21:F23) -> 87970755 | G24: =SUM(G21:G23) -> 263385.49 | H24: =SUM(H21:H23) -> 277.54266
A25: Per NSF | B25: =+B23/H10 -> 463.31207 | D25: Uses
A26: Cost Of Sale | B26: 0.02 | D26: Acquisitions Costs | E26: 0.1140798 | F26: ='Project 1 Financial Analysis'!B64*-1 -> 10157500 | G26: 30000 | H26: 31.612523
D27: Hard Costs | E27: 0.64456738 | F27: =+'Project 1 Financial Analysis'!B71*-1 -> 56614451 | G27: 169504.35 | H27: 178.61533
D28: Soft Costs | E28: 0.18462341 | F28: =+'Project 1 Financial Analysis'!B83*-1 -> 16216075 | G28: 48551.122 | H28: 51.160781
A29: Construction Financing | D29: Financing Costs | E29: 0.056729413 | F29: =+B57 -> 4982729 | G29: 14918.35 | H29: 15.720223
A30: Loan Amount | B30: 57637500 | D30: Total Uses | E30: 1 | F30: =SUM(F26:F29) -> 87970755 | G30: =SUM(G26:G29) -> 262973.82 | H30: =SUM(H26:H29) -> 277.10886
A31: Per Unit | B31: =+B30/E10 -> 172567.37
A32: Per NSF | B32: =+B31/G10 -> 181.84299
A33: Going-In Metrics (Untrended Pro Forma)
A34: Pro Forma NCF Year 6 | B34: =+'Project 1 Financial Analysis'!J94 -> 4888059.7
A35: Valuation Cap Rate | B35: 0.0525
A36: Valuation | B36: ='Project 1 Financial Analysis'!O90 -> 1.4685278e+08
A37: LTV % | B37: =+B30/B36 -> 0.3924849
A38: Debt Yield | B38: =+B34/B30 -> 0.084806935
A39: Takeout Metrics
A40: Year 6 NOI | B40: ='Project 1 Financial Analysis'!J51 -> 6687602.9
A41: Valuation Cap Rate | B41: 0.0525
A42: Valuation | B42: =+B36 -> 1.4685278e+08
A43: Debt Yield | B43: =+B40/B30 -> 0.11602868
A44: Financing Costs
A45: Appraisal | B45: 15000
A46: Lender Third Party Reports | B46: 30000
A47: Lender Legal Fees | B47: 100000
A48: Lender Inspection | B48: 31050
A49: Mortgage Recording Tax | B49: 191475
A50: Doc Stamps and Intangible Tax | B50: 25000
A51: Lender Fee | B51: 575000
A52: Mortgage Broker Fee | B52: 517500
A53: Equity Broker Fee | B53: 245699.36
A54: Title Insurance | B54: 86251
A55: Monthly Title Updates | B55: 11950
A56: Interest Reserve | B56: 3153803.6
A57: Total Financing Costs | B57: 4982729

Sheet Project 1 Unit Mix Pivot
A3: Row Labels | B3: Sum of Annual Rent | C3: Sum of Rent/SF
A4: 2 Bed / 2 Bath (B1) | B4: 2791021 | C4: 21.84
A5: 1 Bed / 1 Bath (A1) | B5: 2407357.9 | C5: 27.48
A6: 1 Bed / 1 Bath (A2) | B6: 1289176.6 | C6: 23.28
A7: 2 Bed / 2 Bath (B2) Den | B7: 609292.8 | C7: 20.64
A8: 3 Bed / 2 Bath (B2) | B8: 352028.16 | C8: 21.12
A9: Grand Total | B9: 7448876.4 | C9: 114.36

Sheet Project 1 Financial Analysis
A1: PROJECT 1 FINANCIAL ANALYSIS
I2: `
A3: Year | D3: 0 | E3: 1 | F3: 2 | G3: 3 | H3: 4 | I3: 5 | J3: 6 | K3: 7 | L3: 8 | M3: 9 | N3: 10 | O3: 11
A4: Month | D4: 0 | E4: 12 | F4: 24 | G4: 36 | H4: 48 | I4: 60 | J4: 72 | K4: 84 | L4: 96 | M4: 108 | N4: 120 | O4: 132
A5: Ending Date | D5: 44927 | E5: =+D5+365 -> 45292 | F5: =+E5+365 -> 45657 | G5: =+F5+365 -> 46022 | H5: =+G5+365 -> 46387 | I5: =+H5+365 -> 46752 | J5: =+I5+365 -> 47117 | K5: =+J5+365 -> 47482 | L5: =+K5+365 -> 47847 | ... O5: =+N5+365 -> 48942
A7: Property Performance
A8: Residential Units
A9: Units Complete | D9: 0 | E9: 0 | F9: 75 | G9: 225 | H9: 275 | I9: 334 | J9: 334 | K9: 334 | L9: 334 | M9: 334 | N9: 334 | O9: 334
A10: Completed % | D10: 0 | E10: 0 | F10: =+F9/334 -> 0.2245509 | G10: =+G9/334 -> 0.67365269 | H10: =+H9/334 -> 0.82335329 | I10: =+I9/334 -> 1 | J10: =+J9/334 -> 1 | K10: =+K9/334 -> 1 | L10: =+L9/334 -> 1 | M10: =+M9/334 -> 1 | ... O10: =+O9/334 -> 1
A11: Unit Type | B11: # Units | C11: SF/Unit
A12: 1 Bed / 1 Bath (A1) | B12: ='Project 1'!E5 -> 121 | C12: 724 | D12: 0 | E12: 0 | F12: 25 | G12: 50 | H12: 100 | I12: 121 | J12: 121 | K12: 121 | L12: 121 | M12: 121 | N12: 121 | O12: 121
A13: 1 Bed / 1 Bath (A2) | B13: ='Project 1'!E6 -> 63 | C13: 879 | D13: 0 | E13: 0 | F13: 25 | G13: 63 | H13: 63 | I13: 63 | J13: 63 | K13: 63 | L13: 63 | M13: 63 | N13: 63 | O13: 63
A14: 2 Bed / 2 Bath (B1) | B14: ='Project 1'!E7 -> 114 | C14: 1121 | D14: 0 | E14: 0 | F14: 25 | G14: 76 | H14: 76 | I14: 114 | J14: 114 | K14: 114 | L14: 114 | M14: 114 | N14: 114 | O14: 114
A15: 2 Bed / 2 Bath (B2) Den | B15: ='Project 1'!E8 -> 24 | C15: 1230 | D15: 0 | E15: 0 | F15: 0 | G15: 24 | H15: 24 | I15: 24 | J15: 24 | K15: 24 | L15: 24 | M15: 24 | N15: 24 | O15: 24
A16: 3 Bed / 2 Bath (B2) | B16: ='Project 1'!E9 -> 12 | C16: 1389 | D16: 0 | E16: 0 | F16: 0 | G16: 12 | H16: 12 | I16: 12 | J16: 12 | K16: 12 | L16: 12 | M16: 12 | N16: 12 | O16: 12
A17: Cumulative Units Leased | B17: Rent/Month | C17: Rent/SF | D17: =SUM(D12:D16) -> 0 | E17: =SUM(E12:E16) -> 0 | F17: =SUM(F12:F16) -> 75 | G17: =SUM(G12:G16) -> 225 | H17: =SUM(H12:H16) -> 275 | I17: =SUM(I12:I16) -> 334 | J17: =SUM(J12:J16) -> 334 | K17: =SUM(K12:K16) -> 334 | ... O17: =SUM(O12:O16) -> 334
A18: 1 Bed / 1 Bath (A1) | B18: 1657.96 | C18: =+B18/C12 -> 2.29 | D18: =+D12*$B$18*12 -> 0 | E18: =+E12*$B$18*12 -> 0 | F18: =+F12*$B$18*12*(1+F$24)^F$27 -> 527678.93 | G18: =+G12*$B$18*12*(1+G$24)^G$27 -> 1087018.6 | H18: =+H12*$B$18*12*(1+H$24)^H$27 -> 2239258.3 | I18: =+I12*$B$18*12*(1+I$24)^I$27 -> 2790787.6 | J18: =+J12*$B$18*12*(1+J$24)^J$27 -> 2874511.3 | K18: =+K12*$B$18*12*(1+K$24)^K$27 -> 2960746.6 | L18: =+L12*$B$18*12*(1+L$24)^L$27 -> 3049569 | M18: =+M12*$B$18*12*(1+M$24)^M$27 -> 3141056.1 | ... O18: =+O12*$B$18*12*(1+O$24)^O$27 -> 3332346.4
A19: 1 Bed / 1 Bath (A2) | B19: 1705.26 | C19: =+B19/C13 -> 1.94 | D19: =+D13*$B$19*12 -> 0 | E19: =+E13*$B$19*12 -> 0 | F19: =+F13*$B$19*12*(1+F$24)^F$27 -> 542733.1 | G19: =+G13*$B$19*12*(1+G$24)^G$27 -> 1408718 | H19: =+H13*$B$19*12*(1+H$24)^H$27 -> 1450979.6 | I19: =+I13*$B$19*12*(1+I$24)^I$27 -> 1494509 | J19: =+J13*$B$19*12*(1+J$24)^J$27 -> 1539344.2 | K19: =+K13*$B$19*12*(1+K$24)^K$27 -> 1585524.6 | L19: =+L13*$B$19*12*(1+L$24)^L$27 -> 1633090.3 | M19: =+M13*$B$19*12*(1+M$24)^M$27 -> 1682083 | ... O19: =+O13*$B$19*12*(1+O$24)^O$27 -> 1784521.9
A20: 2 Bed / 2 Bath (B1) | B20: 2040.22 | C20: =+B20/C14 -> 1.82 | D20: =+D14*$B$20*12 -> 0 | E20: =+E14*$B$20*12 -> 0 | F20: =+F14*$B$20*12*(1+F$24)^F$27 -> 649340.82 | G20: =+G14*$B$20*12*(1+G$24)^G$27 -> 2033216 | H20: =+H14*$B$20*12*(1+H$24)^H$27 -> 2094212.5 | I20: =+I14*$B$20*12*(1+I$24)^I$27 -> 3235558.2 | J20: =+J14*$B$20*12*(1+J$24)^J$27 -> 3332625 | K20: =+K14*$B$20*12*(1+K$24)^K$27 -> 3432603.7 | L20: =+L14*$B$20*12*(1+L$24)^L$27 -> 3535581.8 | M20: =+M14*$B$20*12*(1+M$24)^M$27 -> 3641649.3 | ... O20: =+O14*$B$20*12*(1+O$24)^O$27 -> 3863425.7
A21: 2 Bed / 2 Bath (B2) Den | B21: 2115.6 | C21: =+B21/C15 -> 1.72 | D21: =+D15*$B$21*12 -> 0 | E21: =+E15*$B$21*12 -> 0 | F21: =+F15*$B$21*12*(1+F$24)^F$27 -> 0 | G21: =+G15*$B$21*12*(1+G$24)^G$27 -> 665790.69 | H21: =+H15*$B$21*12*(1+H$24)^H$27 -> 685764.41 | I21: =+I15*$B$21*12*(1+I$24)^I$27 -> 706337.35 | J21: =+J15*$B$21*12*(1+J$24)^J$27 -> 727527.47 | K21: =+K15*$B$21*12*(1+K$24)^K$27 -> 749353.29 | L21: =+L15*$B$21*12*(1+L$24)^L$27 -> 771833.89 | M21: =+M15*$B$21*12*(1+M$24)^M$27 -> 794988.91 | ... O21: =+O15*$B$21*12*(1+O$24)^O$27 -> 843403.73
A22: 3 Bed / 2 Bath (B2) | B22: 2444.64 | C22: =+B22/C16 -> 1.76 | D22: =+D16*$B$22*12 -> 0 | E22: =+E16*$B$22*12 -> 0 | F22: =+F16*$B$22*12*(1+F$24)^F$27 -> 0 | G22: =+G16*$B$22*12*(1+G$24)^G$27 -> 384670.68 | H22: =+H16*$B$22*12*(1+H$24)^H$27 -> 396210.8 | I22: =+I16*$B$22*12*(1+I$24)^I$27 -> 408097.12 | J22: =+J16*$B$22*12*(1+J$24)^J$27 -> 420340.03 | K22: =+K16*$B$22*12*(1+K$24)^K$27 -> 432950.23 | L22: =+L16*$B$22*12*(1+L$24)^L$27 -> 445938.74 | M22: =+M16*$B$22*12*(1+M$24)^M$27 -> 459316.9 | ... O22: =+O16*$B$22*12*(1+O$24)^O$27 -> 487289.3
A23: Avg Market Rent ($/Unit/Mo.) | D23: 0 | E23: 0 | F23: =SUM(F18:F22)/F17/12 -> 1910.8365 | G23: =SUM(G18:G22)/G17/12 -> 2066.4496 | H23: =SUM(H18:H22)/H17/12 -> 2080.735 | I23: =SUM(I18:I22)/I17/12 -> 2154.5133 | J23: =SUM(J18:J22)/J17/12 -> 2219.1487 | K23: =SUM(K18:K22)/K17/12 -> 2285.7232 | L23: =SUM(L18:L22)/L17/12 -> 2354.2949 | M23: =SUM(M18:M22)/M17/12 -> 2424.9237 | ... O23: =SUM(O18:O22)/O17/12 -> 2572.6015
A24: Market Rent Growth | D24: 0 | E24: ='Project 1'!$F$15 -> 0.03 | F24: ='Project 1'!$F$15 -> 0.03 | G24: ='Project 1'!$F$15 -> 0.03 | H24: ='Project 1'!$F$15 -> 0.03 | I24: ='Project 1'!$F$15 -> 0.03 | J24: ='Project 1'!$F$15 -> 0.03 | K24: ='Project 1'!$F$15 -> 0.03 | L24: ='Project 1'!$F$15 -> 0.03 | ... O24: ='Project 1'!$F$15 -> 0.03
A26: Operating Cash Flow | B26: Total/WA
A27: Year | D27: 0 | E27: 1 | F27: 2 | G27: 3 | H27: 4 | I27: 5 | J27: 6 | K27: 7 | L27: 8 | M27: 9 | N27: 10 | O27: 11
A28: Month | D28: 0 | E28: 12 | F28: 24 | G28: 36 | H28: 48 | I28: 60 | J28: 72 | K28: 84 | L28: 96 | M28: 108 | N28: 120 | O28: 132
A29: Ending Date | D29: 44927 | E29: =+D29+365 -> 45292 | F29: =+E29+365 -> 45657 | G29: =+F29+365 -> 46022 | H29: =+G29+365 -> 46387 | I29: =+H29+365 -> 46752 | J29: =+I29+365 -> 47117 | K29: =+J29+365 -> 47482 | L29: =+K29+365 -> 47847 | ... O29: =+N29+365 -> 48942
A30: Revenue
A31: Apartment Rental Revenue | B31: =SUM(D31:O31) -> 80333170 | D31: 0 | E31: 0 | F31: =SUM(F18:F22) -> 1719752.8 | G31: =SUM(G18:G22) -> 5579414 | H31: =SUM(H18:H22) -> 6866425.5 | I31: =SUM(I18:I22) -> 8635289.3 | J31: =SUM(J18:J22) -> 8894348 | K31: =SUM(K18:K22) -> 9161178.4 | L31: =SUM(L18:L22) -> 9436013.8 | M31: =SUM(M18:M22) -> 9719094.2 | ... O31: =SUM(O18:O22) -> 10310987
A32: Parking Income 5% of Rent | B32: =SUM(D32:O32) -> 4016658.5 | D32: 0 | E32: 0 | F32: =+F31*0.05 -> 85987.642 | G32: =+G31*0.05 -> 278970.7 | H32: =+H31*0.05 -> 343321.28 | I32: =+I31*0.05 -> 431764.46 | J32: =+J31*0.05 -> 444717.4 | K32: =+K31*0.05 -> 458058.92 | L32: =+L31*0.05 -> 471800.69 | M32: =+M31*0.05 -> 485954.71 | ... O32: =+O31*0.05 -> 515549.35
A33: Tenant Storage Income 2% of Rent | B33: =SUM(D33:O33) -> 1606663.4 | D33: 0 | E33: 0 | F33: =+F31*0.02 -> 34395.057 | G33: =+G31*0.02 -> 111588.28 | H33: =+H31*0.02 -> 137328.51 | I33: =+I31*0.02 -> 172705.79 | J33: =+J31*0.02 -> 177886.96 | K33: =+K31*0.02 -> 183223.57 | L33: =+L31*0.02 -> 188720.28 | M33: =+M31*0.02 -> 194381.88 | ... O33: =+O31*0.02 -> 206219.74
A35: Potential Gross Revenue | B35: =SUM(D35:O35) -> 85956492 | D35: 0 | E35: 0 | F35: =SUM(F31:F33) -> 1840135.5 | G35: =SUM(G31:G33) -> 5969972.9 | H35: =SUM(H31:H33) -> 7347075.3 | I35: =SUM(I31:I33) -> 9239759.5 | J35: =SUM(J31:J33) -> 9516952.3 | K35: =SUM(K31:K33) -> 9802460.9 | L35: =SUM(L31:L33) -> 10096535 | M35: =SUM(M31:M33) -> 10399431 | ... O35: =SUM(O31:O33) -> 11032756
A36: Vacancy Loss - Residential -2% | B36: =SUM(D36:O36) -> 1719129.8 | D36: 0 | E36: 0 | F36: =+F35*0.02 -> 36802.711 | G36: =+G35*0.02 -> 119399.46 | H36: =+H35*0.02 -> 146941.51 | I36: =+I35*0.02 -> 184795.19 | J36: =+J35*0.02 -> 190339.05 | K36: =+K35*0.02 -> 196049.22 | L36: =+L35*0.02 -> 201930.69 | M36: =+M35*0.02 -> 207988.62 | ... O36: =+O35*0.02 -> 220655.12
A37: Vacancy Loss - Parking -2% | B37: =SUM(D37:O37) -> 80333.17 | D37: 0 | E37: 0 | F37: =+F32*0.02 -> 1719.7528 | G37: =+G32*0.02 -> 5579.414 | H37: =+H32*0.02 -> 6866.4255 | I37: =+I32*0.02 -> 8635.2893 | J37: =+J32*0.02 -> 8894.348 | K37: =+K32*0.02 -> 9161.1784 | L37: =+L32*0.02 -> 9436.0138 | M37: =+M32*0.02 -> 9719.0942 | ... O37: =+O32*0.02 -> 10310.987
A38: Vacancy Loss - Storage -2% | B38: =SUM(D38:O38) -> 32133.268 | D38: 0 | E38: 0 | F38: =+F33*0.02 -> 687.90114 | G38: =+G33*0.02 -> 2231.7656 | H38: =+H33*0.02 -> 2746.5702 | I38: =+I33*0.02 -> 3454.1157 | J38: =+J33*0.02 -> 3557.7392 | K38: =+K33*0.02 -> 3664.4714 | L38: =+L33*0.02 -> 3774.4055 | M38: =+M33*0.02 -> 3887.6377 | ... O38: =+O33*0.02 -> 4124.3948
A39: Effective Gross Revenue | B39: =SUM(D39:O39) -> 84124896 | D39: 0 | E39: 0 | F39: =+F35-F36-F37-F38 -> 1800925.2 | G39: =+G35-G36-G37-G38 -> 5842762.3 | H39: =+H35-H36-H37-H38 -> 7190520.8 | I39: =+I35-I36-I37-I38 -> 9042874.9 | J39: =+J35-J36-J37-J38 -> 9314161.2 | K39: =+K35-K36-K37-K38 -> 9593586 | L39: =+L35-L36-L37-L38 -> 9881393.6 | M39: =+M35-M36-M37-M38 -> 10177835 | ... O39: =+O35-O36-O37-O38 -> 10797666
A41: Operating Expenses
A42: Real Estate Taxes | B42: =SUM(D42:O42) -> -9161691.7 | D42: 0 | E42: 0 | F42: -350843.75 | G42: -867285.75 | H42: -893304.32 | I42: -920103.45 | J42: -947706.56 | K42: -976137.75 | L42: -1005421.9 | M42: -1035584.5 | N42: -1066652.1 | O42: -1098651.6
A43: Payroll & Benefits | B43: =SUM(D43:O43) -> -5409724 | D43: 0 | E43: 0 | F43: -207163.47 | G43: -512108.1 | H43: -527471.34 | I43: -543295.48 | J43: -559594.35 | K43: -576382.18 | L43: -593673.64 | M43: -611483.85 | N43: -629828.37 | O43: -648723.22
A44: Insurance | B44: =SUM(D44:O44) -> -916169.17 | D44: 0 | E44: 0 | F44: -35084.375 | G44: -86728.575 | H44: -89330.432 | I44: -92010.345 | J44: -94770.656 | K44: -97613.775 | L44: -100542.19 | M44: -103558.45 | N44: -106665.21 | O44: -109865.16
A45: Utilities | B45: =SUM(D45:O45) -> -2477321.4 | D45: 0 | E45: 0 | F45: -94868.15 | G45: -234514.07 | H45: -241549.49 | I45: -248795.97 | J45: -256259.85 | K45: -263947.65 | L45: -271866.08 | M45: -280022.06 | N45: -288422.72 | O45: -297075.4
A46: Repairs & Maintenance,Con Serv, TO | B46: =SUM(D46:O46) -> -3749726.3 | D46: 0 | E46: 0 | F46: -143594.45 | G46: -354965.47 | H46: -365614.43 | I46: -376582.87 | J46: -387880.35 | K46: -399516.76 | L46: -411502.27 | M46: -423847.33 | N46: -436562.75 | O46: -449659.64
A47: Administrative & Marketing | B47: =SUM(D47:O47) -> -1960602 | D47: 0 | E47: 0 | F47: -75080.562 | G47: -185599.15 | H47: -191167.13 | I47: -196902.14 | J47: -202809.2 | K47: -208893.48 | L47: -215160.28 | M47: -221615.09 | N47: -228263.54 | O47: -235111.45
A48: Management Fee | B48: =SUM(D48:O48) -> -1716293.1 | D48: 0 | E48: 0 | F48: -65724.837 | G48: -162471.8 | H48: -167345.95 | I48: -172366.33 | J48: -177537.32 | K48: -182863.44 | L48: -188349.34 | M48: -193999.82 | N48: -199819.82 | O48: -205814.41
A49: Total Operating Expenses | B49: =SUM(D49:O49) -> -25391528 | D49: 0 | E49: 0 | F49: =SUM(F42:F48) -> -972359.59 | G49: =SUM(G42:G48) -> -2403672.9 | H49: =SUM(H42:H48) -> -2475783.1 | I49: =SUM(I42:I48) -> -2550056.6 | J49: =SUM(J42:J48) -> -2626558.3 | K49: =SUM(K42:K48) -> -2705355 | L49: =SUM(L42:L48) -> -2786515.7 | M49: =SUM(M42:M48) -> -2870111.2 | ... O49: =SUM(O42:O48) -> -3044900.9
A51: Net Operating Income EBIT | B51: =SUM(D51:O51) -> 58733368 | D51: 0 | E51: 0 | F51: =+F39+F49 -> 828565.59 | G51: =+G39+G49 -> 3439089.4 | H51: =+H39+H49 -> 4714737.7 | I51: =+I39+I49 -> 6492818.4 | J51: =+J39+J49 -> 6687602.9 | K51: =+K39+K49 -> 6888231 | L51: =+L39+L49 -> 7094877.9 | M51: =+M39+M49 -> 7307724.3 | ... O51: =+O39+O49 -> 7752764.7
A52: Operating Profit Margin | D52: 0 | E52: 0 | F52: =+F51/F39 -> 0.46007774 | G52: =+G51/G39 -> 0.58860676 | H52: =+H51/H39 -> 0.65568793 | I52: =+I51/I39 -> 0.71800378 | J52: =+J51/J39 -> 0.71800378 | K52: =+K51/K39 -> 0.71800378 | L52: =+L51/L39 -> 0.71800378 | M52: =+M51/M39 -> 0.71800378 | ... O52: =+O51/O39 -> 0.71800378
A53: Reserves | B53: =SUM(D53:O53) -> -429980 | D53: 0 | E53: 0 | F53: -43002.5 | G53: -43001.5 | H53: -43000.5 | I53: -42999.5 | J53: -42998.5 | K53: -42997.5 | L53: -42996.5 | M53: -42995.5 | N53: -42994.5 | O53: -42993.5
A54: Net Cash Flow | B54: =SUM(D54:O54) -> 58303388 | D54: 0 | E54: 0 | F54: =+F51+F53 -> 785563.09 | G54: =+G51+G53 -> 3396087.9 | H54: =+H51+H53 -> 4671737.2 | I54: =+I51+I53 -> 6449818.9 | J54: =+J51+J53 -> 6644604.4 | K54: =+K51+K53 -> 6845233.5 | L54: =+L51+L53 -> 7051881.4 | M54: =+M51+M53 -> 7264728.8 | ... O54: =+O51+O53 -> 7709771.2
A55: Year | D55: 0 | E55: 1 | F55: 2 | G55: 3 | H55: 4 | I55: 5 | J55: 6 | K55: 7 | L55: 8 | M55: 9 | N55: 10 | O55: 11
A56: Development Cash Flow | B56: Total | D56: 44927 | E56: =+D56+365 -> 45292 | F56: =+E56+365 -> 45657 | G56: =+F56+365 -> 46022 | H56: =+G56+365 -> 46387 | I56: =+H56+365 -> 46752 | J56: =+I56+365 -> 47117 | K56: =+J56+365 -> 47482 | L56: =+K56+365 -> 47847 | ... O56: =+N56+365 -> 48942
A57: Acquisition Costs
A58: Land Costs | B58: =SUM(D58:O58) -> -10020000 | D58: -10020000 | E58: 0 | F58: 0 | G58: 0 | H58: 0 | I58: 0 | J58: 0 | K58: 0 | L58: 0 | M58: 0 | N58: 0 | O58: 0
A59: Legal Fees (Acquisition & LLC) | B59: =SUM(D59:O59) -> -25000 | D59: -25000 | E59: 0 | F59: 0 | G59: 0 | H59: 0 | I59: 0 | J59: 0 | K59: 0 | L59: 0 | M59: 0 | N59: 0 | O59: 0
A60: Buyers Brokers Fee | B60: =SUM(D60:O60) -> -30000 | D60: -30000 | E60: 0 | F60: 0 | G60: 0 | H60: 0 | I60: 0 | J60: 0 | K60: 0 | L60: 0 | M60: 0 | N60: 0 | O60: 0
A61: Acquisition Fee | B61: =SUM(D61:O61) -> -5000 | D61: -5000 | E61: 0 | F61: 0 | G61: 0 | H61: 0 | I61: 0 | J61: 0 | K61: 0 | L61: 0 | M61: 0 | N61: 0 | O61: 0
A62: Other Closing Costs | B62: =SUM(D62:O62) -> -75000 | D62: -75000 | E62: 0 | F62: 0 | G62: 0 | H62: 0 | I62: 0 | J62: 0 | K62: 0 | L62: 0 | M62: 0 | N62: 0 | O62: 0
A63: Other Pre-Development DD Costs | B63: =SUM(D63:O63) -> -2500 | D63: -2500 | E63: 0 | F63: 0 | G63: 0 | H63: 0 | I63: 0 | J63: 0 | K63: 0 | L63: 0 | M63: 0 | N63: 0 | O63: 0
A64: Total Acquisitions Costs | B64: =SUM(B58:B63) -> -10157500 | D64: =SUM(D58:D63) -> -10157500 | E64: =SUM(E58:E63) -> 0 | F64: =SUM(F58:F63) -> 0 | G64: =SUM(G58:G63) -> 0 | H64: =SUM(H58:H63) -> 0 | I64: =SUM(I58:I63) -> 0 | J64: =SUM(J58:J63) -> 0 | K64: =SUM(K58:K63) -> 0 | ... O64: =SUM(O58:O63) -> 0
A66: Hard Costs
A67: Building Construction Costs | B67: =SUM(D67:O67) -> -43351270 | D67: 0 | E67: -17719703 | F67: -25390228 | G67: -241338.78 | H67: 0 | I67: 0 | J67: 0 | K67: 0 | L67: 0 | M67: 0 | N67: 0 | O67: 0
A68: Structure Parking Costs | B68: =SUM(D68:O68) -> -7985768 | D68: 0 | E68: -3264159.1 | F68: -4677151.8 | G68: -44457.186 | H68: 0 | I68: 0 | J68: 0 | K68: 0 | L68: 0 | M68: 0 | N68: 0 | O68: 0
A69: Sitework | B69: =SUM(D69:O69) -> -2581487 | D69: 0 | E69: -1055175.2 | F69: -1511940.5 | G69: -14371.272 | H69: 0 | I69: 0 | J69: 0 | K69: 0 | L69: 0 | M69: 0 | N69: 0 | O69: 0
A70: Hard Cost Contingency | B70: =SUM(D70:O70) -> -2695926.2 | D70: 0 | E70: -1101951.9 | F70: -1578966 | G70: -15008.362 | H70: 0 | I70: 0 | J70: 0 | K70: 0 | L70: 0 | M70: 0 | N70: 0 | O70: 0
A71: Total Hard Costs | B71: =SUM(B65:B70) -> -56614451 | D71: 0 | E71: =SUM(E67:E70) -> -23140990 | F71: =SUM(F67:F70) -> -33158286 | G71: =SUM(G67:G70) -> -315175.6 | H71: =SUM(H67:H70) -> 0 | I71: =SUM(I67:I70) -> 0 | J71: =SUM(J67:J70) -> 0 | K71: =SUM(K67:K70) -> 0 | L71: =SUM(L67:L70) -> 0 | ... O71: =SUM(O67:O70) -> 0
A73: Soft Costs
A74: Legal Fees | B74: =SUM(D74:O74) -> -250000 | D74: 0 | E74: -102186.76 | F74: -146421.48 | G74: -1391.763 | H74: 0 | I74: 0 | J74: 0 | K74: 0 | L74: 0 | M74: 0 | N74: 0 | O74: 0
A75: Insurance, Taxes & Mermit Fees | B75: =SUM(D75:O75) -> -9423458 | D75: 0 | E75: -3851810.6 | F75: -5519186.5 | G75: -52460.881 | H75: 0 | I75: 0 | J75: 0 | K75: 0 | L75: 0 | M75: 0 | N75: 0 | O75: 0
A76: Architecture, Engineering & Survey | B76: =SUM(D76:O76) -> -2000000 | D76: 0 | E76: -817494.09 | F76: -1171371.8 | G76: -11134.104 | H76: 0 | I76: 0 | J76: 0 | K76: 0 | L76: 0 | M76: 0 | N76: 0 | O76: 0
A77: FF&E | B77: =SUM(D77:O77) -> -400000 | D77: 0 | E77: -163498.82 | F77: -234274.36 | G77: -2226.8208 | H77: 0 | I77: 0 | J77: 0 | K77: 0 | L77: 0 | M77: 0 | N77: 0 | O77: 0
A78: Marketing Costs | B78: =SUM(D78:O78) -> -300000 | D78: 0 | E78: -122624.11 | F78: -175705.77 | G78: -1670.1156 | H78: 0 | I78: 0 | J78: 0 | K78: 0 | L78: 0 | M78: 0 | N78: 0 | O78: 0
A79: Misc. Reimbursable | B79: =SUM(D79:O79) -> -137500 | D79: 0 | E79: -56202.718 | F79: -80531.812 | G79: -765.46965 | H79: 0 | I79: 0 | J79: 0 | K79: 0 | L79: 0 | M79: 0 | N79: 0 | O79: 0
A80: Construction Management Fee | B80: =SUM(D80:O80) -> -539185.25 | D80: 0 | E80: -220390.38 | F80: -315793.2 | G80: -3001.6723 | H80: 0 | I80: 0
A81: Developers Overhead | B81: =SUM(D81:O81) -> -2540383.5 | D81: 0 | E81: -1038374.3 | F81: -1487866.8 | G81: -14142.447 | H81: 0 | I81: 0
A82: Soft Costs Contingency | B82: =SUM(D82:O82) -> -625547.9 | D82: 0 | E82: -255690.85 | F82: -366374.59 | G82: -3482.4577 | H82: 0 | I82: 0 | J82: 0 | K82: 0 | L82: 0 | M82: 0 | N82: 0 | O82: 0
A83: Total Soft Costs | B83: =SUM(B74:B82) -> -16216075 | D83: =SUM(D74:D82) -> 0 | E83: =SUM(E74:E82) -> -6628272.6 | F83: =SUM(F74:F82) -> -9497526.4 | G83: =SUM(G74:G82) -> -90275.731 | H83: =SUM(H74:H82) -> 0 | I83: =SUM(I74:I82) -> 0 | J83: =SUM(J74:J82) -> 0 | K83: =SUM(K74:K82) -> 0 | ... O83: =SUM(O74:O82) -> 0
A85: Total Development Cash Flow | B85: =+B83+B71+B64 -> -82988026 | D85: =+D83+D71+D64 -> -10157500 | E85: =+E83+E71+E64 -> -29769262 | F85: =+F83+F71+F64 -> -42655812 | G85: =+G83+G71+G64 -> -405451.33 | H85: =+H83+H71+H64 -> 0 | I85: =+I83+I71+I64 -> 0 | J85: =+J83+J71+J64 -> 0 | K85: =+K83+K71+K64 -> 0 | ... O85: =+O83+O71+O64 -> 0
A86: Year | D86: 0 | E86: 1 | F86: 2 | G86: 3 | H86: 4 | I86: 5 | J86: 6 | K86: 7 | L86: 8 | M86: 9 | N86: 10 | O86: 11
A87: Sale Proceeds | B87: Total | D87: 44927 | E87: =+D87+365 -> 45292 | F87: =+E87+365 -> 45657 | G87: =+F87+365 -> 46022 | H87: =+G87+365 -> 46387 | I87: =+H87+365 -> 46752 | J87: =+I87+365 -> 47117 | K87: =+J87+365 -> 47482 | L87: =+K87+365 -> 47847 | ... O87: =+N87+365 -> 48942
A88: Net Cash Flow | B88: =SUM(D88:O88) -> -24684638 | D88: =+D54+D85 -> -10157500 | E88: =+E54+E85 -> -29769262 | F88: =+F54+F85 -> -41870249 | G88: =+G54+G85 -> 2990636.6 | H88: =+H54+H85 -> 4671737.2 | I88: =+I54+I85 -> 6449818.9 | J88: =+J54+J85 -> 6644604.4 | K88: =+K54+K85 -> 6845233.5 | ... O88: =+O54+O85 -> 7709771.2
A89: Exit Cap Rate WACC | D89: 0.0525 | E89: 0.0525 | F89: 0.0525 | G89: 0.0525 | H89: 0.0525 | I89: 0.0525 | J89: 0.0525 | K89: 0.0525 | L89: 0.0525 | M89: 0.0525 | N89: 0.0525 | O89: 0.0525
A90: Gross Proceeds From Sale | B90: =SUM(D90:O90) -> 1.4685278e+08 | D90: 0 | E90: 0 | F90: 0 | G90: 0 | H90: 0 | I90: 0 | J90: 0 | K90: 0 | L90: 0 | M90: 0 | N90: 0 | O90: ='Project 1'!B23 -> 1.4685278e+08
A91: Sales Cost | B91: =SUM(D91:O91) -> 2937055.7 | D91: 0 | E91: 0 | F91: 0 | G91: 0 | H91: 0 | I91: 0 | J91: 0 | K91: 0 | L91: 0 | M91: 0 | N91: 0 | O91: =+O90*0.02 -> 2937055.7
A92: Net Proceeds | B92: =SUM(B88:B91) -> 1.251052e+08 | D92: =+D88+D90+D91 -> -10157500 | E92: =+E88+E90+E91 -> -29769262 | F92: =+F88+F90+F91 -> -41870249 | G92: =+G88+G90+G91 -> 2990636.6 | H92: =+H88+H90+H91 -> 4671737.2 | I92: =+I88+I90+I91 -> 6449818.9 | J92: =+J88+J90+J91 -> 6644604.4 | K92: =+K88+K90+K91 -> 6845233.5 | ... O92: =+O88+O90+O91 -> 1.5749961e+08
A94: Discounted Cash Flow | B94: =SUM(D94:O94) -> 48261715 | D94: =D92/(1+D89)^D86 -> -10157500 | E94: =E92/(1+E89)^E86 -> -28284335 | F94: =F92/(1+F89)^F86 -> -37797349 | G94: =G92/(1+G89)^G86 -> 2565058.8 | H94: =H92/(1+H89)^H86 -> 3807062.3 | I94: =I92/(1+I89)^I86 -> 4993867.3 | J94: =J92/(1+J89)^J86 -> 4888059.7 | K94: =K92/(1+K89)^K86 -> 4784466.7 | ... O94: =O92/(1+O89)^O86 -> 89709066
A95: NPV | B95: =NPV(D89,E92:O92)+D92 -> 48261715
A97: Project Level Returns
A98: NPV | B98: =NPV(D89,E92:O92)+D92 -> 48261715
A99: IRR | B99: =IRR(D92:O92) -> 0.11654589
A100: Equity Multiple (EM) | B100: =+B98/'Project 1'!F20 -> 1.5910497
A101: Whole Dollar Profit (WDP) | B101: =+B92 -> 1.251052e+08
A102: % WDP From Development | B102: =+B54/B101 -> 0.46603488
A104: Financing Cash Flow | B104: Total
A105: Year | D105: 0 | E105: 1 | F105: 2 | G105: 3 | H105: 4 | I105: 5 | J105: 6 | K105: 7 | L105: 8 | M105: 9 | N105: 10 | O105: 11
A106: Month | D106: 0 | E106: 12 | F106: 24 | G106: 36 | H106: 48 | I106: 60 | J106: 72 | K106: 84 | L106: 96 | M106: 108 | N106: 120 | O106: 132
A107: Ending Date | D107: 44927 | E107: =+D107+365 -> 45292 | F107: =+E107+365 -> 45657 | G107: =+F107+365 -> 46022 | H107: =+G107+365 -> 46387 | I107: =+H107+365 -> 46752 | J107: =+I107+365 -> 47117 | K107: =+J107+365 -> 47482 | L107: =+K107+365 -> 47847 | ... O107: =+N107+365 -> 48942
A108: Construction Loan | D108: ='Project 1'!B30 -> 57637500
A109: Interest Payments
A110: Construction Loan Interest payments | D110: 0 | E110: =C126 -> -3025968.8 | F110: =C127 -> -2788183.5 | G110: =C128 -> -2537914.6 | H110: -2274506.5 | I110: -1997269.5 | J110: -1705477.6 | K110: -1398366.6 | L110: -1075132.3 | M110: -734928.12 | N110: -376863.26 | O110: 0
A111: Total Interest Payments | B111: =SUM(D111:N111) -> -17914611 | D111: 0 | E111: =E110 -> -3025968.8 | F111: =F110 -> -2788183.5 | G111: =G110 -> -2537914.6 | H111: =H110 -> -2274506.5 | I111: =I110 -> -1997269.5 | J111: =J110 -> -1705477.6 | K111: =K110 -> -1398366.6 | L111: =L110 -> -1075132.3 | ... O111: =O110 -> 0
...

Sheet Project 2
A1: PROJECT 2 ASSUMPTIONS
H2: `
A3: Site Assumptions | D3: Unit Mix
A4: Project Name | B4: Apartments | D4: Unit Type | E4: # Units | F4: % Total | G4: SF/ Per Unit | H4: SF (square footage) | I4: Rent/Month | J4: Rent/SF | K4: Annual Rent
A5: County | B5: Queens | D5: Studio | E5: 100 | F5: =+E5/$E$12 -> 0.22988506 | G5: 500 | H5: =+G5*E5 -> 50000 | I5: 1750 | J5: =+(I5*12)/G5 -> 42 | K5: =+I5*12*E5 -> 2100000
A6: State | B6: New York | D6: 1 Bed / 1 Bath (A1) | E6: 150 | F6: =+E6/$E$12 -> 0.34482759 | G6: 700 | H6: =+G6*E6 -> 105000 | I6: 2100 | J6: =+(I6*12)/G6 -> 36 | K6: =+I6*12*E6 -> 3780000
A7: Building Assumptions | D7: 1 Bed / 1 Bath (A2) | E7: 50 | F7: =+E7/$E$12 -> 0.11494253 | G7: 800 | H7: =+G7*E7 -> 40000 | I7: 2200 | J7: =+(I7*12)/G7 -> 33 | K7: =+I7*12*E7 -> 1320000
A8: Gross Buildable SF (GSF) | B8: 0 | D8: 2 Bed / 2 Bath (B1) | E8: 125 | F8: =+E8/$E$12 -> 0.28735632 | G8: 1200 | H8: =+G8*E8 -> 150000 | I8: 2400 | J8: =+(I8*12)/G8 -> 24 | K8: =+I8*12*E8 -> 3600000
A9: Residential Net Rentable SF | B9: =H12 -> 452500 | D9: 2 Bed / 2 Bath (B2) Den | E9: 75 | F9: =+E9/$E$12 -> 0.17241379 | G9: 1400 | H9: =+G9*E9 -> 105000 | I9: 2500 | J9: =+(I9*12)/G9 -> 21.428571 | K9: =+I9*12*E9 -> 2250000
A10: Commercial Net Rentable SF | B10: 0 | D10: 3 Bed / 2 Bath (B2) | E10: 35 | F10: =+E10/$E$12 -> 0.08045977 | G10: 1500 | H10: =+G10*E10 -> 52500 | I10: 2800 | J10: =+(I10*12)/G10 -> 22.4 | K10: =+I10*12*E10 -> 1176000
A11: Total Net Rentable SF (NSF) | B11: =B9+B10 -> 452500 | D11: 4 Bed / 2 Bath (B2) | E11: 25 | F11: =+E11/$E$12 -> 0.057471264 | G11: 1750 | H11: =+G11*E11 -> 43750 | I11: 3000 | J11: =+(I11*12)/G11 -> 20.571429 | K11: =+I11*12*E11 -> 900000
A12: Efficiency Factor | B12: 0 | D12: Total | E12: =SUM(E6:E10) -> 435 | F12: =SUM(F6:F10) -> 1 | G12: =SUM(G6:G10) -> 5600 | H12: =SUM(H6:H10) -> 452500 | I12: =SUM(I6:I10) -> 12000 | J12: =SUM(J6:J10) -> 136.82857 | K12: =SUM(K6:K10) -> 12126000
A13: Residential Units | B13: =E12 -> 435 | D13: Average | E13: =+AVERAGE(E5:E11) -> 80 | F13: =+AVERAGE(F5:F11) -> 0.18390805 | G13: =+AVERAGE(G5:G11) -> 1121.4286 | H13: =+AVERAGE(H5:H11) -> 78035.714 | I13: =+AVERAGE(I5:I11) -> 2392.8571 | J13: =+AVERAGE(J5:J11) -> 28.485714 | K13: =+AVERAGE(K5:K11) -> 2160857.1
A14: Avg. Unit Size | B14: =G13 -> 1121.4286
A15: Parking Spaces | B15: 700 | D15: Market Rent Growth | F15: 0.0325
A16: Storage Units | B16: 200
A18: Exit Assumptions | D18: Sources And Uses | E18: % Total | F18: $ Amount | G18: $/Unit | H18: $/NSF
A19: Hold Period (Years) | B19: 11 | D19: Sources
A20: Sale Date | B20: 44927 | D20: Equity | E20: 0.34535046 | F20: 30333255 | G20: =+F20/$E$12 -> 69731.62 | H20: =+G20/$G$12 -> 12.452075
A21: Forward NOI | B21: ='Project 2 Financial Analysis'!O61 -> 18338998 | D21: LP Equity | E21: 0.31081541 | F21: 28000000 | G21: =+F21/$E$12 -> 64367.816 | H21: =+G21/$G$12 -> 11.494253
A22: Exit Cap | B22: 0.0525 | D22: GP Equity | E22: 0.034535046 | F22: 4000000 | G22: =+F22/$E$12 -> 9195.4023 | H22: =+G22/$G$12 -> 1.6420361
A23: Gross Proceeds | B23: =+B21/B22 -> 3.4931425e+08 | D23: Debt | E23: 0.65464954 | F23: =+F30-F20 -> 85949710 | G23: =+F23/$E$12 -> 197585.54 | H23: =+G23/$G$12 -> 35.283132
A24: Per Unit | B24: =+B23/E12 -> 803021.25 | D24: Total Sources | E24: 1 | F24: =SUM(F21:F23) -> 1.1794971e+08 | G24: =SUM(G21:G23) -> 271148.76 | H24: =SUM(H21:H23) -> 48.419421
A25: Per NSF | B25: =+B23/H12 -> 771.96518 | D25: Uses
A26: Cost Of Sale | B26: 0.02 | D26: Acquisitions Costs | E26: 0.1140798 | F26: ='Project 2 Financial Analysis'!B71*-1 -> 16103175 | G26: 30000 | H26: 31.612523
D27: Hard Costs | E27: 0.64456738 | F27: =+'Project 2 Financial Analysis'!B78*-1 -> 73032642 | G27: 169504.35 | H27: 178.61533
D28: Soft Costs | E28: 0.18462341 | F28: =+'Project 2 Financial Analysis'!B90*-1 -> 20918736 | G28: 48551.122 | H28: 51.160781
A29: Construction Financing | D29: Financing Costs | E29: 0.056729413 | F29: =+B57 -> 6228411.2 | G29: 14918.35 | H29: 15.720223
A30: Loan Amount | B30: =F23 -> 85949710 | D30: Total Uses | E30: 1 | F30: =SUM(F26:F29) -> 1.1628296e+08 | G30: =SUM(G26:G29) -> 262973.82 | H30: =SUM(H26:H29) -> 277.10886
A31: Per Unit | B31: =+B30/E12 -> 197585.54
A32: Per NSF | B32: =+B31/G12 -> 35.283132
A33: Going-In Metrics (Untrended Pro Forma)
A34: Pro Forma NCF Year 6 | B34: ='Project 2 Financial Analysis'!J101 -> 11462680
A35: Valuation Cap Rate | B35: 0.0625
A36: Valuation | B36: ='Project 2 Financial Analysis'!O97 -> 3.4931425e+08
A37: LTV % | B37: =B30/B36 -> 0.24605269
A38: Debt Yield | B38: =B34/B30 -> 0.13336497
A39: Takeout Metrics
A40: Year 6 NOI | B40: ='Project 2 Financial Analysis'!J58 -> 15631843
A41: Valuation Cap Rate | B41: 0.0625
A42: Valuation | B42: =+B36 -> 3.4931425e+08
A43: Debt Yield | B43: =B40/B30 -> 0.18187197
A44: Financing Costs
A45: Appraisal | B45: 18750
A46: Lender Third Party Reports | B46: 37500
A47: Lender Legal Fees | B47: 125000
A48: Lender Inspection | B48: 38812.5
A49: Mortgage Recording Tax | B49: 239343.75
A50: Doc Stamps and Intangible Tax | B50: 31250
A51: Lender Fee | B51: 718750
A52: Mortgage Broker Fee | B52: 646875
A53: Equity Broker Fee | B53: 307124.21
A54: Title Insurance | B54: 107813.75
A55: Monthly Title Updates | B55: 14937.5
A56: Interest Reserve | B56: 3942254.5
A57: Total Financing Costs | B57: =SUM(B45:B56) -> 6228411.2

Sheet Project 2 Unit Mix Pivot
A3: Row Labels | B3: Sum of Annual Rent | C3: Sum of Rent/SF
A4: 1 Bed / 1 Bath (A1) | B4: 3780000 | C4: 36
A5: 2 Bed / 2 Bath (B1) | B5: 3600000 | C5: 24
A6: 2 Bed / 2 Bath (B2) Den | B6: 2250000 | C6: 21.428571
A7: Studio | B7: 2100000 | C7: 42
A8: 1 Bed / 1 Bath (A2) | B8: 1320000 | C8: 33
A9: 3 Bed / 2 Bath (B2) | B9: 1176000 | C9: 22.4
A10: 4 Bed / 2 Bath (B2) | B10: 900000 | C10: 20.571429
A11: Grand Total | B11: 15126000 | C11: 199.4

Sheet Project 2 Financial Analysis
A1: PROJECT 2 FINANCIAL ANALYSIS
A3: Year | D3: 0 | E3: 1 | F3: 2 | G3: 3 | H3: 4 | I3: 5 | J3: 6 | K3: 7 | L3: 8 | M3: 9 | N3: 10 | O3: 11
A4: Month | D4: 0 | E4: 12 | F4: 24 | G4: 36 | H4: 48 | I4: 60 | J4: 72 | K4: 84 | L4: 96 | M4: 108 | N4: 120 | O4: 132
A5: Ending Date | D5: 44927 | E5: =+D5+365 -> 45292 | F5: =+E5+365 -> 45657 | G5: =+F5+365 -> 46022 | H5: =+G5+365 -> 46387 | I5: =+H5+365 -> 46752 | J5: =+I5+365 -> 47117 | K5: =+J5+365 -> 47482 | L5: =+K5+365 -> 47847 | ... O5: =+N5+365 -> 48942
A7: Property Performance
A8: Residential Units
A9: Units Complete | D9: 0 | E9: 0 | F9: =SUM(F12:F18) -> 130 | G9: =SUM(G12:G18) -> 255 | H9: =SUM(H12:H18) -> 350 | I9: =SUM(I12:I18) -> 455 | J9: =SUM(J12:J18) -> 560 | K9: =SUM(K12:K18) -> 560 | L9: =SUM(L12:L18) -> 560 | M9: =SUM(M12:M18) -> 560 | ... O9: =SUM(O12:O18) -> 560
A10: Completed % | D10: 0 | E10: 0 | F10: =+F9/560 -> 0.23214286 | G10: =+G9/560 -> 0.45535714 | H10: =+H9/560 -> 0.625 | I10: =+I9/560 -> 0.8125 | J10: =+J9/560 -> 1 | K10: =+K9/560 -> 1 | L10: =+L9/560 -> 1 | M10: =+M9/560 -> 1 | ... O10: =+O9/560 -> 1
A11: Unit Type | B11: # Units | C11: SF/Unit
A12: Studio | B12: 100 | C12: 500 | D12: 0 | E12: 0 | F12: 25 | G12: 50 | H12: 75 | I12: 100 | J12: 100 | K12: 100 | L12: 100 | M12: 100 | N12: 100 | O12: 100
A13: 1 Bed / 1 Bath (A1) | B13: 150 | C13: 700 | D13: 0 | E13: 0 | F13: 25 | G13: 50 | H13: 75 | I13: 100 | J13: 150 | K13: 150 | L13: 150 | M13: 150 | N13: 150 | O13: 150
A14: 1 Bed / 1 Bath (A2) | B14: 50 | C14: 800 | D14: 0 | E14: 0 | F14: 25 | G14: 50 | H14: 50 | I14: 50 | J14: 50 | K14: 50 | L14: 50 | M14: 50 | N14: 50 | O14: 50
A15: 2 Bed / 2 Bath (B1) | B15: 125 | C15: 1200 | D15: 0 | E15: 0 | F15: 25 | G15: 50 | H15: 75 | I15: 100 | J15: 125 | K15: 125 | L15: 125 | M15: 125 | N15: 125 | O15: 125
A16: 2 Bed / 2 Bath (B2) Den | B16: 75 | C16: 1400 | D16: 0 | E16: 0 | F16: 20 | G16: 25 | H16: 35 | I16: 50 | J16: 75 | K16: 75 | L16: 75 | M16: 75 | N16: 75 | O16: 75
A17: 3 Bed / 2 Bath (B2) | B17: 35 | C17: 1500 | D17: 0 | E17: 0 | F17: 5 | G17: 15 | H17: 20 | I17: 30 | J17: 35 | K17: 35 | L17: 35 | M17: 35 | N17: 35 | O17: 35
A18: 4 Bed / 2 Bath (B2) | B18: 25 | C18: 1750 | D18: 0 | E18: 0 | F18: 5 | G18: 15 | H18: 20 | I18: 25 | J18: 25 | K18: 25 | L18: 25 | M18: 25 | N18: 25 | O18: 25
A21: Cumulative Units Leased | B21: Rent/Month | C21: Rent/SF | D21: =SUM(D12:D18) -> 0 | E21: =SUM(E12:E18) -> 0 | F21: =SUM(F12:F18) -> 130 | G21: =SUM(G12:G18) -> 255 | H21: =SUM(H12:H18) -> 350 | I21: =SUM(I12:I18) -> 455 | J21: =SUM(J12:J18) -> 560 | K21: =SUM(K12:K18) -> 560 | ... O21: =SUM(O12:O18) -> 560
A22: Studio | B22: ='Project 2'!I5 -> 1750 | C22: ='Project 2'!J5 -> 42 | D22: =D12*$B$22*12 -> 0 | E22: =E12*$B$22*12 -> 0 | F22: =F12*$B$22*12*(1+F$30)^F$33 -> 559679.53 | G22: =G12*$B$22*12*(1+G$30)^G$33 -> 1155738.2 | H22: =H12*$B$22*12*(1+H$30)^H$33 -> 1789949.6 | I22: =I12*$B$22*12*(1+I$30)^I$33 -> 2464163.9 | J22: =J12*$B$22*12*(1+J$30)^J$33 -> 2544249.3 | K22: =K12*$B$22*12*(1+K$30)^K$33 -> 2626937.4 | L22: =L12*$B$22*12*(1+L$30)^L$33 -> 2712312.8 | M22: =M12*$B$22*12*(1+M$30)^M$33 -> 2800463 | ... O22: =O12*$B$22*12*(1+O$30)^O$33 -> 2985451.1
A23: 1 Bed / 1 Bath (A1) | B23: ='Project 2'!I6 -> 2100 | C23: ='Project 2'!J6 -> 36 | D23: =D13*$B$23*12 -> 0 | E23: =E13*$B$23*12 -> 0 | F23: =F13*$B$23*12*(1+F$30)^F$33 -> 671615.44 | G23: =G13*$B$23*12*(1+G$30)^G$33 -> 1386885.9 | H23: =H13*$B$23*12*(1+H$30)^H$33 -> 2147939.5 | I23: =I13*$B$23*12*(1+I$30)^I$33 -> 2956996.7 | J23: =J13*$B$23*12*(1+J$30)^J$33 -> 4579648.7 | K23: =K13*$B$23*12*(1+K$30)^K$33 -> 4728487.2 | L23: =L13*$B$23*12*(1+L$30)^L$33 -> 4882163.1 | M23: =M13*$B$23*12*(1+M$30)^M$33 -> 5040833.4 | ... O23: =O13*$B$23*12*(1+O$30)^O$33 -> 5373811.9
A24: 1 Bed / 1 Bath (A2) | B24: ='Project 2'!I7 -> 2200 | C24: ='Project 2'!J7 -> 33 | D24: =D14*$B$24*12 -> 0 | E24: =E14*$B$24*12 -> 0 | F24: =F14*$B$24*12*(1+F$30)^F$33 -> 703597.12 | G24: =G14*$B$24*12*(1+G$30)^G$33 -> 1452928.1 | H24: =H14*$B$24*12*(1+H$30)^H$33 -> 1500148.2 | I24: =I14*$B$24*12*(1+I$30)^I$33 -> 1548903 | J24: =J14*$B$24*12*(1+J$30)^J$33 -> 1599242.4 | K24: =K14*$B$24*12*(1+K$30)^K$33 -> 1651217.8 | L24: =L14*$B$24*12*(1+L$30)^L$33 -> 1704882.3 | M24: =M14*$B$24*12*(1+M$30)^M$33 -> 1760291 | ... O24: =O14*$B$24*12*(1+O$30)^O$33 -> 1876569.2
A25: 2 Bed / 2 Bath (B1) | B25: ='Project 2'!I8 -> 2400 | C25: ='Project 2'!J8 -> 24 | D25: =D15*$B$25*12 -> 0 | E25: =E15*$B$25*12 -> 0 | F25: =F15*$B$25*12*(1+F$30)^F$33 -> 767560.5 | G25: =G15*$B$25*12*(1+G$30)^G$33 -> 1585012.4 | H25: =H15*$B$25*12*(1+H$30)^H$33 -> 2454788 | I25: =I15*$B$25*12*(1+I$30)^I$33 -> 3379424.8 | J25: =J15*$B$25*12*(1+J$30)^J$33 -> 4361570.2 | K25: =K15*$B$25*12*(1+K$30)^K$33 -> 4503321.2 | L25: =L15*$B$25*12*(1+L$30)^L$33 -> 4649679.1 | M25: =M15*$B$25*12*(1+M$30)^M$33 -> 4800793.7 | ... O25: =O15*$B$25*12*(1+O$30)^O$33 -> 5117916.1
A26: 2 Bed / 2 Bath (B2) Den | B26: ='Project 2'!I9 -> 2500 | C26: ='Project 2'!J9 -> 21.428571 | D26: =D16*$B$26*12 -> 0 | E26: =E16*$B$26*12 -> 0 | F26: =F16*$B$26*12*(1+F$30)^F$33 -> 639633.75 | G26: =G16*$B$26*12*(1+G$30)^G$33 -> 825527.31 | H26: =H16*$B$26*12*(1+H$30)^H$33 -> 1193299.7 | I26: =I16*$B$26*12*(1+I$30)^I$33 -> 1760117.1 | J26: =J16*$B$26*12*(1+J$30)^J$33 -> 2725981.3 | K26: =K16*$B$26*12*(1+K$30)^K$33 -> 2814575.7 | L26: =L16*$B$26*12*(1+L$30)^L$33 -> 2906049.5 | M26: =M16*$B$26*12*(1+M$30)^M$33 -> 3000496.1 | ... O26: =O16*$B$26*12*(1+O$30)^O$33 -> 3198697.6
A27: 3 Bed / 2 Bath (B2) | B27: ='Project 2'!I10 -> 2800 | C27: ='Project 2'!J10 -> 22.4 | D27: =D17*$B$27*12 -> 0 | E27: =E17*$B$27*12 -> 0 | F27: =F17*$B$27*12*(1+F$30)^F$33 -> 179097.45 | G27: =G17*$B$27*12*(1+G$30)^G$33 -> 554754.35 | H27: =H17*$B$27*12*(1+H$30)^H$33 -> 763711.82 | I27: =I17*$B$27*12*(1+I$30)^I$33 -> 1182798.7 | J27: =J17*$B$27*12*(1+J$30)^J$33 -> 1424779.6 | K27: =K17*$B$27*12*(1+K$30)^K$33 -> 1471084.9 | L27: =L17*$B$27*12*(1+L$30)^L$33 -> 1518895.2 | M27: =M17*$B$27*12*(1+M$30)^M$33 -> 1568259.3 | ... O27: =O17*$B$27*12*(1+O$30)^O$33 -> 1671852.6
A28: 4 Bed / 2 Bath (B2) | B28: ='Project 2'!I11 -> 3000 | C28: ='Project 2'!J11 -> 20.571429 | D28: =D18*$B$28*12 -> 0 | E28: =E18*$B$28*12 -> 0 | F28: =F18*$B$28*12*(1+F$30)^F$33 -> 191890.12 | G28: =G18*$B$28*12*(1+G$30)^G$33 -> 594379.66 | H28: =H18*$B$28*12*(1+H$30)^H$33 -> 818262.67 | I28: =I18*$B$28*12*(1+I$30)^I$33 -> 1056070.3 | J28: =J18*$B$28*12*(1+J$30)^J$33 -> 1090392.5 | K28: =K18*$B$28*12*(1+K$30)^K$33 -> 1125830.3 | L28: =L18*$B$28*12*(1+L$30)^L$33 -> 1162419.8 | M28: =M18*$B$28*12*(1+M$30)^M$33 -> 1200198.4 | ... O28: =O18*$B$28*12*(1+O$30)^O$33 -> 1279479
A29: Avg Market Rent ($/Unit/Mo.) | D29: 0 | E29: 0 | F29: =SUM(F22:F28)/F21/12 -> 2380.1756 | G29: =SUM(G22:G28)/G21/12 -> 2469.0281 | H29: =SUM(H22:H28)/H21/12 -> 2540.0237 | I29: =SUM(I22:I28)/I21/12 -> 2627.9257 | J29: =SUM(J22:J28)/J21/12 -> 2727.0631 | K29: =SUM(K22:K28)/K21/12 -> 2815.6926 | L29: =SUM(L22:L28)/L21/12 -> 2907.2026 | M29: =SUM(M22:M28)/M21/12 -> 3001.6867 | ... O29: =SUM(O22:O28)/O21/12 -> 3199.9669
A30: Market Rent Growth | E30: ='Project 2'!$F$15 -> 0.0325 | F30: ='Project 2'!$F$15 -> 0.0325 | G30: ='Project 2'!$F$15 -> 0.0325 | H30: ='Project 2'!$F$15 -> 0.0325 | I30: ='Project 2'!$F$15 -> 0.0325 | J30: ='Project 2'!$F$15 -> 0.0325 | K30: ='Project 2'!$F$15 -> 0.0325 | L30: ='Project 2'!$F$15 -> 0.0325 | ... O30: ='Project 2'!$F$15 -> 0.0325
A32: Operating Cash Flow | B32: Total W/A
A33: Year | D33: 0 | E33: 1 | F33: 2 | G33: 3 | H33: 4 | I33: 5 | J33: 6 | K33: 7 | L33: 8 | M33: 9 | N33: 10 | O33: 11
A34: Month | D34: 0 | E34: 12 | F34: 24 | G34: 36 | H34: 48 | I34: 60 | J34: 72 | K34: 84 | L34: 96 | M34: 108 | N34: 120 | O34: 132
A35: Ending Date | D35: 44927 | E35: =+D35+365 -> 45292 | F35: =+E35+365 -> 45657 | G35: =+F35+365 -> 46022 | H35: =+G35+365 -> 46387 | I35: =+H35+365 -> 46752 | J35: =+I35+365 -> 47117 | K35: =+J35+365 -> 47482 | L35: =+K35+365 -> 47847 | ... O35: =+N35+365 -> 48942
A36: Revenue
A37: Apartment Rental Revenue | B37: =SUM(D37:O37) -> 1.5557061e+08 | D37: 0 | E37: 0 | F37: =SUM(F22:F28) -> 3713073.9 | G37: =SUM(G22:G28) -> 7555225.9 | H37: =SUM(H22:H28) -> 10668100 | I37: =SUM(I22:I28) -> 14348475 | J37: =SUM(J22:J28) -> 18325864 | K37: =SUM(K22:K28) -> 18921455 | L37: =SUM(L22:L28) -> 19536402 | M37: =SUM(M22:M28) -> 20171335 | ... O37: =SUM(O22:O28) -> 21503778
A38: Parking Income 4% of Rent | B38: =SUM(D38:O38) -> 6222824.4 | D38: 0 | E38: 0 | F38: =F37*0.04 -> 148522.96 | G38: =G37*0.04 -> 302209.04 | H38: =H37*0.04 -> 426723.98 | I38: =I37*0.04 -> 573938.98 | J38: =J37*0.04 -> 733034.56 | K38: =K37*0.04 -> 756858.18 | L38: =L37*0.04 -> 781456.07 | M38: =M37*0.04 -> 806853.39 | ... O38: =O37*0.04 -> 860151.1
A39: Tenant Storage Income 1.5% of Rent | B39: =SUM(D39:O39) -> 2333559.1 | D39: 0 | E39: 0 | F39: =F37*0.015 -> 55696.109 | G39: =G37*0.015 -> 113328.39 | H39: =H37*0.015 -> 160021.49 | I39: =I37*0.015 -> 215227.12 | J39: =J37*0.015 -> 274887.96 | K39: =K37*0.015 -> 283821.82 | L39: =L37*0.015 -> 293046.03 | M39: =M37*0.015 -> 302570.02 | ... O39: =O37*0.015 -> 322556.66
A40: Pet Fee Income 1% of Rent | B40: =SUM(D40:O40) -> 1555706.1 | D40: 0 | E40: 0 | F40: =F37*0.01 -> 37130.739 | G40: =G37*0.01 -> 75552.259 | H40: =H37*0.01 -> 106681 | I40: =I37*0.01 -> 143484.75 | J40: =J37*0.01 -> 183258.64 | K40: =K37*0.01 -> 189214.55 | L40: =L37*0.01 -> 195364.02 | M40: =M37*0.01 -> 201713.35 | ... O40: =O37*0.01 -> 215037.78
A41: Potential Gross Revenue | B41: =SUM(D41:O41) -> 1.656827e+08 | D41: 0 | E41: 0 | F41: =SUM(F37:F40) -> 3954423.7 | G41: =SUM(G37:G40) -> 8046315.6 | H41: =SUM(H37:H40) -> 11361526 | I41: =SUM(I37:I40) -> 15281125 | J41: =SUM(J37:J40) -> 19517045 | K41: =SUM(K37:K40) -> 20151349 | L41: =SUM(L37:L40) -> 20806268 | M41: =SUM(M37:M40) -> 21482472 | ... O41: =SUM(O37:O40) -> 22901523
A42: Vacancy Loss - Residential -3% | B42: =SUM(D42:O42) -> 4970481 | D42: 0 | E42: 0 | F42: =F41*0.03 -> 118632.71 | G42: =G41*0.03 -> 241389.47 | H42: =H41*0.03 -> 340845.78 | I42: =I41*0.03 -> 458433.76 | J42: =J41*0.03 -> 585511.35 | K42: =K41*0.03 -> 604540.47 | L42: =L41*0.03 -> 624188.04 | M42: =M41*0.03 -> 644474.15 | ... O42: =O41*0.03 -> 687045.69
A43: Vacancy Loss - Parking -1% | B43: =SUM(D43:O43) -> 62228.244 | D43: 0 | E43: 0 | F43: =F38*0.01 -> 1485.2296 | G43: =G38*0.01 -> 3022.0904 | H43: =H38*0.01 -> 4267.2398 | I43: =I38*0.01 -> 5739.3898 | J43: =J38*0.01 -> 7330.3456 | K43: =K38*0.01 -> 7568.5818 | L43: =L38*0.01 -> 7814.5607 | M43: =M38*0.01 -> 8068.5339 | ... O43: =O38*0.01 -> 8601.511
A44: Vacancy Loss - Storage -2% | B44: =SUM(D44:O44) -> 46671.183 | D44: 0 | E44: 0 | F44: =F39*0.02 -> 1113.9222 | G44: =G39*0.02 -> 2266.5678 | H44: =H39*0.02 -> 3200.4299 | I44: =I39*0.02 -> 4304.5424 | J44: =J39*0.02 -> 5497.7592 | K44: =K39*0.02 -> 5676.4364 | L44: =L39*0.02 -> 5860.9205 | M44: =M39*0.02 -> 6051.4005 | ... O44: =O39*0.02 -> 6451.1333
A45: Vacancy Loss - Pet -2% | B45: =SUM(D45:O45) -> 31114.122 | D45: 0 | E45: 0 | F45: =F40*0.02 -> 742.61478 | G45: =G40*0.02 -> 1511.0452 | H45: =H40*0.02 -> 2133.6199 | I45: =I40*0.02 -> 2869.6949 | J45: =J40*0.02 -> 3665.1728 | K45: =K40*0.02 -> 3784.2909 | L45: =L40*0.02 -> 3907.2804 | M45: =M40*0.02 -> 4034.267 | ... O45: =O40*0.02 -> 4300.7555
A46: Effective Gross Revenue | B46: =SUM(D46:O46) -> 1.6057221e+08 | D46: 0 | E46: 0 | F46: =F41-F42-F43-F44-F45 -> 3832449.2 | G46: =G41-G42-G43-G44-G45 -> 7798126.4 | H46: =H41-H42-H43-H44-H45 -> 11011079 | I46: =I41-I42-I43-I44-I45 -> 14809778 | J46: =J41-J42-J43-J44-J45 -> 18915040 | K46: =K41-K42-K43-K44-K45 -> 19529779 | L46: =L41-L42-L43-L44-L45 -> 20164497 | M46: =M41-M42-M43-M44-M45 -> 20819843 | ... O46: =O41-O42-O43-O44-O45 -> 22195124
A48: Operating Expenses
A49: Real Estate Taxes | B49: -9161691.7 | D49: 0 | E49: 0 | F49: -438554.69 | G49: -1084107.2 | H49: -1116630.4 | I49: -1150129.3 | J49: -1184633.2 | K49: -1220172.2 | L49: -1256777.4 | M49: -1294480.7 | N49: -1333315.1 | O49: -1373314.6
A50: Payroll & Benefits | B50: -5409724 | D50: 0 | E50: 0 | F50: -258954.34 | G50: -640135.12 | H50: -659339.18 | I50: -679119.35 | J50: -699492.93 | K50: -720477.72 | L50: -742092.05 | M50: -764354.82 | N50: -787285.46 | O50: -810904.02
A51: Insurance | B51: -916169.17 | D51: 0 | E51: 0 | F51: -43855.469 | G51: -108410.72 | H51: -111663.04 | I51: -115012.93 | J51: -118463.32 | K51: -122017.22 | L51: -125677.74 | M51: -129448.07 | N51: -133331.51 | O51: -137331.46
A52: Utilities | B52: -2477321.4 | D52: 0 | E52: 0 | F52: -118585.19 | G52: -293142.58 | H52: -301936.86 | I52: -310994.97 | J52: -320324.82 | K52: -329934.56 | L52: -339832.6 | M52: -350027.58 | N52: -360528.4 | O52: -371344.25
A53: Repairs & Maintenance,Con Serv, TO | B53: -3749726.3 | D53: 0 | E53: 0 | F53: -179493.06 | G53: -443706.84 | H53: -457018.04 | I53: -470728.58 | J53: -484850.44 | K53: -499395.95 | L53: -514377.83 | M53: -529809.17 | N53: -545703.44 | O53: -562074.55
A54: Administrative & Marketing | B54: -1960602 | D54: 0 | E54: 0 | F54: -93850.703 | G54: -231998.94 | H54: -238958.91 | I54: -246127.67 | J54: -253511.5 | K54: -261116.85 | L54: -268950.35 | M54: -277018.86 | N54: -285329.43 | O54: -293889.31
A55: Management Fee | B55: -1716293.1 | D55: 0 | E55: 0 | F55: -82156.046 | G55: -203089.75 | H55: -209182.44 | I55: -215457.91 | J55: -221921.65 | K55: -228579.3 | L55: -235436.68 | M55: -242499.78 | N55: -249774.77 | O55: -257268.02
A56: Total Operating Expenses | B56: -25391528 | D56: 0 | E56: 0 | F56: =SUM(F49:F55) -> -1215449.5 | G56: =SUM(G49:G55) -> -3004591.1 | H56: =SUM(H49:H55) -> -3094728.9 | I56: =SUM(I49:I55) -> -3187570.7 | J56: =SUM(J49:J55) -> -3283197.9 | K56: =SUM(K49:K55) -> -3381693.8 | L56: =SUM(L49:L55) -> -3483144.6 | M56: =SUM(M49:M55) -> -3587638.9 | ... O56: =SUM(O49:O55) -> -3806126.2
A58: Net Operating Income EBIT | D58: 0 | E58: 0 | F58: =F46+F56 -> 2616999.8 | G58: =G46+G56 -> 4793535.3 | H58: =H46+H56 -> 7916350.1 | I58: =I46+I56 -> 11622207 | J58: =J46+J56 -> 15631843 | K58: =K46+K56 -> 16148085 | L58: =L46+L56 -> 16681353 | M58: =M46+M56 -> 17232204 | ... O58: =O46+O56 -> 18388998
A59: Operating Profit Margin | D59: 0 | E59: 0 | F59: =F58/F46 -> 0.68285308 | G59: =G58/G46 -> 0.61470346 | H59: =H58/H46 -> 0.71894408 | I59: =I58/I46 -> 0.7847658 | J59: =J58/J46 -> 0.82642396 | K59: =K58/K46 -> 0.82684424 | L59: =L58/L46 -> 0.8272635 | M59: =M58/M46 -> 0.82768175 | ... O59: =O58/O46 -> 0.82851521
A60: Reserves | B60: -429980 | D60: 0 | E60: 0 | F60: -50000 | G60: -50000 | H60: -50000 | I60: -50000 | J60: -50000 | K60: -50000 | L60: -50000 | M60: -50000 | N60: -50000 | O60: -50000
A61: Net Cash Flow | B61: =SUM(D61:O61) -> 1.283328e+08 | D61: 0 | E61: 0 | F61: =F58+F60 -> 2566999.8 | G61: =G58+G60 -> 4743535.3 | H61: =H58+H60 -> 7866350.1 | I61: =I58+I60 -> 11572207 | J61: =J58+J60 -> 15581843 | K61: =K58+K60 -> 16098085 | L61: =L58+L60 -> 16631353 | M61: =M58+M60 -> 17182204 | ... O61: =O58+O60 -> 18338998
A62: Year | D62: 0 | E62: 1 | F62: 2 | G62: 3 | H62: 4 | I62: 5 | J62: 6 | K62: 7 | L62: 8 | M62: 9 | N62: 10 | O62: 11
A63: Development Cash Flow | B63: Total | D63: 44927 | E63: 45292 | F63: 45657 | G63: 46022 | H63: 46387 | I63: 46752 | J63: 47117 | K63: 47482 | L63: 47847 | M63: 48212 | N63: 48577 | O63: 48942
A64: Acquisition Costs
A65: Land Costs | B65: =SUM(D65:O65) -> -15925800 | D65: -15925800 | E65: 0 | F65: 0 | G65: 0 | H65: 0 | I65: 0 | J65: 0 | K65: 0 | L65: 0 | M65: 0 | N65: 0 | O65: 0
A66: Legal Fees (Acquisition & LLC) | B66: =SUM(D66:O66) -> -32250 | D66: -32250 | E66: 0 | F66: 0 | G66: 0 | H66: 0 | I66: 0 | J66: 0 | K66: 0 | L66: 0 | M66: 0 | N66: 0 | O66: 0
A67: Buyers Brokers Fee | B67: =SUM(D67:O67) -> -38700 | D67: -38700 | E67: 0 | F67: 0 | G67: 0 | H67: 0 | I67: 0 | J67: 0 | K67: 0 | L67: 0 | M67: 0 | N67: 0 | O67: 0
A68: Acquisition Fee | B68: =SUM(D68:O68) -> -6450 | D68: -6450 | E68: 0 | F68: 0 | G68: 0 | H68: 0 | I68: 0 | J68: 0 | K68: 0 | L68: 0 | M68: 0 | N68: 0 | O68: 0
A69: Other Closing Costs | B69: =SUM(D69:O69) -> -96750 | D69: -96750 | E69: 0 | F69: 0 | G69: 0 | H69: 0 | I69: 0 | J69: 0 | K69: 0 | L69: 0 | M69: 0 | N69: 0 | O69: 0
A70: Other Pre-Development DD Costs | B70: =SUM(D70:O70) -> -3225 | D70: -3225 | E70: 0 | F70: 0 | G70: 0 | H70: 0 | I70: 0 | J70: 0 | K70: 0 | L70: 0 | M70: 0 | N70: 0 | O70: 0
A71: Total Acquisitions Costs | B71: =SUM(D71:O71) -> -16103175 | D71: =SUM(D65:D70) -> -16103175 | E71: 0 | F71: 0 | G71: 0 | H71: 0 | I71: 0 | J71: 0 | K71: 0 | L71: 0 | M71: 0 | N71: 0 | O71: 0
A73: Hard Costs | D73: 0 | E73: 0 | F73: 0 | G73: 0
A74: Building Construction Costs | B74: =SUM(D74:O74) -> -55923138 | D74: 0 | E74: -22858417 | F74: -32753394 | G74: -311327.02 | H74: 0 | I74: 0 | J74: 0 | K74: 0 | L74: 0 | M74: 0 | N74: 0 | O74: 0
A75: Structure Parking Costs | B75: =SUM(D75:O75) -> -10301641 | D75: 0 | E75: -4210765.2 | F75: -6033525.8 | G75: -57349.77 | H75: 0 | I75: 0 | J75: 0 | K75: 0 | L75: 0 | M75: 0 | N75: 0 | O75: 0
A76: Sitework | B76: =SUM(D76:O76) -> -3330118.2 | D76: 0 | E76: -1361176 | F76: -1950403.3 | G76: -18538.941 | H76: 0 | I76: 0 | J76: 0 | K76: 0 | L76: 0 | M76: 0 | N76: 0 | O76: 0
A77: Hard Cost Contingency | B77: =SUM(D77:O77) -> -3477744.9 | D77: 0 | E77: -1421517.9 | F77: -2036866.1 | G77: -19360.787 | H77: 0 | I77: 0 | J77: 0 | K77: 0 | L77: 0 | M77: 0 | N77: 0 | O77: 0
B78: =SUM(D78:O78) -> -73032642 | D78: 0 | E78: =SUM(E73:E77) -> -29851877 | F78: =SUM(F73:F77) -> -42774189 | G78: =SUM(G73:G77) -> -406576.52 | H78: =SUM(H73:H77) -> 0 | I78: =SUM(I73:I77) -> 0 | J78: =SUM(J73:J77) -> 0 | K78: =SUM(K73:K77) -> 0 | L78: =SUM(L73:L77) -> 0 | ... O78: =SUM(O73:O77) -> 0
A80: Soft Costs | D80: 0 | E80: 0 | F80: 0 | G80: 0
A81: Legal Fees | B81: =SUM(D81:O81) -> -322500 | D81: 0 | E81: -131820.92 | F81: -188883.7 | G81: -1795.3743 | H81: 0 | I81: 0 | J81: 0 | K81: 0 | L81: 0 | M81: 0 | N81: 0 | O81: 0
A82: Insurance, Taxes & Mermit Fees | B82: =SUM(D82:O82) -> -12156261 | D82: 0 | E82: -4968835.7 | F82: -7119750.6 | G82: -67674.536 | H82: 0 | I82: 0 | J82: 0 | K82: 0 | L82: 0 | M82: 0 | N82: 0 | O82: 0
A83: Architecture, Engineering & Survey | B83: =SUM(D83:O83) -> -2580000 | D83: 0 | E83: -1054567.4 | F83: -1511069.6 | G83: -14362.994 | H83: 0 | I83: 0 | J83: 0 | K83: 0 | L83: 0 | M83: 0 | N83: 0 | O83: 0
A84: FF&E | B84: =SUM(D84:O84) -> -516000 | D84: 0 | E84: -210913.47 | F84: -302213.93 | G84: -2872.5988 | H84: 0 | I84: 0 | J84: 0 | K84: 0 | L84: 0 | M84: 0 | N84: 0 | O84: 0
A85: Marketing Costs | B85: =SUM(D85:O85) -> -387000 | D85: 0 | E85: -158185.11 | F85: -226660.45 | G85: -2154.4491 | H85: 0 | I85: 0 | J85: 0 | K85: 0 | L85: 0 | M85: 0 | N85: 0 | O85: 0
A86: Misc. Reimbursable | B86: =SUM(D86:O86) -> -177375 | D86: 0 | E86: -72501.507 | F86: -103886.04 | G86: -987.45585 | H86: 0 | I86: 0 | J86: 0 | K86: 0 | L86: 0 | M86: 0 | N86: 0 | O86: 0
A87: Construction Management Fee | B87: =SUM(D87:O87) -> -695548.97 | D87: 0 | E87: -284303.59 | F87: -407373.23 | G87: -3872.1573 | H87: 0 | I87: 0
A88: Developers Overhead | B88: =SUM(D88:O88) -> -3277094.8 | D88: 0 | E88: -1339502.8 | F88: -1919348.2 | G88: -18243.757 | H88: 0 | I88: 0
A89: Soft Costs Contingency | B89: =SUM(D89:O89) -> -806956.79 | D89: 0 | E89: -329841.2 | F89: -472623.22 | G89: -4492.3704 | H89: 0 | I89: 0 | J89: 0 | K89: 0 | L89: 0 | M89: 0 | N89: 0 | O89: 0
A90: Total Soft Costs | B90: =SUM(D90:O90) -> -20918736 | D90: 0 | E90: =SUM(E80:E89) -> -8550471.6 | F90: =SUM(F80:F89) -> -12251809 | G90: =SUM(G80:G89) -> -116455.69 | H90: =SUM(H80:H89) -> 0 | I90: =SUM(I80:I89) -> 0 | J90: =SUM(J80:J89) -> 0 | K90: =SUM(K80:K89) -> 0 | L90: =SUM(L80:L89) -> 0 | ... O90: =SUM(O80:O89) -> 0
A92: Total Development Cash Flow | B92: =+B90+B78+B71 -> -1.1005455e+08 | D92: =+D71+D90 -> -16103175 | E92: =+E90+E78+E71 -> -38402348 | F92: =+F90+F78+F71 -> -55025998 | G92: =+G90+G78+G71 -> -523032.21 | H92: 0 | I92: 0 | J92: 0 | K92: 0 | L92: 0 | M92: 0 | N92: 0 | O92: 0
A93: Year | D93: 0 | E93: 1 | F93: 2 | G93: 3 | H93: 4 | I93: 5 | J93: 6 | K93: 7 | L93: 8 | M93: 9 | N93: 10 | O93: 11
A94: Sale Proceeds | D94: 44927 | E94: =+D94+365 -> 45292 | F94: =+E94+365 -> 45657 | G94: =+F94+365 -> 46022 | H94: =+G94+365 -> 46387 | I94: =+H94+365 -> 46752 | J94: =+I94+365 -> 47117 | K94: =+J94+365 -> 47482 | L94: =+K94+365 -> 47847 | ... O94: =+N94+365 -> 48942
A95: Net Cash Flow | B95: =SUM(D95:O95) -> 18278242 | D95: =D61+D92 -> -16103175 | E95: =E61+E92 -> -38402348 | F95: =F61+F92 -> -52458998 | G95: =G61+G92 -> 4220503.1 | H95: =H61+H92 -> 7866350.1 | I95: =I61+I92 -> 11572207 | J95: =J61+J92 -> 15581843 | K95: =K61+K92 -> 16098085 | ... O95: =O61+O92 -> 18338998
A96: Exit Cap Rate WACC | D96: ='Project 2'!$B$22 -> 0.0525 | E96: ='Project 2'!$B$22 -> 0.0525 | F96: ='Project 2'!$B$22 -> 0.0525 | G96: ='Project 2'!$B$22 -> 0.0525 | H96: ='Project 2'!$B$22 -> 0.0525 | I96: ='Project 2'!$B$22 -> 0.0525 | J96: ='Project 2'!$B$22 -> 0.0525 | K96: ='Project 2'!$B$22 -> 0.0525 | ... O96: ='Project 2'!$B$22 -> 0.0525
A97: Gross Proceeds From Sale | B97: =SUM(D97:O97) -> 3.4931425e+08 | D97: 0 | E97: 0 | F97: 0 | G97: 0 | H97: 0 | I97: 0 | J97: 0 | K97: 0 | L97: 0 | M97: 0 | N97: 0 | O97: ='Project 2'!B23 -> 3.4931425e+08
A98: Sales Cost | B98: =SUM(D98:O98) -> 6986284.9 | D98: 0 | E98: 0 | F98: 0 | G98: 0 | H98: 0 | I98: 0 | J98: 0 | K98: 0 | L98: 0 | M98: 0 | N98: 0 | O98: =O97*0.02 -> 6986284.9
A99: Net Proceeds | B99: =SUM(D99:O99) -> 3.7457877e+08 | D99: =D95+D97+D98 -> -16103175 | E99: =E95+E97+E98 -> -38402348 | F99: =F95+F97+F98 -> -52458998 | G99: =G95+G97+G98 -> 4220503.1 | H99: =H95+H97+H98 -> 7866350.1 | I99: =I95+I97+I98 -> 11572207 | J99: =J95+J97+J98 -> 15581843 | K99: =K95+K97+K98 -> 16098085 | ... O99: =O95+O97+O98 -> 3.7463953e+08
A101: Discounted Cash Flow | B101: =SUM(D101:O101) -> 1.8767434e+08 | D101: =D99/(1+D96)^D93 -> -16103175 | E101: =E99/(1+E96)^E93 -> -36486792 | F101: =F99/(1+F96)^F93 -> -47356084 | G101: =G99/(1+G96)^G93 -> 3619911.1 | H101: =H99/(1+H96)^H93 -> 6410395.9 | I101: =I99/(1+I96)^I93 -> 8959952 | J101: =J99/(1+J96)^J93 -> 11462680 | K101: =K99/(1+K96)^K93 -> 11251735 | ... O101: =O99/(1+O96)^O93 -> 2.1338822e+08
A102: NPV | B102: =NPV(D96,E99:O99)+D99 -> 1.8767434e+08
A104: Project Level Returns
A105: NPV | B105: =NPV(D96,E99:O99)+D99 -> 1.8767434e+08
A106: IRR | B106: =IRR(D99:O99) -> 0.19380996
A107: Equity Multiple (EM) | B107: =B105/'Project 2'!F20 -> 6.187082
A108: Whole Dollar Profit (WDP) | B108: =B99 -> 3.7457877e+08
A109: % WDP From Development | B109: =B61/B108 -> 0.34260563
A111: Financing Cash Flow | B111: Total
A112: Year | D112: 0 | E112: 1 | F112: 2 | G112: 3 | H112: 4 | I112: 5 | J112: 6 | K112: 7 | L112: 8 | M112: 9 | N112: 10 | O112: 11
A113: Month | D113: 0 | E113: 12 | F113: 24 | G113: 36 | H113: 48 | I113: 60 | J113: 72 | K113: 84 | L113: 96 | M113: 108 | N113: 120 | O113: 132
...
